Workbook

Sheet Index
B1: Index
B3: Sheet | C3: Description
B4: =HYPERLINK("#'Control'!A1","Control") | C4: 핵심 가정과 주요 결과 요약
B5: =HYPERLINK("#'Assumptions'!A1","Assumptions") | C5: 모든 하드코딩 입력값 집중 시트
B6: =HYPERLINK("#'Model'!A1","Model") | C6: HTML D 그래프를 기간별 Excel 수식으로 전개한 계산 시트
B7: =HYPERLINK("#'Formula Audit'!A1","Formula Audit") | C7: 생성된 모든 수식 셀 감사
B8: =HYPERLINK("#'Structure'!A1","Structure") | C8: HTML 노드 ID, parent, formula, description
B9: =HYPERLINK("#'Checks'!A1","Checks") | C9: 수식/구조/정합성 검증
B10: =HYPERLINK("#'Metadata'!A1","Metadata") | C10: 생성 정보

Sheet Assumptions
B1: Assumptions
I3: Historical | J3: Forecast
G4: ID | H4: Unit | I4: 2023 | J4: 2024 | K4: 2025 | L4: 2026 | M4: 2027 | N4: 2028 | O4: 2029
F5: SUV 시장판매대수 | G5: market_suv | H5: 대 | I5: 420000 | J5: 438000 | K5: 456000 | L5: 475000 | M5: 494000 | N5: 514000 | O5: 535000
F6: 이커머스 SUV 점유율 | G6: ec_suv_share | H6: % | I6: 0.018 | J6: 0.019 | K6: 0.02 | L6: 0.021 | M6: 0.022 | N6: 0.023 | O6: 0.024
F7: 이커머스 SUV ASP | G7: ec_suv_asp | H7: 원/대 | I7: 28000000 | J7: 28504000 | K7: 29017072 | L7: 29539379 | M7: 30071088 | N7: 30612368 | O7: 31163390
F8: 대형 시장판매대수 | G8: market_large | H8: 대 | I8: 105000 | J8: 108000 | K8: 111000 | L8: 114000 | M8: 118000 | N8: 121000 | O8: 125000
F9: 이커머스 대형 점유율 | G9: ec_large_share | H9: % | I9: 0.014 | J9: 0.015 | K9: 0.016 | L9: 0.017 | M9: 0.018 | N9: 0.019 | O9: 0.02
F10: 이커머스 대형 ASP | G10: ec_large_asp | H10: 원/대 | I10: 32000000 | J10: 32576000 | K10: 33162368 | L10: 33759291 | M10: 34366958 | N10: 34985563 | O10: 35615303
F11: 중형 시장판매대수 | G11: market_midsize | H11: 대 | I11: 260000 | J11: 267000 | K11: 274000 | L11: 282000 | M11: 290000 | N11: 298000 | O11: 307000
F12: 이커머스 중형 점유율 | G12: ec_midsize_share | H12: % | I12: 0.017 | J12: 0.018 | K12: 0.019 | L12: 0.02 | M12: 0.021 | N12: 0.022 | O12: 0.023
F13: 이커머스 중형 ASP | G13: ec_midsize_asp | H13: 원/대 | I13: 22000000 | J13: 22396000 | K13: 22799128 | L13: 23209512 | M13: 23627284 | N13: 24052575 | O13: 24485521
F14: 준중형 시장판매대수 | G14: market_compact | H14: 대 | I14: 230000 | J14: 234000 | K14: 239000 | L14: 244000 | M14: 249000 | N14: 254000 | O14: 259000
F15: 이커머스 준중형 점유율 | G15: ec_compact_share | H15: % | I15: 0.016 | J15: 0.017 | K15: 0.018 | L15: 0.019 | M15: 0.02 | N15: 0.021 | O15: 0.022
F16: 이커머스 준중형 ASP | G16: ec_compact_asp | H16: 원/대 | I16: 16500000 | J16: 16797000 | K16: 17099346 | L16: 17407134 | M16: 17720463 | N16: 18039431 | O16: 18364141
... F39: 지점내방 기타 ASP | G39: br_other_asp | H39: 원/대 | I39: 14800000 | J39: 15036800 | K39: 15277389 | L39: 15521827 | M39: 15770176 | N39: 16022499 | O39: 16278859
E40: 경매 상품 매출 | G40: auction_product_sales | H40: 원 | I40: 42000000000 | J40: 43680000000 | K40: 45427200000 | L40: 47017152000 | M40: 48662752320 | N40: 50122634890 | O40: 51626313937
E41: 경매 용역 매출 | G41: auction_service_sales | H41: 원 | I41: 9000000000 | J41: 9450000000 | K41: 9922500000 | L41: 10369012500 | M41: 10783773000 | N41: 11161205055 | O41: 11551847232
E42: 렌터카 매각 매출 | G42: rental_disposal_sales | H42: 원 | I42: 36000000000 | J42: 37080000000 | K42: 38192400000 | L42: 39261787200 | M42: 40243331880 | N42: 41249415177 | O42: 42074403481
E43: 장기렌트 매출 | G43: longterm_rental_sales | H43: 원 | I43: 18000000000 | J43: 18810000000 | K43: 19656450000 | L43: 20442708000 | M43: 21219530904 | N43: 21962214486 | O43: 22686967564
F44: 이커머스 용역 매출률 | G44: ecommerce_service_rate | H44: % | I44: 0.008 | J44: 0.0082 | K44: 0.0084 | L44: 0.0086 | M44: 0.0088 | N44: 0.009 | O44: 0.0092
F45: 지점내방 용역 매출률 | G45: branch_service_rate | H45: % | I45: 0.006 | J45: 0.0061 | K45: 0.0062 | L45: 0.0063 | M45: 0.0064 | N45: 0.0065 | O45: 0.0066
E46: 기타 매출 | G46: other_sales | H46: 원 | I46: 12000000000 | J46: 12360000000 | K46: 12730800000 | L46: 13112724000 | M46: 13479880272 | N46: 13857316920 | O46: 14203749843
E47: 중고차 1대당 원가 | G47: unit_inventory_cost | H47: 원/대 | I47: 18000000 | J47: 18270000 | K47: 18544050 | L47: 18822211 | M47: 19104544 | N47: 19391112 | O47: 19681979
E48: 대당 보증비 | G48: warranty_cost_per_unit | H48: 원/대 | I48: 420000 | J48: 427560 | K48: 435256 | L48: 443091 | M48: 451066 | N48: 459186 | O48: 467451
E49: 차량매각원가율 | G49: rental_disposal_cost_rate | H49: % | I49: 0.74 | J49: 0.735 | K49: 0.73 | L49: 0.728 | M49: 0.725 | N49: 0.723 | O49: 0.72
E50: 변동 판관비율 | G50: variable_sga_rate | H50: % | I50: 0.035 | J50: 0.034 | K50: 0.033 | L50: 0.0325 | M50: 0.032 | N50: 0.0315 | O50: 0.031
D51: 고정 판관비 | G51: fixed_sga | H51: 원 | I51: 52000000000 | J51: 53820000000 | K51: 55703700000 | L51: 57541922100 | M51: 59383263607 | N51: 61164761515 | O51: 62999704360
E52: 필요 인원 | G52: employee_count | H52: 명 | I52: 930 | J52: 960 | K52: 990 | L52: 1020 | M52: 1050 | N52: 1080 | O52: 1110
E53: 평균 급여 | G53: avg_salary | H53: 원/명 | I53: 62000000 | J53: 63860000 | K53: 65775800 | L53: 67749074 | M53: 69781546 | N53: 71874993 | O53: 74031242
D54: 감가상각비 | G54: da | H54: 원 | I54: 18500000000 | J54: 18962500000 | K54: 19436562500 | L54: 19903040000 | M54: 20360809920 | N54: 20808747738 | O54: 21266540188
E55: 법인세율 | G55: tax_rate | H55: % | I55: 0.24 | J55: 0.24 | K55: 0.24 | L55: 0.24 | M55: 0.24 | N55: 0.24 | O55: 0.24
E56: 운전자본율 | G56: nwc_rate | H56: % | I56: 0.055 | J56: 0.055 | K56: 0.054 | L56: 0.054 | M56: 0.053 | N56: 0.053 | O56: 0.052
D57: CapEx | G57: capex | H57: 원 | I57: 21000000000 | J57: 21840000000 | K57: 22713600000 | L57: 23576716800 | M57: 24401901888 | N57: 25207164650 | O57: 25963379590
D58: WACC | G58: wacc | H58: % | I58: 0.085 | J58: 0.085 | K58: 0.084 | L58: 0.084 | M58: 0.083 | N58: 0.083 | O58: 0.082
D59: Terminal Growth | G59: terminal_growth | H59: % | I59: 0.02 | J59: 0.02 | K59: 0.02 | L59: 0.02 | M59: 0.02 | N59: 0.02 | O59: 0.02
D60: Discount Factor | G60: discount_factor | H60: x | I60: 0.922 | J60: 0.85 | K60: 0.785 | L60: 0.724 | M60: 0.669 | N60: 0.619 | O60: 0.573
D61: 순차입금 / 조정 | G61: net_debt | H61: 원 | I61: 145000000000 | J61: 140650000000 | K61: 136430500000 | L61: 132337585000 | M61: 128367457450 | N61: 124516433726 | O61: 120780940714
D62: 주식수 | G62: shares_outstanding | H62: 주 | I62: 48200000 | J62: 48200000 | K62: 48200000 | L62: 48200000 | M62: 48200000 | N62: 48200000 | O62: 48200000

Sheet Model
B1: Model
I2: Unit: source units from HTML IR
I3: Historical | J3: Forecast
G4: ID | H4: Unit | I4: 2023 | J4: 2024 | K4: 2025 | L4: 2026 | M4: 2027 | N4: 2028 | O4: 2029
B5: KCar Enterprise Value | G5: root | H5: 원 | I5: =I116 | J5: =J116 | K5: =K116 | L5: =L116 | M5: =M116 | N5: =N116 | O5: =O116
C6: 매출 합계 | G6: rev | H6: 원 | I6: =SUM(I7,I74,I77,I80) | J6: =SUM(J7,J74,J77,J80) | K6: =SUM(K7,K74,K77,K80) | L6: =SUM(L7,L74,L77,L80) | M6: =SUM(M7,M74,M77,M80) | N6: =SUM(N7,N74,N77,N80) | O6: =SUM(O7,O74,O77,O80)
D7: 중고차 판매 | G7: used_car_sales | H7: 원 | I7: =(I8+I44) | J7: =(J8+J44) | K7: =(K8+K44) | L7: =(L8+L44) | M7: =(M8+M44) | N7: =(N8+N44) | O7: =(O8+O44)
E8: 이커머스 중고차 판매 | G8: ecommerce_sales | H8: 원 | I8: =SUM(I9,I14,I19,I24,I29,I34,I39) | J8: =SUM(J9,J14,J19,J24,J29,J34,J39) | K8: =SUM(K9,K14,K19,K24,K29,K34,K39) | L8: =SUM(L9,L14,L19,L24,L29,L34,L39) | M8: =SUM(M9,M14,M19,M24,M29,M34,M39) | N8: =SUM(N9,N14,N19,N24,N29,N34,N39) | O8: =SUM(O9,O14,O19,O24,O29,O34,O39)
F9: 이커머스 SUV | G9: ec_suv_rev | H9: 원 | I9: =(I12*I13) | J9: =(J12*J13) | K9: =(K12*K13) | L9: =(L12*L13) | M9: =(M12*M13) | N9: =(N12*N13) | O9: =(O12*O13)
F10: SUV 시장판매대수 | G10: market_suv | H10: 대 | I10: ='Assumptions'!I5 | J10: ='Assumptions'!J5 | K10: ='Assumptions'!K5 | L10: ='Assumptions'!L5 | M10: ='Assumptions'!M5 | N10: ='Assumptions'!N5 | O10: ='Assumptions'!O5
F11: 이커머스 SUV 점유율 | G11: ec_suv_share | H11: % | I11: ='Assumptions'!I6 | J11: ='Assumptions'!J6 | K11: ='Assumptions'!K6 | L11: ='Assumptions'!L6 | M11: ='Assumptions'!M6 | N11: ='Assumptions'!N6 | O11: ='Assumptions'!O6
F12: 이커머스 SUV 판매대수 | G12: ec_suv_volume | H12: 대 | I12: =(I10*I11) | J12: =(J10*J11) | K12: =(K10*K11) | L12: =(L10*L11) | M12: =(M10*M11) | N12: =(N10*N11) | O12: =(O10*O11)
F13: 이커머스 SUV ASP | G13: ec_suv_asp | H13: 원/대 | I13: ='Assumptions'!I7 | J13: ='Assumptions'!J7 | K13: ='Assumptions'!K7 | L13: ='Assumptions'!L7 | M13: ='Assumptions'!M7 | N13: ='Assumptions'!N7 | O13: ='Assumptions'!O7
F14: 이커머스 대형 | G14: ec_large_rev | H14: 원 | I14: =(I17*I18) | J14: =(J17*J18) | K14: =(K17*K18) | L14: =(L17*L18) | M14: =(M17*M18) | N14: =(N17*N18) | O14: =(O17*O18)
F15: 대형 시장판매대수 | G15: market_large | H15: 대 | I15: ='Assumptions'!I8 | J15: ='Assumptions'!J8 | K15: ='Assumptions'!K8 | L15: ='Assumptions'!L8 | M15: ='Assumptions'!M8 | N15: ='Assumptions'!N8 | O15: ='Assumptions'!O8
F16: 이커머스 대형 점유율 | G16: ec_large_share | H16: % | I16: ='Assumptions'!I9 | J16: ='Assumptions'!J9 | K16: ='Assumptions'!K9 | L16: ='Assumptions'!L9 | M16: ='Assumptions'!M9 | N16: ='Assumptions'!N9 | O16: ='Assumptions'!O9
F17: 이커머스 대형 판매대수 | G17: ec_large_volume | H17: 대 | I17: =(I15*I16) | J17: =(J15*J16) | K17: =(K15*K16) | L17: =(L15*L16) | M17: =(M15*M16) | N17: =(N15*N16) | O17: =(O15*O16)
F18: 이커머스 대형 ASP | G18: ec_large_asp | H18: 원/대 | I18: ='Assumptions'!I10 | J18: ='Assumptions'!J10 | K18: ='Assumptions'!K10 | L18: ='Assumptions'!L10 | M18: ='Assumptions'!M10 | N18: ='Assumptions'!N10 | O18: ='Assumptions'!O10
F19: 이커머스 중형 | G19: ec_midsize_rev | H19: 원 | I19: =(I22*I23) | J19: =(J22*J23) | K19: =(K22*K23) | L19: =(L22*L23) | M19: =(M22*M23) | N19: =(N22*N23) | O19: =(O22*O23)
F20: 중형 시장판매대수 | G20: market_midsize | H20: 대 | I20: ='Assumptions'!I11 | J20: ='Assumptions'!J11 | K20: ='Assumptions'!K11 | L20: ='Assumptions'!L11 | M20: ='Assumptions'!M11 | N20: ='Assumptions'!N11 | O20: ='Assumptions'!O11
F21: 이커머스 중형 점유율 | G21: ec_midsize_share | H21: % | I21: ='Assumptions'!I12 | J21: ='Assumptions'!J12 | K21: ='Assumptions'!K12 | L21: ='Assumptions'!L12 | M21: ='Assumptions'!M12 | N21: ='Assumptions'!N12 | O21: ='Assumptions'!O12
F22: 이커머스 중형 판매대수 | G22: ec_midsize_volume | H22: 대 | I22: =(I20*I21) | J22: =(J20*J21) | K22: =(K20*K21) | L22: =(L20*L21) | M22: =(M20*M21) | N22: =(N20*N21) | O22: =(O20*O21)
F23: 이커머스 중형 ASP | G23: ec_midsize_asp | H23: 원/대 | I23: ='Assumptions'!I13 | J23: ='Assumptions'!J13 | K23: ='Assumptions'!K13 | L23: ='Assumptions'!L13 | M23: ='Assumptions'!M13 | N23: ='Assumptions'!N13 | O23: ='Assumptions'!O13
F24: 이커머스 준중형 | G24: ec_compact_rev | H24: 원 | I24: =(I27*I28) | J24: =(J27*J28) | K24: =(K27*K28) | L24: =(L27*L28) | M24: =(M27*M28) | N24: =(N27*N28) | O24: =(O27*O28)
F25: 준중형 시장판매대수 | G25: market_compact | H25: 대 | I25: ='Assumptions'!I14 | J25: ='Assumptions'!J14 | K25: ='Assumptions'!K14 | L25: ='Assumptions'!L14 | M25: ='Assumptions'!M14 | N25: ='Assumptions'!N14 | O25: ='Assumptions'!O14
F26: 이커머스 준중형 점유율 | G26: ec_compact_share | H26: % | I26: ='Assumptions'!I15 | J26: ='Assumptions'!J15 | K26: ='Assumptions'!K15 | L26: ='Assumptions'!L15 | M26: ='Assumptions'!M15 | N26: ='Assumptions'!N15 | O26: ='Assumptions'!O15
F27: 이커머스 준중형 판매대수 | G27: ec_compact_volume | H27: 대 | I27: =(I25*I26) | J27: =(J25*J26) | K27: =(K25*K26) | L27: =(L25*L26) | M27: =(M25*M26) | N27: =(N25*N26) | O27: =(O25*O26)
F28: 이커머스 준중형 ASP | G28: ec_compact_asp | H28: 원/대 | I28: ='Assumptions'!I16 | J28: ='Assumptions'!J16 | K28: ='Assumptions'!K16 | L28: ='Assumptions'!L16 | M28: ='Assumptions'!M16 | N28: ='Assumptions'!N16 | O28: ='Assumptions'!O16
F29: 이커머스 소형 | G29: ec_small_rev | H29: 원 | I29: =(I32*I33) | J29: =(J32*J33) | K29: =(K32*K33) | L29: =(L32*L33) | M29: =(M32*M33) | N29: =(N32*N33) | O29: =(O32*O33)
F30: 소형 시장판매대수 | G30: market_small | H30: 대 | I30: ='Assumptions'!I17 | J30: ='Assumptions'!J17 | K30: ='Assumptions'!K17 | L30: ='Assumptions'!L17 | M30: ='Assumptions'!M17 | N30: ='Assumptions'!N17 | O30: ='Assumptions'!O17
F31: 이커머스 소형 점유율 | G31: ec_small_share | H31: % | I31: ='Assumptions'!I18 | J31: ='Assumptions'!J18 | K31: ='Assumptions'!K18 | L31: ='Assumptions'!L18 | M31: ='Assumptions'!M18 | N31: ='Assumptions'!N18 | O31: ='Assumptions'!O18
F32: 이커머스 소형 판매대수 | G32: ec_small_volume | H32: 대 | I32: =(I30*I31) | J32: =(J30*J31) | K32: =(K30*K31) | L32: =(L30*L31) | M32: =(M30*M31) | N32: =(N30*N31) | O32: =(O30*O31)
F33: 이커머스 소형 ASP | G33: ec_small_asp | H33: 원/대 | I33: ='Assumptions'!I19 | J33: ='Assumptions'!J19 | K33: ='Assumptions'!K19 | L33: ='Assumptions'!L19 | M33: ='Assumptions'!M19 | N33: ='Assumptions'!N19 | O33: ='Assumptions'!O19
F34: 이커머스 화물차 | G34: ec_truck_rev | H34: 원 | I34: =(I37*I38) | J34: =(J37*J38) | K34: =(K37*K38) | L34: =(L37*L38) | M34: =(M37*M38) | N34: =(N37*N38) | O34: =(O37*O38)
F35: 화물차 시장판매대수 | G35: market_truck | H35: 대 | I35: ='Assumptions'!I20 | J35: ='Assumptions'!J20 | K35: ='Assumptions'!K20 | L35: ='Assumptions'!L20 | M35: ='Assumptions'!M20 | N35: ='Assumptions'!N20 | O35: ='Assumptions'!O20
F36: 이커머스 화물차 점유율 | G36: ec_truck_share | H36: % | I36: ='Assumptions'!I21 | J36: ='Assumptions'!J21 | K36: ='Assumptions'!K21 | L36: ='Assumptions'!L21 | M36: ='Assumptions'!M21 | N36: ='Assumptions'!N21 | O36: ='Assumptions'!O21
F37: 이커머스 화물차 판매대수 | G37: ec_truck_volume | H37: 대 | I37: =(I35*I36) | J37: =(J35*J36) | K37: =(K35*K36) | L37: =(L35*L36) | M37: =(M35*M36) | N37: =(N35*N36) | O37: =(O35*O36)
F38: 이커머스 화물차 ASP | G38: ec_truck_asp | H38: 원/대 | I38: ='Assumptions'!I22 | J38: ='Assumptions'!J22 | K38: ='Assumptions'!K22 | L38: ='Assumptions'!L22 | M38: ='Assumptions'!M22 | N38: ='Assumptions'!N22 | O38: ='Assumptions'!O22
F39: 이커머스 기타 | G39: ec_other_rev | H39: 원 | I39: =(I42*I43) | J39: =(J42*J43) | K39: =(K42*K43) | L39: =(L42*L43) | M39: =(M42*M43) | N39: =(N42*N43) | O39: =(O42*O43)
F40: 기타 시장판매대수 | G40: market_other | H40: 대 | I40: ='Assumptions'!I23 | J40: ='Assumptions'!J23 | K40: ='Assumptions'!K23 | L40: ='Assumptions'!L23 | M40: ='Assumptions'!M23 | N40: ='Assumptions'!N23 | O40: ='Assumptions'!O23
F41: 이커머스 기타 점유율 | G41: ec_other_share | H41: % | I41: ='Assumptions'!I24 | J41: ='Assumptions'!J24 | K41: ='Assumptions'!K24 | L41: ='Assumptions'!L24 | M41: ='Assumptions'!M24 | N41: ='Assumptions'!N24 | O41: ='Assumptions'!O24
F42: 이커머스 기타 판매대수 | G42: ec_other_volume | H42: 대 | I42: =(I40*I41) | J42: =(J40*J41) | K42: =(K40*K41) | L42: =(L40*L41) | M42: =(M40*M41) | N42: =(N40*N41) | O42: =(O40*O41)
F43: 이커머스 기타 ASP | G43: ec_other_asp | H43: 원/대 | I43: ='Assumptions'!I25 | J43: ='Assumptions'!J25 | K43: ='Assumptions'!K25 | L43: ='Assumptions'!L25 | M43: ='Assumptions'!M25 | N43: ='Assumptions'!N25 | O43: ='Assumptions'!O25
E44: 지점내방 중고차 판매 | G44: branch_sales | H44: 원 | I44: =SUM(I45,I49,I53,I57,I61,I65,I69) | J44: =SUM(J45,J49,J53,J57,J61,J65,J69) | K44: =SUM(K45,K49,K53,K57,K61,K65,K69) | L44: =SUM(L45,L49,L53,L57,L61,L65,L69) | M44: =SUM(M45,M49,M53,M57,M61,M65,M69) | N44: =SUM(N45,N49,N53,N57,N61,N65,N69) | O44: =SUM(O45,O49,O53,O57,O61,O65,O69)
F45: 지점내방 SUV | G45: br_suv_rev | H45: 원 | I45: =(I47*I48) | J45: =(J47*J48) | K45: =(K47*K48) | L45: =(L47*L48) | M45: =(M47*M48) | N45: =(N47*N48) | O45: =(O47*O48)
F46: 지점내방 SUV 점유율 | G46: br_suv_share | H46: % | I46: ='Assumptions'!I26 | J46: ='Assumptions'!J26 | K46: ='Assumptions'!K26 | L46: ='Assumptions'!L26 | M46: ='Assumptions'!M26 | N46: ='Assumptions'!N26 | O46: ='Assumptions'!O26
F47: 지점내방 SUV 판매대수 | G47: br_suv_volume | H47: 대 | I47: =(I10*I46) | J47: =(J10*J46) | K47: =(K10*K46) | L47: =(L10*L46) | M47: =(M10*M46) | N47: =(N10*N46) | O47: =(O10*O46)
F48: 지점내방 SUV ASP | G48: br_suv_asp | H48: 원/대 | I48: ='Assumptions'!I27 | J48: ='Assumptions'!J27 | K48: ='Assumptions'!K27 | L48: ='Assumptions'!L27 | M48: ='Assumptions'!M27 | N48: ='Assumptions'!N27 | O48: ='Assumptions'!O27
F49: 지점내방 대형 | G49: br_large_rev | H49: 원 | I49: =(I51*I52) | J49: =(J51*J52) | K49: =(K51*K52) | L49: =(L51*L52) | M49: =(M51*M52) | N49: =(N51*N52) | O49: =(O51*O52)
F50: 지점내방 대형 점유율 | G50: br_large_share | H50: % | I50: ='Assumptions'!I28 | J50: ='Assumptions'!J28 | K50: ='Assumptions'!K28 | L50: ='Assumptions'!L28 | M50: ='Assumptions'!M28 | N50: ='Assumptions'!N28 | O50: ='Assumptions'!O28
F51: 지점내방 대형 판매대수 | G51: br_large_volume | H51: 대 | I51: =(I15*I50) | J51: =(J15*J50) | K51: =(K15*K50) | L51: =(L15*L50) | M51: =(M15*M50) | N51: =(N15*N50) | O51: =(O15*O50)
F52: 지점내방 대형 ASP | G52: br_large_asp | H52: 원/대 | I52: ='Assumptions'!I29 | J52: ='Assumptions'!J29 | K52: ='Assumptions'!K29 | L52: ='Assumptions'!L29 | M52: ='Assumptions'!M29 | N52: ='Assumptions'!N29 | O52: ='Assumptions'!O29
F53: 지점내방 중형 | G53: br_midsize_rev | H53: 원 | I53: =(I55*I56) | J53: =(J55*J56) | K53: =(K55*K56) | L53: =(L55*L56) | M53: =(M55*M56) | N53: =(N55*N56) | O53: =(O55*O56)
F54: 지점내방 중형 점유율 | G54: br_midsize_share | H54: % | I54: ='Assumptions'!I30 | J54: ='Assumptions'!J30 | K54: ='Assumptions'!K30 | L54: ='Assumptions'!L30 | M54: ='Assumptions'!M30 | N54: ='Assumptions'!N30 | O54: ='Assumptions'!O30
F55: 지점내방 중형 판매대수 | G55: br_midsize_volume | H55: 대 | I55: =(I20*I54) | J55: =(J20*J54) | K55: =(K20*K54) | L55: =(L20*L54) | M55: =(M20*M54) | N55: =(N20*N54) | O55: =(O20*O54)
F56: 지점내방 중형 ASP | G56: br_midsize_asp | H56: 원/대 | I56: ='Assumptions'!I31 | J56: ='Assumptions'!J31 | K56: ='Assumptions'!K31 | L56: ='Assumptions'!L31 | M56: ='Assumptions'!M31 | N56: ='Assumptions'!N31 | O56: ='Assumptions'!O31
F57: 지점내방 준중형 | G57: br_compact_rev | H57: 원 | I57: =(I59*I60) | J57: =(J59*J60) | K57: =(K59*K60) | L57: =(L59*L60) | M57: =(M59*M60) | N57: =(N59*N60) | O57: =(O59*O60)
F58: 지점내방 준중형 점유율 | G58: br_compact_share | H58: % | I58: ='Assumptions'!I32 | J58: ='Assumptions'!J32 | K58: ='Assumptions'!K32 | L58: ='Assumptions'!L32 | M58: ='Assumptions'!M32 | N58: ='Assumptions'!N32 | O58: ='Assumptions'!O32
F59: 지점내방 준중형 판매대수 | G59: br_compact_volume | H59: 대 | I59: =(I25*I58) | J59: =(J25*J58) | K59: =(K25*K58) | L59: =(L25*L58) | M59: =(M25*M58) | N59: =(N25*N58) | O59: =(O25*O58)
F60: 지점내방 준중형 ASP | G60: br_compact_asp | H60: 원/대 | I60: ='Assumptions'!I33 | J60: ='Assumptions'!J33 | K60: ='Assumptions'!K33 | L60: ='Assumptions'!L33 | M60: ='Assumptions'!M33 | N60: ='Assumptions'!N33 | O60: ='Assumptions'!O33
F61: 지점내방 소형 | G61: br_small_rev | H61: 원 | I61: =(I63*I64) | J61: =(J63*J64) | K61: =(K63*K64) | L61: =(L63*L64) | M61: =(M63*M64) | N61: =(N63*N64) | O61: =(O63*O64)
F62: 지점내방 소형 점유율 | G62: br_small_share | H62: % | I62: ='Assumptions'!I34 | J62: ='Assumptions'!J34 | K62: ='Assumptions'!K34 | L62: ='Assumptions'!L34 | M62: ='Assumptions'!M34 | N62: ='Assumptions'!N34 | O62: ='Assumptions'!O34
F63: 지점내방 소형 판매대수 | G63: br_small_volume | H63: 대 | I63: =(I30*I62) | J63: =(J30*J62) | K63: =(K30*K62) | L63: =(L30*L62) | M63: =(M30*M62) | N63: =(N30*N62) | O63: =(O30*O62)
F64: 지점내방 소형 ASP | G64: br_small_asp | H64: 원/대 | I64: ='Assumptions'!I35 | J64: ='Assumptions'!J35 | K64: ='Assumptions'!K35 | L64: ='Assumptions'!L35 | M64: ='Assumptions'!M35 | N64: ='Assumptions'!N35 | O64: ='Assumptions'!O35
F65: 지점내방 화물차 | G65: br_truck_rev | H65: 원 | I65: =(I67*I68) | J65: =(J67*J68) | K65: =(K67*K68) | L65: =(L67*L68) | M65: =(M67*M68) | N65: =(N67*N68) | O65: =(O67*O68)
F66: 지점내방 화물차 점유율 | G66: br_truck_share | H66: % | I66: ='Assumptions'!I36 | J66: ='Assumptions'!J36 | K66: ='Assumptions'!K36 | L66: ='Assumptions'!L36 | M66: ='Assumptions'!M36 | N66: ='Assumptions'!N36 | O66: ='Assumptions'!O36
F67: 지점내방 화물차 판매대수 | G67: br_truck_volume | H67: 대 | I67: =(I35*I66) | J67: =(J35*J66) | K67: =(K35*K66) | L67: =(L35*L66) | M67: =(M35*M66) | N67: =(N35*N66) | O67: =(O35*O66)
F68: 지점내방 화물차 ASP | G68: br_truck_asp | H68: 원/대 | I68: ='Assumptions'!I37 | J68: ='Assumptions'!J37 | K68: ='Assumptions'!K37 | L68: ='Assumptions'!L37 | M68: ='Assumptions'!M37 | N68: ='Assumptions'!N37 | O68: ='Assumptions'!O37
F69: 지점내방 기타 | G69: br_other_rev | H69: 원 | I69: =(I71*I72) | J69: =(J71*J72) | K69: =(K71*K72) | L69: =(L71*L72) | M69: =(M71*M72) | N69: =(N71*N72) | O69: =(O71*O72)
F70: 지점내방 기타 점유율 | G70: br_other_share | H70: % | I70: ='Assumptions'!I38 | J70: ='Assumptions'!J38 | K70: ='Assumptions'!K38 | L70: ='Assumptions'!L38 | M70: ='Assumptions'!M38 | N70: ='Assumptions'!N38 | O70: ='Assumptions'!O38
F71: 지점내방 기타 판매대수 | G71: br_other_volume | H71: 대 | I71: =(I40*I70) | J71: =(J40*J70) | K71: =(K40*K70) | L71: =(L40*L70) | M71: =(M40*M70) | N71: =(N40*N70) | O71: =(O40*O70)
F72: 지점내방 기타 ASP | G72: br_other_asp | H72: 원/대 | I72: ='Assumptions'!I39 | J72: ='Assumptions'!J39 | K72: ='Assumptions'!K39 | L72: ='Assumptions'!L39 | M72: ='Assumptions'!M39 | N72: ='Assumptions'!N39 | O72: ='Assumptions'!O39
E73: 중고차 판매대수 | G73: used_car_volume | H73: 대 | I73: =SUM(I12,I17,I22,I27,I32,I37,I42,I47,I51,I55,I59,I63,I67,I71) | J73: =SUM(J12,J17,J22,J27,J32,J37,J42,J47,J51,J55,J59,J63,J67,J71) | K73: =SUM(K12,K17,K22,K27,K32,K37,K42,K47,K51,K55,K59,K63,K67,K71) | L73: =SUM(L12,L17,L22,L27,L32,L37,L42,L47,L51,L55,L59,L63,L67,L71) | M73: =SUM(M12,M17,M22,M27,M32,M37,M42,M47,M51,M55,M59,M63,M67,M71) | N73: =SUM(N12,N17,N22,N27,N32,N37,N42,N47,N51,N55,N59,N63,N67,N71) | O73: =SUM(O12,O17,O22,O27,O32,O37,O42,O47,O51,O55,O59,O63,O67,O71)
D74: 경매 매출 | G74: auction_sales | H74: 원 | I74: =(I75+I76) | J74: =(J75+J76) | K74: =(K75+K76) | L74: =(L75+L76) | M74: =(M75+M76) | N74: =(N75+N76) | O74: =(O75+O76)
E75: 경매 상품 매출 | G75: auction_product_sales | H75: 원 | I75: ='Assumptions'!I40 | J75: ='Assumptions'!J40 | K75: ='Assumptions'!K40 | L75: ='Assumptions'!L40 | M75: ='Assumptions'!M40 | N75: ='Assumptions'!N40 | O75: ='Assumptions'!O40
E76: 경매 용역 매출 | G76: auction_service_sales | H76: 원 | I76: ='Assumptions'!I41 | J76: ='Assumptions'!J41 | K76: ='Assumptions'!K41 | L76: ='Assumptions'!L41 | M76: ='Assumptions'!M41 | N76: ='Assumptions'!N41 | O76: ='Assumptions'!O41
D77: 렌터카 매출 | G77: rental_sales | H77: 원 | I77: =(I78+I79) | J77: =(J78+J79) | K77: =(K78+K79) | L77: =(L78+L79) | M77: =(M78+M79) | N77: =(N78+N79) | O77: =(O78+O79)
E78: 렌터카 매각 매출 | G78: rental_disposal_sales | H78: 원 | I78: ='Assumptions'!I42 | J78: ='Assumptions'!J42 | K78: ='Assumptions'!K42 | L78: ='Assumptions'!L42 | M78: ='Assumptions'!M42 | N78: ='Assumptions'!N42 | O78: ='Assumptions'!O42
E79: 장기렌트 매출 | G79: longterm_rental_sales | H79: 원 | I79: ='Assumptions'!I43 | J79: ='Assumptions'!J43 | K79: ='Assumptions'!K43 | L79: ='Assumptions'!L43 | M79: ='Assumptions'!M43 | N79: ='Assumptions'!N43 | O79: ='Assumptions'!O43
D80: 용역 / 기타 매출 | G80: service_other_sales | H80: 원 | I80: =((I81+I83)+I85) | J80: =((J81+J83)+J85) | K80: =((K81+K83)+K85) | L80: =((L81+L83)+L85) | M80: =((M81+M83)+M85) | N80: =((N81+N83)+N85) | O80: =((O81+O83)+O85)
E81: 이커머스 용역 매출 | G81: ecommerce_service_sales | H81: 원 | I81: =(I8*I82) | J81: =(J8*J82) | K81: =(K8*K82) | L81: =(L8*L82) | M81: =(M8*M82) | N81: =(N8*N82) | O81: =(O8*O82)
F82: 이커머스 용역 매출률 | G82: ecommerce_service_rate | H82: % | I82: ='Assumptions'!I44 | J82: ='Assumptions'!J44 | K82: ='Assumptions'!K44 | L82: ='Assumptions'!L44 | M82: ='Assumptions'!M44 | N82: ='Assumptions'!N44 | O82: ='Assumptions'!O44
E83: 지점내방 용역 매출 | G83: branch_service_sales | H83: 원 | I83: =(I44*I84) | J83: =(J44*J84) | K83: =(K44*K84) | L83: =(L44*L84) | M83: =(M44*M84) | N83: =(N44*N84) | O83: =(O44*O84)
F84: 지점내방 용역 매출률 | G84: branch_service_rate | H84: % | I84: ='Assumptions'!I45 | J84: ='Assumptions'!J45 | K84: ='Assumptions'!K45 | L84: ='Assumptions'!L45 | M84: ='Assumptions'!M45 | N84: ='Assumptions'!N45 | O84: ='Assumptions'!O45
E85: 기타 매출 | G85: other_sales | H85: 원 | I85: ='Assumptions'!I46 | J85: ='Assumptions'!J46 | K85: ='Assumptions'!K46 | L85: ='Assumptions'!L46 | M85: ='Assumptions'!M46 | N85: ='Assumptions'!N46 | O85: ='Assumptions'!O46
C86: 비용 합계 | G86: total_cost | H86: 원 | I86: =SUM(I87,I89,I91,I93,I95,I96,I99) | J86: =SUM(J87,J89,J91,J93,J95,J96,J99) | K86: =SUM(K87,K89,K91,K93,K95,K96,K99) | L86: =SUM(L87,L89,L91,L93,L95,L96,L99) | M86: =SUM(M87,M89,M91,M93,M95,M96,M99) | N86: =SUM(N87,N89,N91,N93,N95,N96,N99) | O86: =SUM(O87,O89,O91,O93,O95,O96,O99)
D87: 재고자산원가 | G87: inventory_cost | H87: 원 | I87: =(I73*I88) | J87: =(J73*J88) | K87: =(K73*K88) | L87: =(L73*L88) | M87: =(M73*M88) | N87: =(N73*N88) | O87: =(O73*O88)
E88: 중고차 1대당 원가 | G88: unit_inventory_cost | H88: 원/대 | I88: ='Assumptions'!I47 | J88: ='Assumptions'!J47 | K88: ='Assumptions'!K47 | L88: ='Assumptions'!L47 | M88: ='Assumptions'!M47 | N88: ='Assumptions'!N47 | O88: ='Assumptions'!O47
D89: 판매보증비 | G89: warranty_cost | H89: 원 | I89: =(I73*I90) | J89: =(J73*J90) | K89: =(K73*K90) | L89: =(L73*L90) | M89: =(M73*M90) | N89: =(N73*N90) | O89: =(O73*O90)
E90: 대당 보증비 | G90: warranty_cost_per_unit | H90: 원/대 | I90: ='Assumptions'!I48 | J90: ='Assumptions'!J48 | K90: ='Assumptions'!K48 | L90: ='Assumptions'!L48 | M90: ='Assumptions'!M48 | N90: ='Assumptions'!N48 | O90: ='Assumptions'!O48
D91: 차량매각원가 | G91: rental_car_cost | H91: 원 | I91: =(I78*I92) | J91: =(J78*J92) | K91: =(K78*K92) | L91: =(L78*L92) | M91: =(M78*M92) | N91: =(N78*N92) | O91: =(O78*O92)
E92: 차량매각원가율 | G92: rental_disposal_cost_rate | H92: % | I92: ='Assumptions'!I49 | J92: ='Assumptions'!J49 | K92: ='Assumptions'!K49 | L92: ='Assumptions'!L49 | M92: ='Assumptions'!M49 | N92: ='Assumptions'!N49 | O92: ='Assumptions'!O49
D93: 변동 판관비 | G93: variable_sga | H93: 원 | I93: =(I6*I94) | J93: =(J6*J94) | K93: =(K6*K94) | L93: =(L6*L94) | M93: =(M6*M94) | N93: =(N6*N94) | O93: =(O6*O94)
E94: 변동 판관비율 | G94: variable_sga_rate | H94: % | I94: ='Assumptions'!I50 | J94: ='Assumptions'!J50 | K94: ='Assumptions'!K50 | L94: ='Assumptions'!L50 | M94: ='Assumptions'!M50 | N94: ='Assumptions'!N50 | O94: ='Assumptions'!O50
D95: 고정 판관비 | G95: fixed_sga | H95: 원 | I95: ='Assumptions'!I51 | J95: ='Assumptions'!J51 | K95: ='Assumptions'!K51 | L95: ='Assumptions'!L51 | M95: ='Assumptions'!M51 | N95: ='Assumptions'!N51 | O95: ='Assumptions'!O51
D96: 인건비 | G96: labor_cost | H96: 원 | I96: =(I97*I98) | J96: =(J97*J98) | K96: =(K97*K98) | L96: =(L97*L98) | M96: =(M97*M98) | N96: =(N97*N98) | O96: =(O97*O98)
E97: 필요 인원 | G97: employee_count | H97: 명 | I97: ='Assumptions'!I52 | J97: ='Assumptions'!J52 | K97: ='Assumptions'!K52 | L97: ='Assumptions'!L52 | M97: ='Assumptions'!M52 | N97: ='Assumptions'!N52 | O97: ='Assumptions'!O52
E98: 평균 급여 | G98: avg_salary | H98: 원/명 | I98: ='Assumptions'!I53 | J98: ='Assumptions'!J53 | K98: ='Assumptions'!K53 | L98: ='Assumptions'!L53 | M98: ='Assumptions'!M53 | N98: ='Assumptions'!N53 | O98: ='Assumptions'!O53
D99: 감가상각비 | G99: da | H99: 원 | I99: ='Assumptions'!I54 | J99: ='Assumptions'!J54 | K99: ='Assumptions'!K54 | L99: ='Assumptions'!L54 | M99: ='Assumptions'!M54 | N99: ='Assumptions'!N54 | O99: ='Assumptions'!O54
C100: 영업이익 | G100: op_profit | H100: 원 | I100: =(I6-I86) | J100: =(J6-J86) | K100: =(K6-K86) | L100: =(L6-L86) | M100: =(M6-M86) | N100: =(N6-N86) | O100: =(O6-O86)
...

Sheet Control
B1: Control
I3: Historical | J3: Forecast
B4: Output | C4: ID | I4: 2023 | J4: 2024 | K4: 2025 | L4: 2026 | M4: 2027 | N4: 2028 | O4: 2029
B5: KCar Enterprise Value | C5: root | I5: ='Model'!I5 | J5: ='Model'!J5 | K5: ='Model'!K5 | L5: ='Model'!L5 | M5: ='Model'!M5 | N5: ='Model'!N5 | O5: ='Model'!O5
B6: 매출 합계 | C6: rev | I6: ='Model'!I6 | J6: ='Model'!J6 | K6: ='Model'!K6 | L6: ='Model'!L6 | M6: ='Model'!M6 | N6: ='Model'!N6 | O6: ='Model'!O6
B7: 중고차 판매 | C7: used_car_sales | I7: ='Model'!I7 | J7: ='Model'!J7 | K7: ='Model'!K7 | L7: ='Model'!L7 | M7: ='Model'!M7 | N7: ='Model'!N7 | O7: ='Model'!O7
B8: 이커머스 중고차 판매 | C8: ecommerce_sales | I8: ='Model'!I8 | J8: ='Model'!J8 | K8: ='Model'!K8 | L8: ='Model'!L8 | M8: ='Model'!M8 | N8: ='Model'!N8 | O8: ='Model'!O8
B9: 지점내방 중고차 판매 | C9: branch_sales | I9: ='Model'!I44 | J9: ='Model'!J44 | K9: ='Model'!K44 | L9: ='Model'!L44 | M9: ='Model'!M44 | N9: ='Model'!N44 | O9: ='Model'!O44
B10: 비용 합계 | C10: total_cost | I10: ='Model'!I86 | J10: ='Model'!J86 | K10: ='Model'!K86 | L10: ='Model'!L86 | M10: ='Model'!M86 | N10: ='Model'!N86 | O10: ='Model'!O86
B11: 영업이익 | C11: op_profit | I11: ='Model'!I100 | J11: ='Model'!J100 | K11: ='Model'!K100 | L11: ='Model'!L100 | M11: ='Model'!M100 | N11: ='Model'!N100 | O11: ='Model'!O100
B12: FCFF | C12: fcff | I12: ='Model'!I101 | J12: ='Model'!J101 | K12: ='Model'!K101 | L12: ='Model'!L101 | M12: ='Model'!M101 | N12: ='Model'!N101 | O12: ='Model'!O101
B13: Enterprise Value | C13: enterprise_value | I13: ='Model'!I116 | J13: ='Model'!J116 | K13: ='Model'!K116 | L13: ='Model'!L116 | M13: ='Model'!M116 | N13: ='Model'!N116 | O13: ='Model'!O116
B14: Equity Value | C14: equity_value | I14: ='Model'!I118 | J14: ='Model'!J118 | K14: ='Model'!K118 | L14: ='Model'!L118 | M14: ='Model'!M118 | N14: ='Model'!N118 | O14: ='Model'!O118
B15: 주당가치 | C15: value_per_share | I15: ='Model'!I120 | J15: ='Model'!J120 | K15: ='Model'!K120 | L15: ='Model'!L120 | M15: ='Model'!M120 | N15: ='Model'!N120 | O15: ='Model'!O120
B16: Valuation | C16: valuation | I16: ='Model'!I109 | J16: ='Model'!J109 | K16: ='Model'!K109 | L16: ='Model'!L109 | M16: ='Model'!M109 | N16: ='Model'!N109 | O16: ='Model'!O109
B17: 이커머스 SUV | C17: ec_suv_rev | I17: ='Model'!I9 | J17: ='Model'!J9 | K17: ='Model'!K9 | L17: ='Model'!L9 | M17: ='Model'!M9 | N17: ='Model'!N9 | O17: ='Model'!O9
B18: 이커머스 SUV 판매대수 | C18: ec_suv_volume | I18: ='Model'!I12 | J18: ='Model'!J12 | K18: ='Model'!K12 | L18: ='Model'!L12 | M18: ='Model'!M12 | N18: ='Model'!N12 | O18: ='Model'!O12
B19: 이커머스 대형 | C19: ec_large_rev | I19: ='Model'!I14 | J19: ='Model'!J14 | K19: ='Model'!K14 | L19: ='Model'!L14 | M19: ='Model'!M14 | N19: ='Model'!N14 | O19: ='Model'!O14
B20: 이커머스 대형 판매대수 | C20: ec_large_volume | I20: ='Model'!I17 | J20: ='Model'!J17 | K20: ='Model'!K17 | L20: ='Model'!L17 | M20: ='Model'!M17 | N20: ='Model'!N17 | O20: ='Model'!O17
B21: 이커머스 중형 | C21: ec_midsize_rev | I21: ='Model'!I19 | J21: ='Model'!J19 | K21: ='Model'!K19 | L21: ='Model'!L19 | M21: ='Model'!M19 | N21: ='Model'!N19 | O21: ='Model'!O19
B22: 이커머스 중형 판매대수 | C22: ec_midsize_volume | I22: ='Model'!I22 | J22: ='Model'!J22 | K22: ='Model'!K22 | L22: ='Model'!L22 | M22: ='Model'!M22 | N22: ='Model'!N22 | O22: ='Model'!O22
B23: 이커머스 준중형 | C23: ec_compact_rev | I23: ='Model'!I24 | J23: ='Model'!J24 | K23: ='Model'!K24 | L23: ='Model'!L24 | M23: ='Model'!M24 | N23: ='Model'!N24 | O23: ='Model'!O24
B24: 이커머스 준중형 판매대수 | C24: ec_compact_volume | I24: ='Model'!I27 | J24: ='Model'!J27 | K24: ='Model'!K27 | L24: ='Model'!L27 | M24: ='Model'!M27 | N24: ='Model'!N27 | O24: ='Model'!O27
B25: 이커머스 소형 | C25: ec_small_rev | I25: ='Model'!I29 | J25: ='Model'!J29 | K25: ='Model'!K29 | L25: ='Model'!L29 | M25: ='Model'!M29 | N25: ='Model'!N29 | O25: ='Model'!O29
B26: 이커머스 소형 판매대수 | C26: ec_small_volume | I26: ='Model'!I32 | J26: ='Model'!J32 | K26: ='Model'!K32 | L26: ='Model'!L32 | M26: ='Model'!M32 | N26: ='Model'!N32 | O26: ='Model'!O32
B27: 이커머스 화물차 | C27: ec_truck_rev | I27: ='Model'!I34 | J27: ='Model'!J34 | K27: ='Model'!K34 | L27: ='Model'!L34 | M27: ='Model'!M34 | N27: ='Model'!N34 | O27: ='Model'!O34
B28: 이커머스 화물차 판매대수 | C28: ec_truck_volume | I28: ='Model'!I37 | J28: ='Model'!J37 | K28: ='Model'!K37 | L28: ='Model'!L37 | M28: ='Model'!M37 | N28: ='Model'!N37 | O28: ='Model'!O37

Sheet Formula Audit
B1: Formula Audit
B3: Sheet | C3: ID | D3: Label | E3: Year | F3: Cell | G3: Formula | H3: Type
B4: Model | C4: root | D4: KCar Enterprise Value | E4: 2023 | F4: I5 | G4: =I116 | H4: calculation
B5: Model | C5: root | D5: KCar Enterprise Value | E5: 2024 | F5: J5 | G5: =J116 | H5: calculation
B6: Model | C6: root | D6: KCar Enterprise Value | E6: 2025 | F6: K5 | G6: =K116 | H6: calculation
B7: Model | C7: root | D7: KCar Enterprise Value | E7: 2026 | F7: L5 | G7: =L116 | H7: calculation
B8: Model | C8: root | D8: KCar Enterprise Value | E8: 2027 | F8: M5 | G8: =M116 | H8: calculation
B9: Model | C9: root | D9: KCar Enterprise Value | E9: 2028 | F9: N5 | G9: =N116 | H9: calculation
B10: Model | C10: root | D10: KCar Enterprise Value | E10: 2029 | F10: O5 | G10: =O116 | H10: calculation
B11: Model | C11: rev | D11: 매출 합계 | E11: 2023 | F11: I6 | G11: =SUM(I7,I74,I77,I80) | H11: calculation
B12: Model | C12: rev | D12: 매출 합계 | E12: 2024 | F12: J6 | G12: =SUM(J7,J74,J77,J80) | H12: calculation
B13: Model | C13: rev | D13: 매출 합계 | E13: 2025 | F13: K6 | G13: =SUM(K7,K74,K77,K80) | H13: calculation
B14: Model | C14: rev | D14: 매출 합계 | E14: 2026 | F14: L6 | G14: =SUM(L7,L74,L77,L80) | H14: calculation
B15: Model | C15: rev | D15: 매출 합계 | E15: 2027 | F15: M6 | G15: =SUM(M7,M74,M77,M80) | H15: calculation
B16: Model | C16: rev | D16: 매출 합계 | E16: 2028 | F16: N6 | G16: =SUM(N7,N74,N77,N80) | H16: calculation
B17: Model | C17: rev | D17: 매출 합계 | E17: 2029 | F17: O6 | G17: =SUM(O7,O74,O77,O80) | H17: calculation
B18: Model | C18: used_car_sales | D18: 중고차 판매 | E18: 2023 | F18: I7 | G18: =(I8+I44) | H18: calculation
B19: Model | C19: used_car_sales | D19: 중고차 판매 | E19: 2024 | F19: J7 | G19: =(J8+J44) | H19: calculation
B20: Model | C20: used_car_sales | D20: 중고차 판매 | E20: 2025 | F20: K7 | G20: =(K8+K44) | H20: calculation
B21: Model | C21: used_car_sales | D21: 중고차 판매 | E21: 2026 | F21: L7 | G21: =(L8+L44) | H21: calculation
B22: Model | C22: used_car_sales | D22: 중고차 판매 | E22: 2027 | F22: M7 | G22: =(M8+M44) | H22: calculation
B23: Model | C23: used_car_sales | D23: 중고차 판매 | E23: 2028 | F23: N7 | G23: =(N8+N44) | H23: calculation
B24: Model | C24: used_car_sales | D24: 중고차 판매 | E24: 2029 | F24: O7 | G24: =(O8+O44) | H24: calculation
B25: Model | C25: ecommerce_sales | D25: 이커머스 중고차 판매 | E25: 2023 | F25: I8 | G25: =SUM(I9,I14,I19,I24,I29,I34,I39) | H25: calculation
B26: Model | C26: ecommerce_sales | D26: 이커머스 중고차 판매 | E26: 2024 | F26: J8 | G26: =SUM(J9,J14,J19,J24,J29,J34,J39) | H26: calculation
B27: Model | C27: ecommerce_sales | D27: 이커머스 중고차 판매 | E27: 2025 | F27: K8 | G27: =SUM(K9,K14,K19,K24,K29,K34,K39) | H27: calculation
B28: Model | C28: ecommerce_sales | D28: 이커머스 중고차 판매 | E28: 2026 | F28: L8 | G28: =SUM(L9,L14,L19,L24,L29,L34,L39) | H28: calculation
B29: Model | C29: ecommerce_sales | D29: 이커머스 중고차 판매 | E29: 2027 | F29: M8 | G29: =SUM(M9,M14,M19,M24,M29,M34,M39) | H29: calculation
B30: Model | C30: ecommerce_sales | D30: 이커머스 중고차 판매 | E30: 2028 | F30: N8 | G30: =SUM(N9,N14,N19,N24,N29,N34,N39) | H30: calculation
B31: Model | C31: ecommerce_sales | D31: 이커머스 중고차 판매 | E31: 2029 | F31: O8 | G31: =SUM(O9,O14,O19,O24,O29,O34,O39) | H31: calculation
B32: Model | C32: ec_suv_rev | D32: 이커머스 SUV | E32: 2023 | F32: I9 | G32: =(I12*I13) | H32: calculation
B33: Model | C33: ec_suv_rev | D33: 이커머스 SUV | E33: 2024 | F33: J9 | G33: =(J12*J13) | H33: calculation
B34: Model | C34: ec_suv_rev | D34: 이커머스 SUV | E34: 2025 | F34: K9 | G34: =(K12*K13) | H34: calculation
B35: Model | C35: ec_suv_rev | D35: 이커머스 SUV | E35: 2026 | F35: L9 | G35: =(L12*L13) | H35: calculation
B36: Model | C36: ec_suv_rev | D36: 이커머스 SUV | E36: 2027 | F36: M9 | G36: =(M12*M13) | H36: calculation
B37: Model | C37: ec_suv_rev | D37: 이커머스 SUV | E37: 2028 | F37: N9 | G37: =(N12*N13) | H37: calculation
B38: Model | C38: ec_suv_rev | D38: 이커머스 SUV | E38: 2029 | F38: O9 | G38: =(O12*O13) | H38: calculation
B39: Model | C39: market_suv | D39: SUV 시장판매대수 | E39: 2023 | F39: I10 | G39: ='Assumptions'!I5 | H39: input link
B40: Model | C40: market_suv | D40: SUV 시장판매대수 | E40: 2024 | F40: J10 | G40: ='Assumptions'!J5 | H40: input link
B41: Model | C41: market_suv | D41: SUV 시장판매대수 | E41: 2025 | F41: K10 | G41: ='Assumptions'!K5 | H41: input link
B42: Model | C42: market_suv | D42: SUV 시장판매대수 | E42: 2026 | F42: L10 | G42: ='Assumptions'!L5 | H42: input link
B43: Model | C43: market_suv | D43: SUV 시장판매대수 | E43: 2027 | F43: M10 | G43: ='Assumptions'!M5 | H43: input link
B44: Model | C44: market_suv | D44: SUV 시장판매대수 | E44: 2028 | F44: N10 | G44: ='Assumptions'!N5 | H44: input link
B45: Model | C45: market_suv | D45: SUV 시장판매대수 | E45: 2029 | F45: O10 | G45: ='Assumptions'!O5 | H45: input link
B46: Model | C46: ec_suv_share | D46: 이커머스 SUV 점유율 | E46: 2023 | F46: I11 | G46: ='Assumptions'!I6 | H46: input link
B47: Model | C47: ec_suv_share | D47: 이커머스 SUV 점유율 | E47: 2024 | F47: J11 | G47: ='Assumptions'!J6 | H47: input link
B48: Model | C48: ec_suv_share | D48: 이커머스 SUV 점유율 | E48: 2025 | F48: K11 | G48: ='Assumptions'!K6 | H48: input link
B49: Model | C49: ec_suv_share | D49: 이커머스 SUV 점유율 | E49: 2026 | F49: L11 | G49: ='Assumptions'!L6 | H49: input link
B50: Model | C50: ec_suv_share | D50: 이커머스 SUV 점유율 | E50: 2027 | F50: M11 | G50: ='Assumptions'!M6 | H50: input link
B51: Model | C51: ec_suv_share | D51: 이커머스 SUV 점유율 | E51: 2028 | F51: N11 | G51: ='Assumptions'!N6 | H51: input link
B52: Model | C52: ec_suv_share | D52: 이커머스 SUV 점유율 | E52: 2029 | F52: O11 | G52: ='Assumptions'!O6 | H52: input link
B53: Model | C53: ec_suv_volume | D53: 이커머스 SUV 판매대수 | E53: 2023 | F53: I12 | G53: =(I10*I11) | H53: calculation
B54: Model | C54: ec_suv_volume | D54: 이커머스 SUV 판매대수 | E54: 2024 | F54: J12 | G54: =(J10*J11) | H54: calculation
B55: Model | C55: ec_suv_volume | D55: 이커머스 SUV 판매대수 | E55: 2025 | F55: K12 | G55: =(K10*K11) | H55: calculation
B56: Model | C56: ec_suv_volume | D56: 이커머스 SUV 판매대수 | E56: 2026 | F56: L12 | G56: =(L10*L11) | H56: calculation
B57: Model | C57: ec_suv_volume | D57: 이커머스 SUV 판매대수 | E57: 2027 | F57: M12 | G57: =(M10*M11) | H57: calculation
B58: Model | C58: ec_suv_volume | D58: 이커머스 SUV 판매대수 | E58: 2028 | F58: N12 | G58: =(N10*N11) | H58: calculation
B59: Model | C59: ec_suv_volume | D59: 이커머스 SUV 판매대수 | E59: 2029 | F59: O12 | G59: =(O10*O11) | H59: calculation
B60: Model | C60: ec_suv_asp | D60: 이커머스 SUV ASP | E60: 2023 | F60: I13 | G60: ='Assumptions'!I7 | H60: input link
B61: Model | C61: ec_suv_asp | D61: 이커머스 SUV ASP | E61: 2024 | F61: J13 | G61: ='Assumptions'!J7 | H61: input link
B62: Model | C62: ec_suv_asp | D62: 이커머스 SUV ASP | E62: 2025 | F62: K13 | G62: ='Assumptions'!K7 | H62: input link
B63: Model | C63: ec_suv_asp | D63: 이커머스 SUV ASP | E63: 2026 | F63: L13 | G63: ='Assumptions'!L7 | H63: input link
B64: Model | C64: ec_suv_asp | D64: 이커머스 SUV ASP | E64: 2027 | F64: M13 | G64: ='Assumptions'!M7 | H64: input link
B65: Model | C65: ec_suv_asp | D65: 이커머스 SUV ASP | E65: 2028 | F65: N13 | G65: ='Assumptions'!N7 | H65: input link
B66: Model | C66: ec_suv_asp | D66: 이커머스 SUV ASP | E66: 2029 | F66: O13 | G66: ='Assumptions'!O7 | H66: input link
B67: Model | C67: ec_large_rev | D67: 이커머스 대형 | E67: 2023 | F67: I14 | G67: =(I17*I18) | H67: calculation
B68: Model | C68: ec_large_rev | D68: 이커머스 대형 | E68: 2024 | F68: J14 | G68: =(J17*J18) | H68: calculation
B69: Model | C69: ec_large_rev | D69: 이커머스 대형 | E69: 2025 | F69: K14 | G69: =(K17*K18) | H69: calculation
B70: Model | C70: ec_large_rev | D70: 이커머스 대형 | E70: 2026 | F70: L14 | G70: =(L17*L18) | H70: calculation
B71: Model | C71: ec_large_rev | D71: 이커머스 대형 | E71: 2027 | F71: M14 | G71: =(M17*M18) | H71: calculation
B72: Model | C72: ec_large_rev | D72: 이커머스 대형 | E72: 2028 | F72: N14 | G72: =(N17*N18) | H72: calculation
B73: Model | C73: ec_large_rev | D73: 이커머스 대형 | E73: 2029 | F73: O14 | G73: =(O17*O18) | H73: calculation
B74: Model | C74: market_large | D74: 대형 시장판매대수 | E74: 2023 | F74: I15 | G74: ='Assumptions'!I8 | H74: input link
B75: Model | C75: market_large | D75: 대형 시장판매대수 | E75: 2024 | F75: J15 | G75: ='Assumptions'!J8 | H75: input link
B76: Model | C76: market_large | D76: 대형 시장판매대수 | E76: 2025 | F76: K15 | G76: ='Assumptions'!K8 | H76: input link
B77: Model | C77: market_large | D77: 대형 시장판매대수 | E77: 2026 | F77: L15 | G77: ='Assumptions'!L8 | H77: input link
B78: Model | C78: market_large | D78: 대형 시장판매대수 | E78: 2027 | F78: M15 | G78: ='Assumptions'!M8 | H78: input link
B79: Model | C79: market_large | D79: 대형 시장판매대수 | E79: 2028 | F79: N15 | G79: ='Assumptions'!N8 | H79: input link
B80: Model | C80: market_large | D80: 대형 시장판매대수 | E80: 2029 | F80: O15 | G80: ='Assumptions'!O8 | H80: input link
B81: Model | C81: ec_large_share | D81: 이커머스 대형 점유율 | E81: 2023 | F81: I16 | G81: ='Assumptions'!I9 | H81: input link
B82: Model | C82: ec_large_share | D82: 이커머스 대형 점유율 | E82: 2024 | F82: J16 | G82: ='Assumptions'!J9 | H82: input link
B83: Model | C83: ec_large_share | D83: 이커머스 대형 점유율 | E83: 2025 | F83: K16 | G83: ='Assumptions'!K9 | H83: input link
B84: Model | C84: ec_large_share | D84: 이커머스 대형 점유율 | E84: 2026 | F84: L16 | G84: ='Assumptions'!L9 | H84: input link
B85: Model | C85: ec_large_share | D85: 이커머스 대형 점유율 | E85: 2027 | F85: M16 | G85: ='Assumptions'!M9 | H85: input link
B86: Model | C86: ec_large_share | D86: 이커머스 대형 점유율 | E86: 2028 | F86: N16 | G86: ='Assumptions'!N9 | H86: input link
B87: Model | C87: ec_large_share | D87: 이커머스 대형 점유율 | E87: 2029 | F87: O16 | G87: ='Assumptions'!O9 | H87: input link
B88: Model | C88: ec_large_volume | D88: 이커머스 대형 판매대수 | E88: 2023 | F88: I17 | G88: =(I15*I16) | H88: calculation
B89: Model | C89: ec_large_volume | D89: 이커머스 대형 판매대수 | E89: 2024 | F89: J17 | G89: =(J15*J16) | H89: calculation
B90: Model | C90: ec_large_volume | D90: 이커머스 대형 판매대수 | E90: 2025 | F90: K17 | G90: =(K15*K16) | H90: calculation
B91: Model | C91: ec_large_volume | D91: 이커머스 대형 판매대수 | E91: 2026 | F91: L17 | G91: =(L15*L16) | H91: calculation
B92: Model | C92: ec_large_volume | D92: 이커머스 대형 판매대수 | E92: 2027 | F92: M17 | G92: =(M15*M16) | H92: calculation
B93: Model | C93: ec_large_volume | D93: 이커머스 대형 판매대수 | E93: 2028 | F93: N17 | G93: =(N15*N16) | H93: calculation
B94: Model | C94: ec_large_volume | D94: 이커머스 대형 판매대수 | E94: 2029 | F94: O17 | G94: =(O15*O16) | H94: calculation
B95: Model | C95: ec_large_asp | D95: 이커머스 대형 ASP | E95: 2023 | F95: I18 | G95: ='Assumptions'!I10 | H95: input link
B96: Model | C96: ec_large_asp | D96: 이커머스 대형 ASP | E96: 2024 | F96: J18 | G96: ='Assumptions'!J10 | H96: input link
B97: Model | C97: ec_large_asp | D97: 이커머스 대형 ASP | E97: 2025 | F97: K18 | G97: ='Assumptions'!K10 | H97: input link
B98: Model | C98: ec_large_asp | D98: 이커머스 대형 ASP | E98: 2026 | F98: L18 | G98: ='Assumptions'!L10 | H98: input link
B99: Model | C99: ec_large_asp | D99: 이커머스 대형 ASP | E99: 2027 | F99: M18 | G99: ='Assumptions'!M10 | H99: input link
B100: Model | C100: ec_large_asp | D100: 이커머스 대형 ASP | E100: 2028 | F100: N18 | G100: ='Assumptions'!N10 | H100: input link
B101: Model | C101: ec_large_asp | D101: 이커머스 대형 ASP | E101: 2029 | F101: O18 | G101: ='Assumptions'!O10 | H101: input link
...

Sheet Structure
B1: Structure
B3: ID | C3: Label | D3: Parent | E3: Level | F3: Type | G3: Formula | H3: Unit | I3: Description
B4: root | C4: KCar Enterprise Value | E4: 0 | F4: computed | G4: enterprise_value | H4: 원 | I4: 케이카 재무모델의 최상위 구조. 채널별 중고차 판매 Q×P에서 매출·비용·FCFF·기업가치를 연결.
B5: rev | C5: 매출 합계 | D5: root | E5: 1 | F5: computed | G5: SUM(used_car_sales, auction_sales, rental_sales, service_other_sales) | H5: 원 | I5: 케이카 매출 합계. 이커머스/지점내방 중고차 판매와 경매, 렌터카, 용역/기타 매출을 합산.
B6: used_car_sales | C6: 중고차 판매 | D6: rev | E6: 2 | F6: computed | G6: ecommerce_sales + branch_sales | H6: 원 | I6: 핵심 매출원. 채널별·차급별 Q×P 모델로 계산.
B7: ecommerce_sales | C7: 이커머스 중고차 판매 | D7: used_car_sales | E7: 3 | F7: computed | G7: SUM(ec_suv_rev, ec_large_rev, ec_midsize_rev, ec_compact_rev, ec_small_rev, ec_truck_rev, ec_other_rev) | H7: 원 | I7: 온라인 채널 매출. 차급별 시장판매대수, 케이카 점유율, ASP를 곱해 계산.
B8: ec_suv_rev | C8: 이커머스 SUV | D8: ecommerce_sales | E8: 4 | F8: computed | G8: ec_suv_volume * ec_suv_asp | H8: 원 | I8: 이커머스 SUV 매출 = 판매대수 × 평균판매가격.
B9: market_suv | C9: SUV 시장판매대수 | D9: ec_suv_rev | E9: 5 | F9: input | H9: 대 | I9: 차급별 중고차 시장 판매대수 가정.
B10: ec_suv_share | C10: 이커머스 SUV 점유율 | D10: ec_suv_rev | E10: 5 | F10: input | H10: % | I10: 해당 차급 시장에서 케이카 이커머스 채널이 확보하는 비율.
B11: ec_suv_volume | C11: 이커머스 SUV 판매대수 | D11: ec_suv_rev | E11: 5 | F11: computed | G11: market_suv * ec_suv_share | H11: 대 | I11: 이커머스 SUV 판매대수 = 시장판매대수 × 점유율.
B12: ec_suv_asp | C12: 이커머스 SUV ASP | D12: ec_suv_rev | E12: 5 | F12: input | H12: 원/대 | I12: 이커머스 SUV 평균판매가격.
B13: ec_large_rev | C13: 이커머스 대형 | D13: ecommerce_sales | E13: 4 | F13: computed | G13: ec_large_volume * ec_large_asp | H13: 원 | I13: 이커머스 대형 매출 = 판매대수 × 평균판매가격.
B14: market_large | C14: 대형 시장판매대수 | D14: ec_large_rev | E14: 5 | F14: input | H14: 대 | I14: 차급별 중고차 시장 판매대수 가정.
B15: ec_large_share | C15: 이커머스 대형 점유율 | D15: ec_large_rev | E15: 5 | F15: input | H15: % | I15: 해당 차급 시장에서 케이카 이커머스 채널이 확보하는 비율.
B16: ec_large_volume | C16: 이커머스 대형 판매대수 | D16: ec_large_rev | E16: 5 | F16: computed | G16: market_large * ec_large_share | H16: 대 | I16: 이커머스 대형 판매대수 = 시장판매대수 × 점유율.
B17: ec_large_asp | C17: 이커머스 대형 ASP | D17: ec_large_rev | E17: 5 | F17: input | H17: 원/대 | I17: 이커머스 대형 평균판매가격.
B18: ec_midsize_rev | C18: 이커머스 중형 | D18: ecommerce_sales | E18: 4 | F18: computed | G18: ec_midsize_volume * ec_midsize_asp | H18: 원 | I18: 이커머스 중형 매출 = 판매대수 × 평균판매가격.
B19: market_midsize | C19: 중형 시장판매대수 | D19: ec_midsize_rev | E19: 5 | F19: input | H19: 대 | I19: 차급별 중고차 시장 판매대수 가정.
B20: ec_midsize_share | C20: 이커머스 중형 점유율 | D20: ec_midsize_rev | E20: 5 | F20: input | H20: % | I20: 해당 차급 시장에서 케이카 이커머스 채널이 확보하는 비율.
B21: ec_midsize_volume | C21: 이커머스 중형 판매대수 | D21: ec_midsize_rev | E21: 5 | F21: computed | G21: market_midsize * ec_midsize_share | H21: 대 | I21: 이커머스 중형 판매대수 = 시장판매대수 × 점유율.
B22: ec_midsize_asp | C22: 이커머스 중형 ASP | D22: ec_midsize_rev | E22: 5 | F22: input | H22: 원/대 | I22: 이커머스 중형 평균판매가격.
B23: ec_compact_rev | C23: 이커머스 준중형 | D23: ecommerce_sales | E23: 4 | F23: computed | G23: ec_compact_volume * ec_compact_asp | H23: 원 | I23: 이커머스 준중형 매출 = 판매대수 × 평균판매가격.
B24: market_compact | C24: 준중형 시장판매대수 | D24: ec_compact_rev | E24: 5 | F24: input | H24: 대 | I24: 차급별 중고차 시장 판매대수 가정.
B25: ec_compact_share | C25: 이커머스 준중형 점유율 | D25: ec_compact_rev | E25: 5 | F25: input | H25: % | I25: 해당 차급 시장에서 케이카 이커머스 채널이 확보하는 비율.
B26: ec_compact_volume | C26: 이커머스 준중형 판매대수 | D26: ec_compact_rev | E26: 5 | F26: computed | G26: market_compact * ec_compact_share | H26: 대 | I26: 이커머스 준중형 판매대수 = 시장판매대수 × 점유율.
B27: ec_compact_asp | C27: 이커머스 준중형 ASP | D27: ec_compact_rev | E27: 5 | F27: input | H27: 원/대 | I27: 이커머스 준중형 평균판매가격.
B28: ec_small_rev | C28: 이커머스 소형 | D28: ecommerce_sales | E28: 4 | F28: computed | G28: ec_small_volume * ec_small_asp | H28: 원 | I28: 이커머스 소형 매출 = 판매대수 × 평균판매가격.
B29: market_small | C29: 소형 시장판매대수 | D29: ec_small_rev | E29: 5 | F29: input | H29: 대 | I29: 차급별 중고차 시장 판매대수 가정.
B30: ec_small_share | C30: 이커머스 소형 점유율 | D30: ec_small_rev | E30: 5 | F30: input | H30: % | I30: 해당 차급 시장에서 케이카 이커머스 채널이 확보하는 비율.
B31: ec_small_volume | C31: 이커머스 소형 판매대수 | D31: ec_small_rev | E31: 5 | F31: computed | G31: market_small * ec_small_share | H31: 대 | I31: 이커머스 소형 판매대수 = 시장판매대수 × 점유율.
B32: ec_small_asp | C32: 이커머스 소형 ASP | D32: ec_small_rev | E32: 5 | F32: input | H32: 원/대 | I32: 이커머스 소형 평균판매가격.
B33: ec_truck_rev | C33: 이커머스 화물차 | D33: ecommerce_sales | E33: 4 | F33: computed | G33: ec_truck_volume * ec_truck_asp | H33: 원 | I33: 이커머스 화물차 매출 = 판매대수 × 평균판매가격.
B34: market_truck | C34: 화물차 시장판매대수 | D34: ec_truck_rev | E34: 5 | F34: input | H34: 대 | I34: 차급별 중고차 시장 판매대수 가정.
B35: ec_truck_share | C35: 이커머스 화물차 점유율 | D35: ec_truck_rev | E35: 5 | F35: input | H35: % | I35: 해당 차급 시장에서 케이카 이커머스 채널이 확보하는 비율.
B36: ec_truck_volume | C36: 이커머스 화물차 판매대수 | D36: ec_truck_rev | E36: 5 | F36: computed | G36: market_truck * ec_truck_share | H36: 대 | I36: 이커머스 화물차 판매대수 = 시장판매대수 × 점유율.
B37: ec_truck_asp | C37: 이커머스 화물차 ASP | D37: ec_truck_rev | E37: 5 | F37: input | H37: 원/대 | I37: 이커머스 화물차 평균판매가격.
B38: ec_other_rev | C38: 이커머스 기타 | D38: ecommerce_sales | E38: 4 | F38: computed | G38: ec_other_volume * ec_other_asp | H38: 원 | I38: 이커머스 기타 매출 = 판매대수 × 평균판매가격.
B39: market_other | C39: 기타 시장판매대수 | D39: ec_other_rev | E39: 5 | F39: input | H39: 대 | I39: 차급별 중고차 시장 판매대수 가정.
B40: ec_other_share | C40: 이커머스 기타 점유율 | D40: ec_other_rev | E40: 5 | F40: input | H40: % | I40: 해당 차급 시장에서 케이카 이커머스 채널이 확보하는 비율.
B41: ec_other_volume | C41: 이커머스 기타 판매대수 | D41: ec_other_rev | E41: 5 | F41: computed | G41: market_other * ec_other_share | H41: 대 | I41: 이커머스 기타 판매대수 = 시장판매대수 × 점유율.
B42: ec_other_asp | C42: 이커머스 기타 ASP | D42: ec_other_rev | E42: 5 | F42: input | H42: 원/대 | I42: 이커머스 기타 평균판매가격.
B43: branch_sales | C43: 지점내방 중고차 판매 | D43: used_car_sales | E43: 3 | F43: computed | G43: SUM(br_suv_rev, br_large_rev, br_midsize_rev, br_compact_rev, br_small_rev, br_truck_rev, br_other_rev) | H43: 원 | I43: 오프라인 지점 방문 채널 매출. 이커머스와 같은 차급 구조를 사용.
B44: br_suv_rev | C44: 지점내방 SUV | D44: branch_sales | E44: 4 | F44: computed | G44: br_suv_volume * br_suv_asp | H44: 원 | I44: 지점내방 SUV 매출 = 판매대수 × 평균판매가격.
B45: br_suv_share | C45: 지점내방 SUV 점유율 | D45: br_suv_rev | E45: 5 | F45: input | H45: % | I45: 해당 차급 시장에서 케이카 지점내방 채널이 확보하는 비율.
B46: br_suv_volume | C46: 지점내방 SUV 판매대수 | D46: br_suv_rev | E46: 5 | F46: computed | G46: market_suv * br_suv_share | H46: 대 | I46: 지점내방 SUV 판매대수 = 시장판매대수 × 점유율.
B47: br_suv_asp | C47: 지점내방 SUV ASP | D47: br_suv_rev | E47: 5 | F47: input | H47: 원/대 | I47: 지점내방 SUV 평균판매가격.
B48: br_large_rev | C48: 지점내방 대형 | D48: branch_sales | E48: 4 | F48: computed | G48: br_large_volume * br_large_asp | H48: 원 | I48: 지점내방 대형 매출 = 판매대수 × 평균판매가격.
B49: br_large_share | C49: 지점내방 대형 점유율 | D49: br_large_rev | E49: 5 | F49: input | H49: % | I49: 해당 차급 시장에서 케이카 지점내방 채널이 확보하는 비율.
B50: br_large_volume | C50: 지점내방 대형 판매대수 | D50: br_large_rev | E50: 5 | F50: computed | G50: market_large * br_large_share | H50: 대 | I50: 지점내방 대형 판매대수 = 시장판매대수 × 점유율.
B51: br_large_asp | C51: 지점내방 대형 ASP | D51: br_large_rev | E51: 5 | F51: input | H51: 원/대 | I51: 지점내방 대형 평균판매가격.
B52: br_midsize_rev | C52: 지점내방 중형 | D52: branch_sales | E52: 4 | F52: computed | G52: br_midsize_volume * br_midsize_asp | H52: 원 | I52: 지점내방 중형 매출 = 판매대수 × 평균판매가격.
B53: br_midsize_share | C53: 지점내방 중형 점유율 | D53: br_midsize_rev | E53: 5 | F53: input | H53: % | I53: 해당 차급 시장에서 케이카 지점내방 채널이 확보하는 비율.
B54: br_midsize_volume | C54: 지점내방 중형 판매대수 | D54: br_midsize_rev | E54: 5 | F54: computed | G54: market_midsize * br_midsize_share | H54: 대 | I54: 지점내방 중형 판매대수 = 시장판매대수 × 점유율.
B55: br_midsize_asp | C55: 지점내방 중형 ASP | D55: br_midsize_rev | E55: 5 | F55: input | H55: 원/대 | I55: 지점내방 중형 평균판매가격.
B56: br_compact_rev | C56: 지점내방 준중형 | D56: branch_sales | E56: 4 | F56: computed | G56: br_compact_volume * br_compact_asp | H56: 원 | I56: 지점내방 준중형 매출 = 판매대수 × 평균판매가격.
B57: br_compact_share | C57: 지점내방 준중형 점유율 | D57: br_compact_rev | E57: 5 | F57: input | H57: % | I57: 해당 차급 시장에서 케이카 지점내방 채널이 확보하는 비율.
B58: br_compact_volume | C58: 지점내방 준중형 판매대수 | D58: br_compact_rev | E58: 5 | F58: computed | G58: market_compact * br_compact_share | H58: 대 | I58: 지점내방 준중형 판매대수 = 시장판매대수 × 점유율.
B59: br_compact_asp | C59: 지점내방 준중형 ASP | D59: br_compact_rev | E59: 5 | F59: input | H59: 원/대 | I59: 지점내방 준중형 평균판매가격.
B60: br_small_rev | C60: 지점내방 소형 | D60: branch_sales | E60: 4 | F60: computed | G60: br_small_volume * br_small_asp | H60: 원 | I60: 지점내방 소형 매출 = 판매대수 × 평균판매가격.
B61: br_small_share | C61: 지점내방 소형 점유율 | D61: br_small_rev | E61: 5 | F61: input | H61: % | I61: 해당 차급 시장에서 케이카 지점내방 채널이 확보하는 비율.
B62: br_small_volume | C62: 지점내방 소형 판매대수 | D62: br_small_rev | E62: 5 | F62: computed | G62: market_small * br_small_share | H62: 대 | I62: 지점내방 소형 판매대수 = 시장판매대수 × 점유율.
B63: br_small_asp | C63: 지점내방 소형 ASP | D63: br_small_rev | E63: 5 | F63: input | H63: 원/대 | I63: 지점내방 소형 평균판매가격.
B64: br_truck_rev | C64: 지점내방 화물차 | D64: branch_sales | E64: 4 | F64: computed | G64: br_truck_volume * br_truck_asp | H64: 원 | I64: 지점내방 화물차 매출 = 판매대수 × 평균판매가격.
B65: br_truck_share | C65: 지점내방 화물차 점유율 | D65: br_truck_rev | E65: 5 | F65: input | H65: % | I65: 해당 차급 시장에서 케이카 지점내방 채널이 확보하는 비율.
B66: br_truck_volume | C66: 지점내방 화물차 판매대수 | D66: br_truck_rev | E66: 5 | F66: computed | G66: market_truck * br_truck_share | H66: 대 | I66: 지점내방 화물차 판매대수 = 시장판매대수 × 점유율.
B67: br_truck_asp | C67: 지점내방 화물차 ASP | D67: br_truck_rev | E67: 5 | F67: input | H67: 원/대 | I67: 지점내방 화물차 평균판매가격.
B68: br_other_rev | C68: 지점내방 기타 | D68: branch_sales | E68: 4 | F68: computed | G68: br_other_volume * br_other_asp | H68: 원 | I68: 지점내방 기타 매출 = 판매대수 × 평균판매가격.
B69: br_other_share | C69: 지점내방 기타 점유율 | D69: br_other_rev | E69: 5 | F69: input | H69: % | I69: 해당 차급 시장에서 케이카 지점내방 채널이 확보하는 비율.
B70: br_other_volume | C70: 지점내방 기타 판매대수 | D70: br_other_rev | E70: 5 | F70: computed | G70: market_other * br_other_share | H70: 대 | I70: 지점내방 기타 판매대수 = 시장판매대수 × 점유율.
B71: br_other_asp | C71: 지점내방 기타 ASP | D71: br_other_rev | E71: 5 | F71: input | H71: 원/대 | I71: 지점내방 기타 평균판매가격.
B72: used_car_volume | C72: 중고차 판매대수 | D72: used_car_sales | E72: 3 | F72: computed | G72: SUM(ec_suv_volume, ec_large_volume, ec_midsize_volume, ec_compact_volume, ec_small_volume, ec_truck_volume, ec_other_volume, br_suv_volume, br_large_volume, br_midsize_volume, br_compact_volume, br_small_volume, br_truck_volume, br_other_volume) | H72: 대 | I72: 매출과 비용이 공유하는 핵심 수량 드라이버.
B73: auction_sales | C73: 경매 매출 | D73: rev | E73: 2 | F73: computed | G73: auction_product_sales + auction_service_sales | H73: 원 | I73: 경매 상품 매출과 경매 용역 매출. 실습 모델에서는 성장률 기반 입력으로 단순화.
B74: auction_product_sales | C74: 경매 상품 매출 | D74: auction_sales | E74: 3 | F74: input | H74: 원 | I74: 경매 상품 매출 가정.
B75: auction_service_sales | C75: 경매 용역 매출 | D75: auction_sales | E75: 3 | F75: input | H75: 원 | I75: 경매 용역 매출 가정.
B76: rental_sales | C76: 렌터카 매출 | D76: rev | E76: 2 | F76: computed | G76: rental_disposal_sales + longterm_rental_sales | H76: 원 | I76: 렌터카 매각 매출과 장기렌트 매출.
B77: rental_disposal_sales | C77: 렌터카 매각 매출 | D77: rental_sales | E77: 3 | F77: input | H77: 원 | I77: 렌터카 매각 매출 가정.
B78: longterm_rental_sales | C78: 장기렌트 매출 | D78: rental_sales | E78: 3 | F78: input | H78: 원 | I78: 장기렌트 매출 가정.
B79: service_other_sales | C79: 용역 / 기타 매출 | D79: rev | E79: 2 | F79: computed | G79: ecommerce_service_sales + branch_service_sales + other_sales | H79: 원 | I79: 이커머스/지점내방 용역 매출은 각 채널 중고차 매출 대비 비율로 계산.
B80: ecommerce_service_sales | C80: 이커머스 용역 매출 | D80: service_other_sales | E80: 3 | F80: computed | G80: ecommerce_sales * ecommerce_service_rate | H80: 원 | I80: 이커머스 용역 매출 = 이커머스 중고차 매출 × 용역 매출률.
B81: ecommerce_service_rate | C81: 이커머스 용역 매출률 | D81: ecommerce_service_sales | E81: 4 | F81: input | H81: % | I81: 이커머스 중고차 매출 대비 용역 매출 비율.
B82: branch_service_sales | C82: 지점내방 용역 매출 | D82: service_other_sales | E82: 3 | F82: computed | G82: branch_sales * branch_service_rate | H82: 원 | I82: 지점내방 용역 매출 = 지점내방 중고차 매출 × 용역 매출률.
B83: branch_service_rate | C83: 지점내방 용역 매출률 | D83: branch_service_sales | E83: 4 | F83: input | H83: % | I83: 지점내방 중고차 매출 대비 용역 매출 비율.
B84: other_sales | C84: 기타 매출 | D84: service_other_sales | E84: 3 | F84: input | H84: 원 | I84: 기타 부가 매출 가정.
B85: total_cost | C85: 비용 합계 | D85: root | E85: 1 | F85: computed | G85: SUM(inventory_cost, warranty_cost, rental_car_cost, variable_sga, fixed_sga, labor_cost, da) | H85: 원 | I85: 총비용. 중고차 판매대수와 매출을 공유 드라이버로 사용.
B86: inventory_cost | C86: 재고자산원가 | D86: total_cost | E86: 2 | F86: computed | G86: used_car_volume * unit_inventory_cost | H86: 원 | I86: 중고차 판매의 핵심 원가. 판매대수와 직접 연결.
B87: unit_inventory_cost | C87: 중고차 1대당 원가 | D87: inventory_cost | E87: 3 | F87: input | H87: 원/대 | I87: 중고차 1대당 매입/상품화 원가.
B88: warranty_cost | C88: 판매보증비 | D88: total_cost | E88: 2 | F88: computed | G88: used_car_volume * warranty_cost_per_unit | H88: 원 | I88: 판매 차량에 붙는 보증 관련 비용.
B89: warranty_cost_per_unit | C89: 대당 보증비 | D89: warranty_cost | E89: 3 | F89: input | H89: 원/대 | I89: 중고차 1대당 보증 관련 비용.
B90: rental_car_cost | C90: 차량매각원가 | D90: total_cost | E90: 2 | F90: computed | G90: rental_disposal_sales * rental_disposal_cost_rate | H90: 원 | I90: 렌터카 매각 매출에 대응되는 원가.
B91: rental_disposal_cost_rate | C91: 차량매각원가율 | D91: rental_car_cost | E91: 3 | F91: input | H91: % | I91: 렌터카 매각 매출 대비 원가율.
B92: variable_sga | C92: 변동 판관비 | D92: total_cost | E92: 2 | F92: computed | G92: rev * variable_sga_rate | H92: 원 | I92: 매출 규모에 연동되는 지급수수료, 부품비, 세금과공과 등.
B93: variable_sga_rate | C93: 변동 판관비율 | D93: variable_sga | E93: 3 | F93: input | H93: % | I93: 매출 대비 변동 판관비율.
B94: fixed_sga | C94: 고정 판관비 | D94: total_cost | E94: 2 | F94: input | H94: 원 | I94: 임차료, 운반비, 차량유지비 등 고정비성 판관비.
B95: labor_cost | C95: 인건비 | D95: total_cost | E95: 2 | F95: computed | G95: employee_count * avg_salary | H95: 원 | I95: 필요 인원 × 평균 급여.
B96: employee_count | C96: 필요 인원 | D96: labor_cost | E96: 3 | F96: input | H96: 명 | I96: 중고차 판매, 경매, 렌탈, 사무/IT/마케팅 인력.
B97: avg_salary | C97: 평균 급여 | D97: labor_cost | E97: 3 | F97: input | H97: 원/명 | I97: 1인당 평균 연간 급여.
B98: da | C98: 감가상각비 | D98: total_cost | E98: 2 | F98: input | H98: 원 | I98: CapEx와 기존 유형자산에서 발생하는 감가상각비.
B99: op_profit | C99: 영업이익 | D99: root | E99: 1 | F99: computed | G99: rev - total_cost | H99: 원 | I99: 영업이익 = 매출 합계 − 비용 합계.
B100: fcff | C100: FCFF | D100: root | E100: 1 | F100: computed | G100: ebiat + da - capex - change_nwc | H100: 원 | I100: 기업가치 산정에 사용하는 단순 FCFF.
B101: tax | C101: 법인세 | D101: fcff | E101: 2 | F101: computed | G101: MAX(op_profit, 0) * tax_rate | H101: 원 | I101: 영업이익이 양수일 때 적용하는 단순 법인세.
...

Sheet Checks
B1: Checks
B3: Check | C3: Result | D3: Status
B4: Formula cells generated | C4: 406 | D4: OK
B5: Input links generated | C5: 406 | D5: OK
B6: Computed nodes | C6: 58 | D6: OK
B7: Input nodes | C7: 58 | D7: OK
B8: All computed formulas parsed | C8: OK | D8: OK
B9: All inputs centralized in Assumptions | C9: OK | D9: OK
B10: HTML nodes in Structure | C10: 116 | D10: OK

Sheet Metadata
B1: Metadata
B3: Generated by | C3: financial-modeling/framework/build_excel.py
B4: IR version | C4: 1
B5: Nodes | C5: 116
B6: Input nodes | C6: 58
B7: Computed nodes | C7: 58
B8: Formula cells | C8: 406
B9: Input link cells | C9: 406
B10: Years | C10: 2023–2029 (7개)
B11: Policy | C11: Inputs are centralized in Assumptions; Model contains links and formulas.
