Workbook

Sheet Index
B1: Index
B3: 구분 | C3: Sheet | D3: Link
B4: Overall | C4: Index | D4: Link
C5: Control
C6: DCF | D6: Link
B7: Sales | C7: Sales | D7: Link
C8: Sales Bridge | D8: Link
B9: Cost | C9: Cost | D9: Link
B10: Others | C10: CapEx, D&A | D10: Link
C11: Labor | D11: Link
C12: NWC | D12: Link
C13: BS | D13: Link
B14: Raw | C14: Dart_FS | D14: Link
C15: Dart_시장리서치 | D15: Link
C16: Dart_Labor | D16: Link
C17: Dart_Cost | D17: Link
C18: Dart_Sales | D18: Link
C19: Dart_중고차 Sales | D19: Link
C20: Dart_Capture | D20: Link

Sheet Control
B1: Control
B3: Equity Value | C3: =DCF!E39 -> 1786998.3
B4: per Share | C4: =DCF!E43 -> 38115.011
D6: Historical | J6: Forecast
B7: KRW in millions | D7: 2018 | E7: 2019 | F7: 2020 | G7: 2021.1H | H7: 2021.2H | I7: 2021 | J7: 2022 | K7: =J7+1 -> 2023 | L7: =K7+1 -> 2024 | M7: =L7+1 -> 2025 | N7: =M7+1 -> 2026
B8: Sales | D8: =DCF!D5 -> 742803 | E8: =DCF!E5 -> 1185356 | F8: =DCF!F5 -> 1323114 | G8: =DCF!G5 -> 910585 | H8: =DCF!H5 -> 910585 | I8: =DCF!I5 -> 1821170 | J8: =DCF!J5 -> 1902459 | K8: =DCF!K5 -> 2256380 | ... N8: =DCF!N5 -> 3792952.9
B9: EBITDA | D9: =DCF!D14 -> 18098.116 | E9: =DCF!E14 -> 42742.643 | F9: =DCF!F14 -> 53572.583 | G9: =DCF!G14 -> 58203.291 | H9: =DCF!H14 -> 58203.291 | I9: =DCF!I14 -> 116406.58 | J9: =DCF!J14 -> 149588.77 | K9: =DCF!K14 -> 175638.61 | ... N9: =DCF!N14 -> 282570.99
B10: FCFF | D10: =DCF!D23 -> 9548.2327 | E10: =DCF!E23 -> 8606.395 | F10: =DCF!F23 -> 33697.41 | G10: =DCF!G23 -> 53519.88 | H10: =DCF!H23 -> 46847.13 | I10: =DCF!I23 -> 100367.01 | J10: =DCF!J23 -> 46648.239 | K10: =DCF!K23 -> 113334.54 | ... N10: =DCF!N23 -> 150980.08
B13: Sales_이커머스 중고차판매 | J13: 2022 | K13: =J13+1 -> 2023 | L13: =K13+1 -> 2024 | M13: =L13+1 -> 2025 | N13: =M13+1 -> 2026
B15: SUV(이커머스) P growth | J15: 0.01 | K15: 0.01 | L15: 0.01 | M15: 0.01 | N15: 0.01
B16: SUV(이커머스) 시장 Q growth | J16: 0.1 | K16: 0.1 | L16: 0.1 | M16: 0.1 | N16: 0.1
B17: SUV(이커머스) 케이카 점유율 | J17: 0.6 | K17: 0.6 | L17: 0.6 | M17: 0.6 | N17: 0.6
B18: 대형(이커머스) P growth | J18: 0.01 | K18: 0.01 | L18: 0.01 | M18: 0.01 | N18: 0.01
B19: 대형(이커머스) 시장 Q growth | J19: 0.1 | K19: 0.1 | L19: 0.1 | M19: 0.1 | N19: 0.1
B20: 대형(이커머스) 케이카 점유율 | J20: 0.6 | K20: 0.6 | L20: 0.6 | M20: 0.6 | N20: 0.6
B21: 중형(이커머스) P growth | J21: 0.01 | K21: 0.01 | L21: 0.01 | M21: 0.01 | N21: 0.01
B22: 중형(이커머스) 시장 Q growth | J22: 0.1 | K22: 0.1 | L22: 0.1 | M22: 0.1 | N22: 0.1
B23: 중형(이커머스) 케이카 점유율 | J23: 0.6 | K23: 0.6 | L23: 0.6 | M23: 0.6 | N23: 0.6
B24: 준중형(이커머스) P growth | J24: 0.01 | K24: 0.01 | L24: 0.01 | M24: 0.01 | N24: 0.01
B25: 준중형(이커머스) 시장 Q growth | J25: 0.2 | K25: 0.2 | L25: 0.2 | M25: 0.2 | N25: 0.2
B26: 준중형(이커머스) 케이카 점유율 | J26: 0.6 | K26: 0.6 | L26: 0.6 | M26: 0.6 | N26: 0.6
... B35: 기타(이커머스) 케이카 점유율 | J35: 0.6 | K35: 0.6 | L35: 0.6 | M35: 0.6 | N35: 0.6
B37: Sales_지점내방 중고차판매 | J37: 2022 | K37: =J37+1 -> 2023 | L37: =K37+1 -> 2024 | M37: =L37+1 -> 2025 | N37: =M37+1 -> 2026
B39: SUV(지점내방) P growth | J39: 0.01 | K39: 0.01 | L39: 0.01 | M39: 0.01 | N39: 0.01
B40: SUV(지점내방) 시장 Q growth | J40: 0.2 | K40: 0.2 | L40: 0.2 | M40: 0.2 | N40: 0.2
B41: SUV(지점내방) 케이카 점유율 | J41: 0.02 | K41: 0.02 | L41: 0.02 | M41: 0.02 | N41: 0.02
B42: 대형(지점내방) P growth | J42: 0.01 | K42: 0.01 | L42: 0.01 | M42: 0.01 | N42: 0.01
B43: 대형(지점내방) 시장 Q growth | J43: 0.2 | K43: 0.2 | L43: 0.2 | M43: 0.2 | N43: 0.2
B44: 대형(지점내방) 케이카 점유율 | J44: 0.02 | K44: 0.02 | L44: 0.02 | M44: 0.02 | N44: 0.02
B45: 중형(지점내방) P growth | J45: 0.01 | K45: 0.01 | L45: 0.01 | M45: 0.01 | N45: 0.01
B46: 중형(지점내방) 시장 Q growth | J46: 0.2 | K46: 0.2 | L46: 0.2 | M46: 0.2 | N46: 0.2
B47: 중형(지점내방) 케이카 점유율 | J47: 0.02 | K47: 0.02 | L47: 0.02 | M47: 0.02 | N47: 0.02
B48: 준중형(지점내방) P growth | J48: 0.01 | K48: 0.01 | L48: 0.01 | M48: 0.01 | N48: 0.01
B49: 준중형(지점내방) 시장 Q growth | J49: 0.2 | K49: 0.2 | L49: 0.2 | M49: 0.2 | N49: 0.2
B50: 준중형(지점내방) 케이카 점유율 | J50: 0.02 | K50: 0.02 | L50: 0.02 | M50: 0.02 | N50: 0.02
... B59: 기타(지점내방) 케이카 점유율 | J59: 0.02 | K59: 0.02 | L59: 0.02 | M59: 0.02 | N59: 0.02
B61: Sales_기타가정 | J61: 2022 | K61: =J61+1 -> 2023 | L61: =K61+1 -> 2024 | M61: =L61+1 -> 2025 | N61: =M61+1 -> 2026
B63: 경매(상품)매출 성장률 | J63: 0.2 | K63: 0.2 | L63: 0.2 | M63: 0.2 | N63: 0.2
B64: 경매(용역)매출 성장률 | J64: 0.2 | K64: 0.2 | L64: 0.2 | M64: 0.2 | N64: 0.2
B65: 렌터카 매각 매출 성장률 | J65: 0.2 | K65: 0.2 | L65: 0.2 | M65: 0.2 | N65: 0.2
B66: 렌터 매출 성장률 | J66: 0.2 | K66: 0.2 | L66: 0.2 | M66: 0.2 | N66: 0.2
B67: 이커머스 용역매출 비율 | J67: 0.028902443 | K67: 0.028902443 | L67: 0.028902443 | M67: 0.028902443 | N67: 0.028902443
B68: 지점내방 용역매출 비율 | J68: 0.028056395 | K68: 0.028056395 | L68: 0.028056395 | M68: 0.028056395 | N68: 0.028056395
B69: 기타매출 비율 | J69: 0.0027737782 | K69: 0.0027737782 | L69: 0.0027737782 | M69: 0.0027737782 | N69: 0.0027737782
B71: Variable Cost | J71: 2022 | K71: =J71+1 -> 2023 | L71: =K71+1 -> 2024 | M71: =L71+1 -> 2025 | N71: =M71+1 -> 2026
B73: 주식보상비용 비율(인건비) | J73: 0.03 | K73: 0.03 | L73: 0.03 | M73: 0.03 | N73: 0.03
B74: 중고차 1대당 원가 | J74: =Cost!J22 -> 14.406963 | K74: =J74*(1+1%) -> 14.551032 | L74: =K74*(1+1%) -> 14.696543 | M74: =L74*(1+1%) -> 14.843508 | N74: =M74*(1+1%) -> 14.991943
B75: 중고차 1대당 보증비 | J75: =Cost!J25 -> 0.033326315 | K75: =J75 -> 0.033326315 | L75: =K75 -> 0.033326315 | M75: =L75 -> 0.033326315 | N75: =M75 -> 0.033326315
B76: 렌터카 원가율 | J76: =Cost!J28 -> 0.77797471 | K76: =J76 -> 0.77797471 | L76: =K76 -> 0.77797471 | M76: =L76 -> 0.77797471 | N76: =M76 -> 0.77797471
B77: 지급수수료율 | J77: =AVERAGE(Cost!E30:G30,Cost!J30) -> 0.0081378855 | K77: =J77 -> 0.0081378855 | L77: =K77 -> 0.0081378855 | M77: =L77 -> 0.0081378855 | N77: =M77 -> 0.0081378855
B78: =Cost!C31&"율" -> 부품비율 | J78: =AVERAGE(Cost!E32:G32,Cost!J32) -> 0.00051002276 | K78: =J78 -> 0.00051002276 | L78: =K78 -> 0.00051002276 | M78: =L78 -> 0.00051002276 | N78: =M78 -> 0.00051002276
B79: =Cost!C33&"율" -> 세금과공과율 | J79: =AVERAGE(Cost!E34:G34,Cost!J34) -> 0.003202408 | K79: =J79 -> 0.003202408 | L79: =K79 -> 0.003202408 | M79: =L79 -> 0.003202408 | N79: =M79 -> 0.003202408
B80: =Cost!C35&"율" -> 위탁차량비율 | J80: =AVERAGE(Cost!E36:G36,Cost!J36) -> 0.00024804999 | K80: =J80 -> 0.00024804999 | L80: =K80 -> 0.00024804999 | M80: =L80 -> 0.00024804999 | N80: =M80 -> 0.00024804999
B81: =Cost!C37&"율" -> 소모품비율 | J81: =AVERAGE(Cost!E38:G38,Cost!J38) -> 0.00044903593 | K81: =J81 -> 0.00044903593 | L81: =K81 -> 0.00044903593 | M81: =L81 -> 0.00044903593 | N81: =M81 -> 0.00044903593
B82: =Cost!C39&"율" -> 보험료율 | J82: =AVERAGE(Cost!E40:G40,Cost!J40) -> 0.0006490869 | K82: =J82 -> 0.0006490869 | L82: =K82 -> 0.0006490869 | M82: =L82 -> 0.0006490869 | N82: =M82 -> 0.0006490869
B83: =Cost!C41&"율" -> 기타비용율 | J83: =AVERAGE(Cost!E42:G42) -> 0.014390409 | K83: =J83 -> 0.014390409 | L83: =K83 -> 0.014390409 | M83: =L83 -> 0.014390409 | N83: =M83 -> 0.014390409
B85: Fixed Cost | J85: 2022 | K85: =J85+1 -> 2023 | L85: =K85+1 -> 2024 | M85: =L85+1 -> 2025 | N85: =M85+1 -> 2026
B87: =Cost!C45&" 상승률" -> 여비교통비 상승률 | J87: 0.02 | K87: 0.02 | L87: 0.02 | M87: 0.02 | N87: 0.02
B88: =Cost!C47&" 상승률" -> 대손상각비 상승률 | J88: 0.02 | K88: 0.02 | L88: 0.02 | M88: 0.02 | N88: 0.02
B89: =Cost!C49&" 상승률" -> 접대비 상승률 | J89: 0.02 | K89: 0.02 | L89: 0.02 | M89: 0.02 | N89: 0.02
B90: =Cost!C51&" 상승률" -> 지급임차료 상승률 | J90: 0.02 | K90: 0.02 | L90: 0.02 | M90: 0.02 | N90: 0.02
B91: =Cost!C53&" 상승률" -> 차량유지비 상승률 | J91: 0.02 | K91: 0.02 | L91: 0.02 | M91: 0.02 | N91: 0.02
B92: =Cost!C55&" 상승률" -> 운반비 상승률 | J92: 0.02 | K92: 0.02 | L92: 0.02 | M92: 0.02 | N92: 0.02
B94: CapEx, D&A | J94: 2022 | K94: =J94+1 -> 2023 | L94: =K94+1 -> 2024 | M94: =L94+1 -> 2025 | N94: =M94+1 -> 2026
B96: 유형자산(사용권) CapEx | J96: 3229 | K96: =J96*(1+5%) -> 3390.45 | L96: =K96*(1+5%) -> 3559.9725 | M96: =L96*(1+5%) -> 3737.9711 | N96: =M96*(1+5%) -> 3924.8697
B97: 무형자산 CapEx | J97: 1027.2992 | K97: =J97*(1+5%) -> 1078.6641 | L97: =K97*(1+5%) -> 1132.5973 | M97: =L97*(1+5%) -> 1189.2272 | N97: =M97*(1+5%) -> 1248.6885
B98: 유형자산(사용권) 기타변동액 | J98: 15000 | K98: 15000 | L98: 15000 | M98: 15000 | N98: 15000
B99: 무형자산 기타변동액 | J99: 1000 | K99: 1000 | L99: 1000 | M99: 1000 | N99: 1000
B100: 유형자산 상각률 | J100: 0.2 | K100: 0.2 | L100: 0.2 | M100: 0.2 | N100: 0.2
B101: 무형자산 상각률 | J101: 0.02 | K101: 0.02 | L101: 0.02 | M101: 0.02 | N101: 0.02
B103: Labor | J103: 2022 | K103: =J103+1 -> 2023 | L103: =K103+1 -> 2024 | M103: =L103+1 -> 2025 | N103: =M103+1 -> 2026
B105: 중고차
B106: 남자 1명당 판매대수 | J106: 139 | K106: 139 | L106: 139 | M106: 139 | N106: 139
B107: 남자 1명당 평균급여 | J107: =Labor!L14*(1+2%) -> 53.875529 | K107: =J107*(1+2%) -> 54.953039 | L107: =K107*(1+2%) -> 56.0521 | M107: =L107*(1+2%) -> 57.173142 | N107: =M107*(1+2%) -> 58.316605
B108: 여자 1명당 판매대수 | J108: 1511.8333 | K108: 1511.8333 | L108: 1511.8333 | M108: 1511.8333 | N108: 1511.8333
B109: 여자 1명당 평균급여 | J109: =Labor!L18*(1+2%) -> 37.527558 | K109: =J109*(1+2%) -> 38.278109 | L109: =K109*(1+2%) -> 39.043671 | M109: =L109*(1+2%) -> 39.824544 | N109: =M109*(1+2%) -> 40.621035
B110: 경매
B111: 남자 1인당 경매매출 | J111: =Labor!L22 -> 7281.2632 | K111: =J111 -> 7281.2632 | L111: =K111 -> 7281.2632 | M111: =L111 -> 7281.2632 | N111: =M111 -> 7281.2632
B112: 남자 1인당 평균급여 | J112: =Labor!L23*(1+2%) -> 71.968956 | K112: =J112*(1+2%) -> 73.408335 | L112: =K112*(1+2%) -> 74.876502 | M112: =L112*(1+2%) -> 76.374032 | N112: =M112*(1+2%) -> 77.901512
B113: 여자 1인당 경매매출 | J113: =Labor!L26 -> 69172 | K113: =J113 -> 69172 | L113: =K113 -> 69172 | M113: =L113 -> 69172 | N113: =M113 -> 69172
B114: 여자 1인당 평균급여 | J114: =Labor!L27*(1+2%) -> 46.426363 | K114: =J114*(1+2%) -> 47.354891 | L114: =K114*(1+2%) -> 48.301988 | M114: =L114*(1+2%) -> 49.268028 | N114: =M114*(1+2%) -> 50.253389
B115: 렌탈
B116: 남자 1인당 렌탈매출 | J116: =Labor!L31 -> 1791.36 | K116: =J116 -> 1791.36 | L116: =K116 -> 1791.36 | M116: =L116 -> 1791.36 | N116: =M116 -> 1791.36
B117: 남자 1인당 평균급여 | J117: =Labor!L32*(1+2%) -> 73.535805 | K117: =J117*(1+2%) -> 75.006521 | L117: =K117*(1+2%) -> 76.506652 | M117: =L117*(1+2%) -> 78.036785 | N117: =M117*(1+2%) -> 79.597521
B118: 여자 1인당 렌탈매출 | J118: =Labor!L35 -> 4976 | K118: =J118 -> 4976 | L118: =K118 -> 4976 | M118: =L118 -> 4976 | N118: =M118 -> 4976
B119: 여자 1인당 평균급여 | J119: =Labor!L36*(1+2%) -> 68.259295 | K119: =J119*(1+2%) -> 69.624481 | L119: =K119*(1+2%) -> 71.016971 | M119: =L119*(1+2%) -> 72.43731 | N119: =M119*(1+2%) -> 73.886057
B120: 마케팅
B121: 남자직원수 | J121: =Labor!L39+1 -> 16 | K121: =J121+2 -> 18 | L121: =K121+2 -> 20 | M121: =L121+2 -> 22 | N121: =M121+2 -> 24
B122: 남자 1인당 평균급여 | J122: =Labor!L40*(1+2%) -> 64.759964 | K122: =J122*(1+2%) -> 66.055163 | L122: =K122*(1+2%) -> 67.376266 | M122: =L122*(1+2%) -> 68.723792 | N122: =M122*(1+2%) -> 70.098268
B123: 여자직원수 | J123: =Labor!L42+1 -> 13 | K123: =J123+2 -> 15 | L123: =K123+2 -> 17 | M123: =L123+2 -> 19 | N123: =M123+2 -> 21
B124: 여자 1인당 평균급여 | J124: =Labor!L43*(1+2%) -> 52.689404 | K124: =J124*(1+2%) -> 53.743193 | L124: =K124*(1+2%) -> 54.818056 | M124: =L124*(1+2%) -> 55.914418 | N124: =M124*(1+2%) -> 57.032706
B125: IT
B126: 남자직원수 | J126: =Labor!L46+1 -> 16 | K126: =J126+2 -> 18 | L126: =K126+2 -> 20 | M126: =L126+2 -> 22 | N126: =M126+2 -> 24
B127: 남자 1인당 평균급여 | J127: =Labor!L47*(1+2%) -> 70.913354 | K127: =J127*(1+2%) -> 72.331622 | L127: =K127*(1+2%) -> 73.778254 | M127: =L127*(1+2%) -> 75.253819 | N127: =M127*(1+2%) -> 76.758895
B128: 여자직원수 | J128: =Labor!L49+1 -> 6 | K128: =J128+2 -> 8 | L128: =K128+2 -> 10 | M128: =L128+2 -> 12 | N128: =M128+2 -> 14
B129: 여자 1인당 평균급여 | J129: =Labor!L50*(1+2%) -> 41.580334 | K129: =J129*(1+2%) -> 42.411941 | L129: =K129*(1+2%) -> 43.260179 | M129: =L129*(1+2%) -> 44.125383 | N129: =M129*(1+2%) -> 45.007891
B130: 사무
B131: 남자직원수 | J131: =Labor!L53+1 -> 50 | K131: =J131+2 -> 52 | L131: =K131+2 -> 54 | M131: =L131+2 -> 56 | N131: =M131+2 -> 58
B132: 남자 1인당 평균급여 | J132: =Labor!L54*(1+2%) -> 77.025699 | K132: =J132*(1+2%) -> 78.566213 | L132: =K132*(1+2%) -> 80.137537 | M132: =L132*(1+2%) -> 81.740288 | N132: =M132*(1+2%) -> 83.375094
B133: 여자직원수 | J133: =Labor!L56+1 -> 21 | K133: =J133+2 -> 23 | L133: =K133+2 -> 25 | M133: =L133+2 -> 27 | N133: =M133+2 -> 29
...

Sheet DCF
B1: DCF_케이카 | E1: Index
D3: Historical | H3: - | I3: Forecast
B4: KRW in millions | D4: =Sales!I4 -> 2018 | E4: =Sales!J4 -> 2019 | F4: =Sales!K4 -> 2020 | G4: =Sales!L4 -> 2021.1H | H4: =Sales!M4 -> 2021.2H | I4: =Sales!N4 -> 2021 | J4: =Sales!O4 -> 2022 | K4: =Sales!P4 -> 2023 | ... N4: =Sales!S4 -> 2026
B5: Sales | D5: =Sales!I160 -> 742803 | E5: =Sales!J160 -> 1185356 | F5: =Sales!K160 -> 1323114 | G5: =Sales!L160 -> 910585 | H5: =Sales!M160 -> 910585 | I5: =Sales!N160 -> 1821170 | J5: =Sales!O160 -> 1902459 | K5: =Sales!P160 -> 2256380 | ... N5: =Sales!S160 -> 3792952.9
C6: %YoY | E6: =E5/D5-1 -> 0.59578785 | F6: =F5/E5-1 -> 0.11621656 | G6: =G5/F5-1 -> -0.31178644 | H6: =H5/G5-1 -> 0 | I6: =I5/H5-1 -> 1 | J6: =J5/I5-1 -> 0.044635601 | K6: =K5/J5-1 -> 0.18603344 | L6: =L5/K5-1 -> 0.18757189 | ... N6: =N5/M5-1 -> 0.19044206
B7: Cost | D7: =Cost!E57 -> 732137.26 | E7: =Cost!F57 -> 1156150.8 | F7: =Cost!G57 -> 1285415.4 | G7: =Cost!H57 -> 872106.02 | H7: =Cost!I57 -> 872106.02 | I7: =Cost!J57 -> 1744212 | J7: =Cost!K57 -> 1786540 | K7: =Cost!L57 -> 2111660.9 | ... N7: =Cost!O57 -> 3536128.4
C8: % of Sales | D8: =D7/D$5 -> 0.98564123 | E8: =E7/E$5 -> 0.97536167 | F8: =F7/F$5 -> 0.97150766 | G8: =G7/G$5 -> 0.95774258 | H8: =H7/H$5 -> 0.95774258 | I8: =I7/I$5 -> 0.95774258 | J8: =J7/J$5 -> 0.93906886 | K8: =K7/K$5 -> 0.93586227 | ... N8: =N7/N$5 -> 0.93228901
B9: EBIT | D9: =D5-D7 -> 10665.739 | E9: =E5-E7 -> 29205.187 | F9: =F5-F7 -> 37698.611 | G9: =G5-G7 -> 38478.975 | H9: =H5-H7 -> 38478.975 | I9: =I5-I7 -> 76957.95 | J9: =J5-J7 -> 115919 | K9: =K5-K7 -> 144719.1 | ... N9: =N5-N7 -> 256824.59
C10: % of Sales | D10: =D9/D$5 -> 0.014358772 | E10: =E9/E$5 -> 0.024638326 | F10: =F9/F$5 -> 0.028492338 | G10: =G9/G$5 -> 0.042257423 | H10: =H9/H$5 -> 0.042257423 | I10: =I9/I$5 -> 0.042257423 | J10: =J9/J$5 -> 0.060931142 | K10: =K9/K$5 -> 0.064137735 | ... N10: =N9/N$5 -> 0.067710987
B11: D&A | D11: =D12+D13 -> 7432.3771 | E11: =E12+E13 -> 13537.456 | F11: =F12+F13 -> 15873.972 | G11: =G12+G13 -> 19724.316 | H11: =H12+H13 -> 19724.316 | I11: =I12+I13 -> 39448.632 | J11: =J12+J13 -> 33669.772 | K11: =K12+K13 -> 30919.503 | ... N11: =N12+N13 -> 25746.402
C12: Depreciation | D12: ='CapEx,D&A'!F9 -> 6680.6336 | E12: ='CapEx,D&A'!G9 -> 12256.755 | F12: ='CapEx,D&A'!H9 -> 14214.472 | G12: ='CapEx,D&A'!I9 -> 18802.028 | H12: ='CapEx,D&A'!J9 -> 18802.028 | I12: ='CapEx,D&A'!K9 -> 37604.056 | J12: ='CapEx,D&A'!L9 -> 32110.436 | K12: ='CapEx,D&A'!M9 -> 29350.294 | ... N12: ='CapEx,D&A'!P9 -> 24142.297
C13: Amortizaton | D13: ='CapEx,D&A'!F10 -> 751.74352 | E13: ='CapEx,D&A'!G10 -> 1280.7009 | F13: ='CapEx,D&A'!H10 -> 1659.4994 | G13: ='CapEx,D&A'!I10 -> 922.28807 | H13: ='CapEx,D&A'!J10 -> 922.28807 | I13: ='CapEx,D&A'!K10 -> 1844.5761 | J13: ='CapEx,D&A'!L10 -> 1559.336 | K13: ='CapEx,D&A'!M10 -> 1569.2089 | ... N13: ='CapEx,D&A'!P10 -> 1604.1048
B14: EBITDA | D14: =D9+D11 -> 18098.116 | E14: =E9+E11 -> 42742.643 | F14: =F9+F11 -> 53572.583 | G14: =G9+G11 -> 58203.291 | H14: =H9+H11 -> 58203.291 | I14: =I9+I11 -> 116406.58 | J14: =J9+J11 -> 149588.77 | K14: =K9+K11 -> 175638.61 | ... N14: =N9+N11 -> 282570.99
C15: % of Sales | D15: =D14/D$5 -> 0.024364624 | E15: =E14/E$5 -> 0.036058908 | F15: =F14/F$5 -> 0.040489771 | G15: =G14/G$5 -> 0.06391857 | H15: =H14/H$5 -> 0.06391857 | I15: =I14/I$5 -> 0.06391857 | J15: =J14/J$5 -> 0.07862917 | K15: =K14/K$5 -> 0.07784088 | ... N15: =N14/N$5 -> 0.074498944
B16: Tax | D16: =D9*D17 -> 2346.4626 | E16: =E9*E17 -> 7067.6553 | F16: =F9*F17 -> 9123.0639 | G16: =G9*G17 -> 9311.912 | H16: =H9*H17 -> 9311.912 | I16: =I9*I17 -> 18623.824 | J16: =J9*J17 -> 28052.398 | K16: =K9*K17 -> 35022.023 | ... N16: =N9*N17 -> 62151.55
C17: Marginal tax rate | D17: =IF(D9<=200, 11%, IF(D9<=20000, 22%, IF(D9<300000, 24.2%, 27.5%))) -> 0.22 | E17: =IF(E9<=200, 11%, IF(E9<=20000, 22%, IF(E9<300000, 24.2%, 27.5%))) -> 0.242 | F17: =IF(F9<=200, 11%, IF(F9<=20000, 22%, IF(F9<300000, 24.2%, 27.5%))) -> 0.242 | G17: =IF(G9<=200, 11%, IF(G9<=20000, 22%, IF(G9<300000, 24.2%, 27.5%))) -> 0.242 | H17: =IF(H9<=200, 11%, IF(H9<=20000, 22%, IF(H9<300000, 24.2%, 27.5%))) -> 0.242 | I17: =IF(I9<=200, 11%, IF(I9<=20000, 22%, IF(I9<300000, 24.2%, 27.5%))) -> 0.242 | J17: =IF(J9<=200, 11%, IF(J9<=20000, 22%, IF(J9<300000, 24.2%, 27.5%))) -> 0.242 | K17: =IF(K9<=200, 11%, IF(K9<=20000, 22%, IF(K9<300000, 24.2%, 27.5%))) -> 0.242 | ... N17: =IF(N9<=200, 11%, IF(N9<=20000, 22%, IF(N9<300000, 24.2%, 27.5%))) -> 0.242
B18: EBIT(1-t) | D18: =D9-D16 -> 8319.2763 | E18: =E9-E16 -> 22137.532 | F18: =F9-F16 -> 28575.547 | G18: =G9-G16 -> 29167.063 | H18: =H9-H16 -> 29167.063 | I18: =I9-I16 -> 58334.126 | J18: =J9-J16 -> 87866.603 | K18: =K9-K16 -> 109697.08 | ... N18: =N9-N16 -> 194673.04
C19: % of Sales | D19: =D18/D$5 -> 0.011199842 | E19: =E18/E$5 -> 0.018675851 | F19: =F18/F$5 -> 0.021597192 | G19: =G18/G$5 -> 0.032031126 | H19: =H18/H$5 -> 0.032031126 | I19: =I18/I$5 -> 0.032031126 | J19: =J18/J$5 -> 0.046185806 | K19: =K18/K$5 -> 0.048616403 | ... N19: =N18/N$5 -> 0.051324928
C20: (+) D&A | D20: =D11 -> 7432.3771 | E20: =E11 -> 13537.456 | F20: =F11 -> 15873.972 | G20: =G11 -> 19724.316 | H20: =H11 -> 19724.316 | I20: =I11 -> 39448.632 | J20: =J11 -> 33669.772 | K20: =K11 -> 30919.503 | ... N20: =N11 -> 25746.402
C21: (-) CapEx | D21: ='CapEx,D&A'!F5 -> 6203.4207 | E21: ='CapEx,D&A'!G5 -> 4496.4141 | F21: ='CapEx,D&A'!H5 -> 2238.3799 | G21: ='CapEx,D&A'!I5 -> 2044.2493 | H21: ='CapEx,D&A'!J5 -> 2044.2493 | I21: ='CapEx,D&A'!K5 -> 4088.4986 | J21: ='CapEx,D&A'!L5 -> 4256.2992 | K21: ='CapEx,D&A'!M5 -> 4469.1141 | ... N21: ='CapEx,D&A'!P5 -> 5173.5582
C22: (-) △NWC | E22: =NWC!F22 -> 22572.179 | F22: =NWC!G22 -> 8513.7289 | G22: =NWC!H22 -> -6672.7502 | H22: =NWC!I22 -> 0 | I22: =NWC!J22 -> -6672.7502 | J22: =NWC!K22 -> 70631.837 | K22: =NWC!L22 -> 22812.933 | L22: =NWC!M22 -> 44703.84 | ... N22: =NWC!O22 -> 64265.799
B23: FCFF | D23: =D18+D20-D21-D22 -> 9548.2327 | E23: =E18+E20-E21-E22 -> 8606.395 | F23: =F18+F20-F21-F22 -> 33697.41 | G23: =G18+G20-G21-G22 -> 53519.88 | H23: =H18+H20-H21-H22 -> 46847.13 | I23: =I18+I20-I21-I22 -> 100367.01 | J23: =J18+J20-J21-J22 -> 46648.239 | K23: =K18+K20-K21-K22 -> 113334.54 | ... N23: =N18+N20-N21-N22 -> 150980.08
C24: Partial Period Factor | H24: 0.5 | J24: 1 | K24: 1 | L24: 1 | M24: 1 | N24: 1
C25: Mid-year convention | H25: =H24/2 -> 0.25 | J25: =SUM($H$24:I24)+J24/2 -> 1 | K25: =SUM($H$24:J24)+K24/2 -> 2 | L25: =SUM($H$24:K24)+L24/2 -> 3 | M25: =SUM($H$24:L24)+M24/2 -> 4 | N25: =SUM($H$24:M24)+N24/2 -> 5
C26: Present value factor | H26: =1/(1+$E$29)^H25 -> 0.97645409 | J26: =1/(1+$E$29)^J25 -> 0.90909091 | K26: =1/(1+$E$29)^K25 -> 0.82644628 | L26: =1/(1+$E$29)^L25 -> 0.7513148 | M26: =1/(1+$E$29)^M25 -> 0.68301346 | N26: =1/(1+$E$29)^N25 -> 0.62092132
B27: Discounted FCFF | H27: =H23*H26 -> 45744.071 | J27: =J23*J26 -> 42407.49 | K27: =K23*K26 -> 93664.906 | L27: =L23*L26 -> 85320.773 | M27: =M23*M26 -> 89196.319 | N27: =N23*N26 -> 93746.752
B29: WACC | E29: 0.1
B30: Terminal growth rate | E30: 0.02
B32: Equity value | G32: Sensitivity Analysis
B33: KRW in millions | I33: WACC
B34: Present Values of Free Cash Flow | E34: =SUM(H27:N27) -> 450080.31 | H34: =E43 -> 38115.011 | I34: 0.08 | J34: 0.09 | K34: 0.1 | L34: 0.11 | M34: 0.12
B35: Terminal Values | E35: =N18/(E29-E30)*N26 -> 1510958 | H35: 0.01 | I35: 46793.795 | J35: 39882.807 | K35: 34534.197 | L35: 30277.91 | M35: 26814.902
B36: Operating Business Value | E36: =E34+E35 -> 1961038.3 | G36: Terminal | H36: 0.015 | I36: 49899.195 | J36: 42131.675 | K36: 36219.286 | L36: 31574.819 | M36: 27834.845
B37: Plus: Non-operating Assets | G37: growth ratio | H37: 0.02 | I37: 53522.162 | J37: 44701.811 | K37: 38115.011 | L37: 33015.828 | M37: 28956.781
B38: Less: Net debt | E38: =BS!H24+BS!H26+BS!H28+BS!H31+BS!H34-BS!H6-BS!H8 -> 174040.05 | H38: 0.025 | I38: 57803.85 | J38: 47667.351 | K38: 40263.5 | L38: 34626.367 | M38: 30196.817
B39: Equity value | E39: =E36+E37-E38 -> 1786998.3 | H39: 0.03 | I39: 62941.876 | J39: 51127.148 | K39: 42718.916 | L39: 36438.224 | M39: 31574.633
B40: 유통주식수(주) | E40: =E41-E42 -> 46884369
C41: 총발행주식수(주) | E41: 46884369
C42: 자기주식수(주) | E42: 0
B43: per share(KRW) | E43: =(E39*10^6/E40) -> 38115.011

Sheet Sales
B1: Sales_bottom up | I1: Index
I3: Historical | N3: Forecast
B4: KRW in millions | I4: 2018 | J4: 2019 | K4: 2020 | L4: 2021.1H | M4: 2021.2H | N4: 2021 | O4: 2022 | P4: =O4+1 -> 2023 | Q4: =P4+1 -> 2024 | R4: =Q4+1 -> 2025 | S4: =R4+1 -> 2026
B5: 중고차 | I5: =I8+I74 -> 674404 | J5: =J8+J74 -> 1070801 | K5: =K8+K74 -> 1184650 | L5: =L8+L74 -> 792061 | M5: =M8+M74 -> 792061 | N5: =N8+N74 -> 1584122 | O5: =O8+O74 -> 1630322.7 | P5: =P8+P74 -> 1930634.3 | ... S5: =S8+S74 -> 3233329.1
C6: % YoY | J6: =J5/(I5/9*12)-1 -> 0.19083035 | K6: =K5/J5-1 -> 0.10632134 | L6: =(L5*2)/K5-1 -> 0.33720677 | M6: =L6 -> 0.33720677 | N6: =N5/K5-1 -> 0.33720677 | O6: =O5/N5-1 -> 0.029164866 | P6: =P5/O5-1 -> 0.18420375 | Q6: =Q5/P5-1 -> 0.18592203 | R6: =R5/Q5-1 -> 0.18756954 | S6: =S5/R5-1 -> 0.18914471
C7: 중고차 판매대수 | I7: =I10+I76 -> 52196 | J7: =J10+J76 -> 84328 | K7: =K10+K76 -> 90149 | L7: =L10+L76 -> 54426 | M7: =M10+M76 -> 54426 | N7: =N10+N76 -> 108852 | O7: =O10+O76 -> 111343.67 | P7: =P10+P76 -> 131007.24 | ... S7: =S10+S76 -> 215003.75
C8: 이커머스 중고차판매 | I8: =I11+I20+I29+I38+I47+I56+I65 -> 155662 | J8: =J11+J20+J29+J38+J47+J56+J65 -> 284782 | K8: =K11+K20+K29+K38+K47+K56+K65 -> 408225 | L8: =L11+L20+L29+L38+L47+L56+L65 -> 322919 | M8: =M11+M20+M29+M38+M47+M56+M65 -> 322919 | N8: =N11+N20+N29+N38+N47+N56+N65 -> 645838 | O8: =O11+O20+O29+O38+O47+O56+O65 -> 645658.78 | P8: =P11+P20+P29+P38+P47+P56+P65 -> 737221.59 | ... S8: =S11+S20+S29+S38+S47+S56+S65 -> 1108624.7
D9: % YoY | J9: =J8/(I8/9*12)-1 -> 0.37211715 | K9: =K8/J8-1 -> 0.4334649 | L9: =(L8*2)/K8-1 -> 0.58206381 | M9: =L9 -> 0.58206381 | N9: =N8/K8-1 -> 0.58206381 | O9: =O8/N8-1 -> -0.00027750151 | P9: =P8/O8-1 -> 0.141813 | Q9: =Q8/P8-1 -> 0.14370707 | R9: =R8/Q8-1 -> 0.14566007 | S9: =S8/R8-1 -> 0.14766708
D10: 이커머스 판매대수 | I10: =I15+I24+I33+I42+I51+I60+I69 -> 12700 | J10: =J15+J24+J33+J42+J51+J60+J69 -> 22554 | K10: =K15+K24+K33+K42+K51+K60+K69 -> 31274 | L10: =L15+L24+L33+L42+L51+L60+L69 -> 22920 | M10: =M15+M24+M33+M42+M51+M60+M69 -> 22920 | N10: =N15+N24+N33+N42+N51+N60+N69 -> 45840 | O10: =O15+O24+O33+O42+O51+O60+O69 -> 45871.669 | P10: =P15+P24+P33+P42+P51+P60+P69 -> 52440.838 | ... S10: =S15+S24+S33+S42+S51+S60+S69 -> 79241.014
D11: SUV(이커머스) | I11: =I15*I13/1000 -> 41558 | J11: =J15*J13/1000 -> 81857 | K11: =K15*K13/1000 -> 120580 | L11: =L15*L13/1000 -> 98632 | M11: =M15*M13/1000 -> 98632 | N11: =N15*N13/1000 -> 197264 | O11: =O15*O13/1000 -> 192195.55 | P11: =P15*P13/1000 -> 213529.26 | ... S11: =S15*S13/1000 -> 292819.22
E12: % YoY | J12: =J11/(I11/9*12)-1 -> 0.47727874 | K12: =K11/J11-1 -> 0.47305667 | L12: =(L11*2)/K11-1 -> 0.63595953 | M12: =L12 -> 0.63595953 | N12: =N11/K11-1 -> 0.63595953 | O12: =O11/N11-1 -> -0.025693717 | P12: =P11/O11-1 -> 0.111 | Q12: =Q11/P11-1 -> 0.111 | R12: =R11/Q11-1 -> 0.111 | S12: =S11/R11-1 -> 0.111
E13: 가격(천원) | I13: ='Dart_중고차 Sales'!D47 -> 15767.147 | J13: ='Dart_중고차 Sales'!E47 -> 15772.841 | K13: ='Dart_중고차 Sales'!F47 -> 16122.497 | L13: ='Dart_중고차 Sales'!G47 -> 17629.367 | M13: =L13 -> 17629.367 | N13: =M13 -> 17629.367 | O13: =(1+Control!J15)*N13 -> 17805.661 | P13: =(1+Control!K15)*O13 -> 17983.717 | Q13: =(1+Control!L15)*P13 -> 18163.554 | R13: =(1+Control!M15)*Q13 -> 18345.19 | S13: =(1+Control!N15)*R13 -> 18528.642
F14: % YoY | J14: =J13/(I13)-1 -> 0.00036115145 | K14: =K13/J13-1 -> 0.022168189 | L14: =(L13)/K13-1 -> 0.093463827 | M14: =L14 -> 0.093463827 | N14: =N13/K13-1 -> 0.093463827 | O14: =O13/N13-1 -> 0.01 | P14: =P13/O13-1 -> 0.01 | Q14: =Q13/P13-1 -> 0.01 | R14: =R13/Q13-1 -> 0.01 | S14: =S13/R13-1 -> 0.01
E15: 판매대수(대) | I15: ='Dart_중고차 Sales'!D36 -> 2635.7336 | J15: ='Dart_중고차 Sales'!E36 -> 5189.7434 | K15: ='Dart_중고차 Sales'!F36 -> 7478.9905 | L15: ='Dart_중고차 Sales'!G36 -> 5594.7556 | M15: =L15 -> 5594.7556 | N15: =L15+M15 -> 11189.511 | O15: =O17*O19 -> 10794.07 | P15: =P17*P19 -> 11873.477 | Q15: =Q17*Q19 -> 13060.825 | R15: =R17*R19 -> 14366.908 | S15: =S17*S19 -> 15803.598
F16: % YoY | J16: =J15/(I15/9*12)-1 -> 0.47674541 | K16: =K15/J15-1 -> 0.44110988 | L16: =(L15*2)/K15-1 -> 0.49612588 | M16: =L16 -> 0.49612588 | N16: =N15/K15-1 -> 0.49612588 | O16: =O15/N15-1 -> -0.035340314 | P16: =P15/O15-1 -> 0.1 | Q16: =Q15/P15-1 -> 0.1 | R16: =R15/Q15-1 -> 0.1 | S16: =S15/R15-1 -> 0.1
G17: 시장판매대수(대) | I17: =I15/I19 -> 3528.1474 | J17: =J15/J19 -> 5522.4724 | K17: =K15/K19 -> 9565.7613 | L17: =L15/L19 -> 8177.326 | M17: =M15/M19 -> 8177.326 | N17: =L17+M17 -> 16354.652 | O17: =(1+Control!J16)*N17 -> 17990.117 | P17: =(1+Control!K16)*O17 -> 19789.129 | Q17: =(1+Control!L16)*P17 -> 21768.042 | R17: =(1+Control!M16)*Q17 -> 23944.846 | S17: =(1+Control!N16)*R17 -> 26339.331
H18: % YoY | J18: =J17/I17-1 -> 0.56526125 | K18: =K17/J17-1 -> 0.73215196 | L18: =(L17*2)/K17-1 -> 0.70970731 | M18: =L18 -> 0.70970731 | N18: =N17/K17-1 -> 0.70970731 | O18: =O17/N17-1 -> 0.1 | P18: =P17/O17-1 -> 0.1 | Q18: =Q17/P17-1 -> 0.1 | R18: =R17/Q17-1 -> 0.1 | S18: =S17/R17-1 -> 0.1
G19: 점유율 | I19: =Dart_시장리서치!F$43 -> 0.74705882 | J19: =Dart_시장리서치!G$43 -> 0.93975 | K19: =Dart_시장리서치!H$43 -> 0.78185 | L19: =Dart_시장리서치!I$43 -> 0.6841791 | M19: =L19 -> 0.6841791 | N19: =M19 -> 0.6841791 | O19: =Control!J17 -> 0.6 | P19: =Control!K17 -> 0.6 | Q19: =Control!L17 -> 0.6 | R19: =Control!M17 -> 0.6 | S19: =Control!N17 -> 0.6
D20: 대형(이커머스) | I20: =I24*I22/1000 -> 32669 | J20: =J24*J22/1000 -> 59689 | K20: =K24*K22/1000 -> 82519 | L20: =L24*L22/1000 -> 68474 | M20: =M24*M22/1000 -> 68474 | N20: =N24*N22/1000 -> 136948 | O20: =O24*O22/1000 -> 133429.3 | P20: =P24*P22/1000 -> 148239.95 | ... S20: =S24*S22/1000 -> 203285.98
E21: % YoY | J21: =J20/(I20/9*12)-1 -> 0.37031283 | K21: =K20/J20-1 -> 0.38248253 | L21: =(L20*2)/K20-1 -> 0.65959355 | M21: =L21 -> 0.65959355 | N21: =N20/K20-1 -> 0.65959355 | O21: =O20/N20-1 -> -0.025693717 | P21: =P20/O20-1 -> 0.111 | Q21: =Q20/P20-1 -> 0.111 | R21: =R20/Q20-1 -> 0.111 | S21: =S20/R20-1 -> 0.111
E22: 가격(천원) | I22: ='Dart_중고차 Sales'!D48 -> 17143.606 | J22: ='Dart_중고차 Sales'!E48 -> 17814.302 | K22: ='Dart_중고차 Sales'!F48 -> 18333.616 | L22: ='Dart_중고차 Sales'!G48 -> 19158.988 | M22: =L22 -> 19158.988 | N22: =M22 -> 19158.988 | O22: =(1+Control!J18)*N22 -> 19350.578 | P22: =(1+Control!K18)*O22 -> 19544.084 | Q22: =(1+Control!L18)*P22 -> 19739.525 | R22: =(1+Control!M18)*Q22 -> 19936.92 | S22: =(1+Control!N18)*R22 -> 20136.289
F23: % YoY | J23: =J22/(I22)-1 -> 0.039122183 | K23: =K22/J22-1 -> 0.029151541 | L23: =(L22)/K22-1 -> 0.045019596 | M23: =L23 -> 0.045019596 | N23: =N22/K22-1 -> 0.045019596 | O23: =O22/N22-1 -> 0.01 | P23: =P22/O22-1 -> 0.01 | Q23: =Q22/P22-1 -> 0.01 | R23: =R22/Q22-1 -> 0.01 | S23: =S22/R22-1 -> 0.01
E24: 판매대수(대) | I24: ='Dart_중고차 Sales'!D37 -> 1905.6084 | J24: ='Dart_중고차 Sales'!E37 -> 3350.6225 | K24: ='Dart_중고차 Sales'!F37 -> 4500.9669 | L24: ='Dart_중고차 Sales'!G37 -> 3573.9883 | M24: =L24 -> 3573.9883 | N24: =L24+M24 -> 7147.9767 | O24: =O26*O28 -> 6895.3649 | P24: =P26*P28 -> 7584.9014 | Q24: =Q26*Q28 -> 8343.3916 | R24: =R26*R28 -> 9177.7307 | S24: =S26*S28 -> 10095.504
F25: % YoY | J25: =J24/(I24/9*12)-1 -> 0.31872157 | K25: =K24/J24-1 -> 0.34332261 | L25: =(L24*2)/K24-1 -> 0.58809802 | M25: =L25 -> 0.58809802 | N25: =N24/K24-1 -> 0.58809802 | O25: =O24/N24-1 -> -0.035340314 | P25: =P24/O24-1 -> 0.1 | Q25: =Q24/P24-1 -> 0.1 | R25: =R24/Q24-1 -> 0.1 | S25: =S24/R24-1 -> 0.1
G26: 시장판매대수(대) | I26: =I24/I28 -> 2550.8144 | J26: =J24/J28 -> 3565.4403 | K26: =K24/K28 -> 5756.8165 | L26: =L24/L28 -> 5223.7613 | M26: =M24/M28 -> 5223.7613 | N26: =L26+M26 -> 10447.523 | O26: =(1+Control!J19)*N26 -> 11492.275 | P26: =(1+Control!K19)*O26 -> 12641.502 | Q26: =(1+Control!L19)*P26 -> 13905.653 | R26: =(1+Control!M19)*Q26 -> 15296.218 | S26: =(1+Control!N19)*R26 -> 16825.84
H27: % YoY | J27: =J26/I26-1 -> 0.39776548 | K27: =K26/J26-1 -> 0.61461588 | L27: =(L26*2)/K26-1 -> 0.81480906 | M27: =L27 -> 0.81480906 | N27: =N26/K26-1 -> 0.81480906 | O27: =O26/N26-1 -> 0.1 | P27: =P26/O26-1 -> 0.1 | Q27: =Q26/P26-1 -> 0.1 | R27: =R26/Q26-1 -> 0.1 | S27: =S26/R26-1 -> 0.1
G28: 점유율 | I28: =Dart_시장리서치!F$43 -> 0.74705882 | J28: =Dart_시장리서치!G$43 -> 0.93975 | K28: =Dart_시장리서치!H$43 -> 0.78185 | L28: =Dart_시장리서치!I$43 -> 0.6841791 | M28: =L28 -> 0.6841791 | N28: =M28 -> 0.6841791 | O28: =Control!J20 -> 0.6 | P28: =Control!K20 -> 0.6 | Q28: =Control!L20 -> 0.6 | R28: =Control!M20 -> 0.6 | S28: =Control!N20 -> 0.6
D29: 중형(이커머스) | I29: =I33*I31/1000 -> 31693 | J29: =J33*J31/1000 -> 55817 | K29: =K33*K31/1000 -> 82069 | L29: =L33*L31/1000 -> 63151 | M29: =M33*M31/1000 -> 63151 | N29: =N33*N31/1000 -> 126302 | O29: =O33*O31/1000 -> 123056.83 | P29: =P33*P31/1000 -> 136716.14 | ... S29: =S33*S31/1000 -> 187483.03
E30: % YoY | J30: =J29/(I29/9*12)-1 -> 0.32088316 | K30: =K29/J29-1 -> 0.47032266 | L30: =(L29*2)/K29-1 -> 0.5389733 | M30: =L30 -> 0.5389733 | N30: =N29/K29-1 -> 0.5389733 | O30: =O29/N29-1 -> -0.025693717 | P30: =P29/O29-1 -> 0.111 | Q30: =Q29/P29-1 -> 0.111 | R30: =R29/Q29-1 -> 0.111 | S30: =S29/R29-1 -> 0.111
E31: 가격(천원) | I31: ='Dart_중고차 Sales'!D49 -> 12395.723 | J31: ='Dart_중고차 Sales'!E49 -> 12891.131 | K31: ='Dart_중고차 Sales'!F49 -> 13679.935 | L31: ='Dart_중고차 Sales'!G49 -> 14570.125 | M31: =L31 -> 14570.125 | N31: =M31 -> 14570.125 | O31: =(1+Control!J21)*N31 -> 14715.826 | P31: =(1+Control!K21)*O31 -> 14862.984 | Q31: =(1+Control!L21)*P31 -> 15011.614 | R31: =(1+Control!M21)*Q31 -> 15161.73 | S31: =(1+Control!N21)*R31 -> 15313.348
F32: % YoY | J32: =J31/(I31)-1 -> 0.039966029 | K32: =K31/J31-1 -> 0.061189687 | L32: =(L31)/K31-1 -> 0.065072664 | M32: =L32 -> 0.065072664 | N32: =N31/K31-1 -> 0.065072664 | O32: =O31/N31-1 -> 0.01 | P32: =P31/O31-1 -> 0.01 | Q32: =Q31/P31-1 -> 0.01 | R32: =R31/Q31-1 -> 0.01 | S32: =S31/R31-1 -> 0.01
E33: 판매대수(대) | I33: ='Dart_중고차 Sales'!D38 -> 2556.769 | J33: ='Dart_중고차 Sales'!E38 -> 4329.8762 | K33: ='Dart_중고차 Sales'!F38 -> 5999.2244 | L33: ='Dart_중고차 Sales'!G38 -> 4334.28 | M33: =L33 -> 4334.28 | N33: =L33+M33 -> 8668.5599 | O33: =O35*O37 -> 8362.2103 | P33: =P35*P37 -> 9198.4313 | Q33: =Q35*Q37 -> 10118.274 | R33: =R35*R37 -> 11130.102 | S33: =S35*S37 -> 12243.112
F34: % YoY | J34: =J33/(I33/9*12)-1 -> 0.27012145 | K34: =K33/J33-1 -> 0.38554179 | L34: =(L33*2)/K33-1 -> 0.44494677 | M34: =L34 -> 0.44494677 | N34: =N33/K33-1 -> 0.44494677 | O34: =O33/N33-1 -> -0.035340314 | P34: =P33/O33-1 -> 0.1 | Q34: =Q33/P33-1 -> 0.1 | R34: =R33/Q33-1 -> 0.1 | S34: =S33/R33-1 -> 0.1
G35: 시장판매대수(대) | I35: =I33/I37 -> 3422.4467 | J35: =J33/J37 -> 4607.4766 | K35: =K33/K37 -> 7673.1143 | L35: =L33/L37 -> 6335.0078 | M35: =M33/M37 -> 6335.0078 | N35: =L35+M35 -> 12670.016 | O35: =(1+Control!J22)*N35 -> 13937.017 | P35: =(1+Control!K22)*O35 -> 15330.719 | Q35: =(1+Control!L22)*P35 -> 16863.791 | R35: =(1+Control!M22)*Q35 -> 18550.17 | S35: =(1+Control!N22)*R35 -> 20405.187
H36: % YoY | J36: =J35/I35-1 -> 0.34625228 | K36: =K35/J35-1 -> 0.66536151 | L36: =(L35*2)/K35-1 -> 0.65122206 | M36: =L36 -> 0.65122206 | N36: =N35/K35-1 -> 0.65122206 | O36: =O35/N35-1 -> 0.1 | P36: =P35/O35-1 -> 0.1 | Q36: =Q35/P35-1 -> 0.1 | R36: =R35/Q35-1 -> 0.1 | S36: =S35/R35-1 -> 0.1
G37: 점유율 | I37: =Dart_시장리서치!F$43 -> 0.74705882 | J37: =Dart_시장리서치!G$43 -> 0.93975 | K37: =Dart_시장리서치!H$43 -> 0.78185 | L37: =Dart_시장리서치!I$43 -> 0.6841791 | M37: =L37 -> 0.6841791 | N37: =M37 -> 0.6841791 | O37: =Control!J23 -> 0.6 | P37: =Control!K23 -> 0.6 | Q37: =Control!L23 -> 0.6 | R37: =Control!M23 -> 0.6 | S37: =Control!N23 -> 0.6
D38: 준중형(이커머스) | I38: =I42*I40/1000 -> 21892 | J38: =J42*J40/1000 -> 35300 | K38: =K42*K40/1000 -> 51859 | L38: =L42*L40/1000 -> 37193 | M38: =M42*M40/1000 -> 37193 | N38: =N42*N40/1000 -> 74386 | O38: =O42*O40/1000 -> 79063.361 | P38: =P42*P40/1000 -> 95824.793 | ... S38: =S42*S40/1000 -> 170602.64
E39: % YoY | J39: =J38/(I38/9*12)-1 -> 0.20934588 | K39: =K38/J38-1 -> 0.46909348 | L39: =(L38*2)/K38-1 -> 0.4343894 | M39: =L39 -> 0.4343894 | N39: =N38/K38-1 -> 0.4343894 | O39: =O38/N38-1 -> 0.062879581 | P39: =P38/O38-1 -> 0.212 | Q39: =Q38/P38-1 -> 0.212 | R39: =R38/Q38-1 -> 0.212 | S39: =S38/R38-1 -> 0.212
E40: 가격(천원) | I40: ='Dart_중고차 Sales'!D50 -> 8863.9807 | J40: ='Dart_중고차 Sales'!E50 -> 9073.7094 | K40: ='Dart_중고차 Sales'!F50 -> 9386.8273 | L40: ='Dart_중고차 Sales'!G50 -> 10130.351 | M40: =L40 -> 10130.351 | N40: =M40 -> 10130.351 | O40: =(1+Control!J24)*N40 -> 10231.655 | P40: =(1+Control!K24)*O40 -> 10333.971 | Q40: =(1+Control!L24)*P40 -> 10437.311 | R40: =(1+Control!M24)*Q40 -> 10541.684 | S40: =(1+Control!N24)*R40 -> 10647.101
F41: % YoY | J41: =J40/(I40)-1 -> 0.023660782 | K41: =K40/J40-1 -> 0.034508264 | L41: =(L40)/K40-1 -> 0.07920929 | M41: =L41 -> 0.07920929 | N41: =N40/K40-1 -> 0.07920929 | O41: =O40/N40-1 -> 0.01 | P41: =P40/O40-1 -> 0.01 | Q41: =Q40/P40-1 -> 0.01 | R41: =R40/Q40-1 -> 0.01 | S41: =S40/R40-1 -> 0.01
E42: 판매대수(대) | I42: ='Dart_중고차 Sales'!D39 -> 2469.7707 | J42: ='Dart_중고차 Sales'!E39 -> 3890.3604 | K42: ='Dart_중고차 Sales'!F39 -> 5524.6569 | L42: ='Dart_중고차 Sales'!G39 -> 3671.4423 | M42: =L42 -> 3671.4423 | N42: =L42+M42 -> 7342.8846 | O42: =O44*O46 -> 7727.3288 | P42: =P44*P46 -> 9272.7946 | Q42: =Q44*Q46 -> 11127.353 | R42: =R44*R46 -> 13352.824 | S42: =S44*S46 -> 16023.389
F43: % YoY | J43: =J42/(I42/9*12)-1 -> 0.18139319 | K43: =K42/J42-1 -> 0.42008869 | L43: =(L42*2)/K42-1 -> 0.32911143 | M43: =L43 -> 0.32911143 | N43: =N42/K42-1 -> 0.32911143 | O43: =O42/N42-1 -> 0.052356021 | P43: =P42/O42-1 -> 0.2 | Q43: =Q42/P42-1 -> 0.2 | R43: =R42/Q42-1 -> 0.2 | S43: =S42/R42-1 -> 0.2
G44: 시장판매대수(대) | I44: =I42/I46 -> 3305.9923 | J44: =J42/J46 -> 4139.7823 | K44: =K42/K46 -> 7066.134 | L44: =L42/L46 -> 5366.2006 | M44: =M42/M46 -> 5366.2006 | N44: =L44+M44 -> 10732.401 | O44: =(1+Control!J25)*N44 -> 12878.881 | P44: =(1+Control!K25)*O44 -> 15454.658 | Q44: =(1+Control!L25)*P44 -> 18545.589 | R44: =(1+Control!M25)*Q44 -> 22254.707 | S44: =(1+Control!N25)*R44 -> 26705.648
H45: % YoY | J45: =J44/I44-1 -> 0.25220567 | K45: =K44/J44-1 -> 0.70688539 | L45: =(L44*2)/K44-1 -> 0.51885049 | M45: =L45 -> 0.51885049 | N45: =N44/K44-1 -> 0.51885049 | O45: =O44/N44-1 -> 0.2 | P45: =P44/O44-1 -> 0.2 | Q45: =Q44/P44-1 -> 0.2 | R45: =R44/Q44-1 -> 0.2 | S45: =S44/R44-1 -> 0.2
G46: 점유율 | I46: =Dart_시장리서치!F$43 -> 0.74705882 | J46: =Dart_시장리서치!G$43 -> 0.93975 | K46: =Dart_시장리서치!H$43 -> 0.78185 | L46: =Dart_시장리서치!I$43 -> 0.6841791 | M46: =L46 -> 0.6841791 | N46: =M46 -> 0.6841791 | O46: =Control!J26 -> 0.6 | P46: =Control!K26 -> 0.6 | Q46: =Control!L26 -> 0.6 | R46: =Control!M26 -> 0.6 | S46: =Control!N26 -> 0.6
D47: 소형(이커머스) | I47: =I51*I49/1000 -> 3952 | J47: =J51*J49/1000 -> 6395 | K47: =K51*K49/1000 -> 9960 | L47: =L51*L49/1000 -> 6434 | M47: =M51*M49/1000 -> 6434 | N47: =N51*N49/1000 -> 12868 | O47: =O51*O49/1000 -> 13677.134 | P47: =P51*P49/1000 -> 16576.687 | ... S47: =S51*S49/1000 -> 29512.473
E48: % YoY | J48: =J47/(I47/9*12)-1 -> 0.21362601 | K48: =K47/J47-1 -> 0.55746677 | L48: =(L47*2)/K47-1 -> 0.29196787 | M48: =L48 -> 0.29196787 | N48: =N47/K47-1 -> 0.29196787 | O48: =O47/N47-1 -> 0.062879581 | P48: =P47/O47-1 -> 0.212 | Q48: =Q47/P47-1 -> 0.212 | R48: =R47/Q47-1 -> 0.212 | S48: =S47/R47-1 -> 0.212
E49: 가격(천원) | I49: ='Dart_중고차 Sales'!D51 -> 9565.0168 | J49: ='Dart_중고차 Sales'!E51 -> 9945.7799 | K49: ='Dart_중고차 Sales'!F51 -> 10748.662 | L49: ='Dart_중고차 Sales'!G51 -> 10132.287 | M49: =L49 -> 10132.287 | N49: =M49 -> 10132.287 | O49: =(1+Control!J27)*N49 -> 10233.61 | P49: =(1+Control!K27)*O49 -> 10335.946 | Q49: =(1+Control!L27)*P49 -> 10439.306 | R49: =(1+Control!M27)*Q49 -> 10543.699 | S49: =(1+Control!N27)*R49 -> 10649.136
F50: % YoY | J50: =J49/(I49)-1 -> 0.039807881 | K50: =K49/J49-1 -> 0.08072594 | L50: =(L49)/K49-1 -> -0.057344326 | M50: =L50 -> -0.057344326 | N50: =N49/K49-1 -> -0.057344326 | O50: =O49/N49-1 -> 0.01 | P50: =P49/O49-1 -> 0.01 | Q50: =Q49/P49-1 -> 0.01 | R50: =R49/Q49-1 -> 0.01 | S50: =S49/R49-1 -> 0.01
E51: 판매대수(대) | I51: ='Dart_중고차 Sales'!D40 -> 413.1723 | J51: ='Dart_중고차 Sales'!E40 -> 642.98628 | K51: ='Dart_중고차 Sales'!F40 -> 926.62694 | L51: ='Dart_중고차 Sales'!G40 -> 634.99975 | M51: =L51 -> 634.99975 | N51: =L51+M51 -> 1269.9995 | O51: =O53*O55 -> 1336.4916 | P51: =P53*P55 -> 1603.7899 | Q51: =Q53*Q55 -> 1924.5479 | R51: =R53*R55 -> 2309.4575 | S51: =S53*S55 -> 2771.349
F52: % YoY | J52: =J51/(I51/9*12)-1 -> 0.1671637 | K52: =K51/J51-1 -> 0.44113018 | L52: =(L51*2)/K51-1 -> 0.37056182 | M52: =L52 -> 0.37056182 | N52: =N51/K51-1 -> 0.37056182 | O52: =O51/N51-1 -> 0.052356021 | P52: =P51/O51-1 -> 0.2 | Q52: =Q51/P51-1 -> 0.2 | R52: =R51/Q51-1 -> 0.2 | S52: =S51/R51-1 -> 0.2
G53: 시장판매대수(대) | I53: =I51/I55 -> 553.06528 | J53: =J51/J55 -> 684.20993 | K53: =K51/K55 -> 1185.1723 | L53: =L51/L55 -> 928.11918 | M53: =M51/M55 -> 928.11918 | N53: =L53+M53 -> 1856.2384 | O53: =(1+Control!J28)*N53 -> 2227.486 | P53: =(1+Control!K28)*O53 -> 2672.9832 | Q53: =(1+Control!L28)*P53 -> 3207.5799 | R53: =(1+Control!M28)*Q53 -> 3849.0959 | S53: =(1+Control!N28)*R53 -> 4618.915
H54: % YoY | J54: =J53/I53-1 -> 0.23712326 | K54: =K53/J53-1 -> 0.73217636 | L54: =(L53*2)/K53-1 -> 0.56621819 | M54: =L54 -> 0.56621819 | N54: =N53/K53-1 -> 0.56621819 | O54: =O53/N53-1 -> 0.2 | P54: =P53/O53-1 -> 0.2 | Q54: =Q53/P53-1 -> 0.2 | R54: =R53/Q53-1 -> 0.2 | S54: =S53/R53-1 -> 0.2
G55: 점유율 | I55: =Dart_시장리서치!F$43 -> 0.74705882 | J55: =Dart_시장리서치!G$43 -> 0.93975 | K55: =Dart_시장리서치!H$43 -> 0.78185 | L55: =Dart_시장리서치!I$43 -> 0.6841791 | M55: =L55 -> 0.6841791 | N55: =M55 -> 0.6841791 | O55: =Control!J29 -> 0.6 | P55: =Control!K29 -> 0.6 | Q55: =Control!L29 -> 0.6 | R55: =Control!M29 -> 0.6 | S55: =Control!N29 -> 0.6
D56: 화물차(이커머스) | I56: =I60*I58/1000 -> 1642 | J56: =J60*J58/1000 -> 3174 | K56: =K60*K58/1000 -> 3633 | L56: =L60*L58/1000 -> 2012 | M56: =M60*M58/1000 -> 2012 | N56: =N60*N58/1000 -> 4024 | O56: =O60*O58/1000 -> 4277.0274 | P56: =P60*P58/1000 -> 5183.7573 | ... S56: =S60*S58/1000 -> 9228.9547
E57: % YoY | J57: =J56/(I56/9*12)-1 -> 0.44975639 | K57: =K56/J56-1 -> 0.14461248 | L57: =(L56*2)/K56-1 -> 0.10762455 | M57: =L57 -> 0.10762455 | N57: =N56/K56-1 -> 0.10762455 | O57: =O56/N56-1 -> 0.062879581 | P57: =P56/O56-1 -> 0.212 | Q57: =Q56/P56-1 -> 0.212 | R57: =R56/Q56-1 -> 0.212 | S57: =S56/R56-1 -> 0.212
E58: 가격(천원) | I58: ='Dart_중고차 Sales'!D52 -> 9323.1166 | J58: ='Dart_중고차 Sales'!E52 -> 9880.1508 | K58: ='Dart_중고차 Sales'!F52 -> 10431.795 | L58: ='Dart_중고차 Sales'!G52 -> 12445.113 | M58: =L58 -> 12445.113 | N58: =M58 -> 12445.113 | O58: =(1+Control!J30)*N58 -> 12569.564 | P58: =(1+Control!K30)*O58 -> 12695.26 | Q58: =(1+Control!L30)*P58 -> 12822.213 | R58: =(1+Control!M30)*Q58 -> 12950.435 | S58: =(1+Control!N30)*R58 -> 13079.939
F59: % YoY | J59: =J58/(I58)-1 -> 0.059747637 | K59: =K58/J58-1 -> 0.055833555 | L59: =(L58)/K58-1 -> 0.19299829 | M59: =L59 -> 0.19299829 | N59: =N58/K58-1 -> 0.19299829 | O59: =O58/N58-1 -> 0.01 | P59: =P58/O58-1 -> 0.01 | Q59: =Q58/P58-1 -> 0.01 | R59: =R58/Q58-1 -> 0.01 | S59: =S58/R58-1 -> 0.01
E60: 판매대수(대) | I60: ='Dart_중고차 Sales'!D41 -> 176.12136 | J60: ='Dart_중고차 Sales'!E41 -> 321.25016 | K60: ='Dart_중고차 Sales'!F41 -> 348.26222 | L60: ='Dart_중고차 Sales'!G41 -> 161.66988 | M60: =L60 -> 161.66988 | N60: =L60+M60 -> 323.33976 | O60: =O62*O64 -> 340.26855 | P60: =P62*P64 -> 408.32226 | Q60: =Q62*Q64 -> 489.98671 | R60: =R62*R64 -> 587.98405 | S60: =S62*S64 -> 705.58086
F61: % YoY | J61: =J60/(I60/9*12)-1 -> 0.36802041 | K61: =K60/J60-1 -> 0.084084202 | L61: =(L60*2)/K60-1 -> -0.071562326 | M61: =L61 -> -0.071562326 | N61: =N60/K60-1 -> -0.071562326 | O61: =O60/N60-1 -> 0.052356021 | P61: =P60/O60-1 -> 0.2 | Q61: =Q60/P60-1 -> 0.2 | R61: =R60/Q60-1 -> 0.2 | S61: =S60/R60-1 -> 0.2
G62: 시장판매대수(대) | I62: =I60/I64 -> 235.753 | J62: =J60/J64 -> 341.8464 | K62: =K60/K64 -> 445.43355 | L62: =L60/L64 -> 236.2976 | M62: =M60/M64 -> 236.2976 | N62: =L62+M62 -> 472.59521 | O62: =(1+Control!J31)*N62 -> 567.11425 | P62: =(1+Control!K31)*O62 -> 680.5371 | Q62: =(1+Control!L31)*P62 -> 816.64452 | R62: =(1+Control!M31)*Q62 -> 979.97342 | S62: =(1+Control!N31)*R62 -> 1175.9681
H63: % YoY | J63: =J62/I62-1 -> 0.45001928 | K63: =K62/J62-1 -> 0.30302248 | L63: =(L62*2)/K62-1 -> 0.060978025 | M63: =L63 -> 0.060978025 | N63: =N62/K62-1 -> 0.060978025 | O63: =O62/N62-1 -> 0.2 | P63: =P62/O62-1 -> 0.2 | Q63: =Q62/P62-1 -> 0.2 | R63: =R62/Q62-1 -> 0.2 | S63: =S62/R62-1 -> 0.2
G64: 점유율 | I64: =Dart_시장리서치!F$43 -> 0.74705882 | J64: =Dart_시장리서치!G$43 -> 0.93975 | K64: =Dart_시장리서치!H$43 -> 0.78185 | L64: =Dart_시장리서치!I$43 -> 0.6841791 | M64: =L64 -> 0.6841791 | N64: =M64 -> 0.6841791 | O64: =Control!J32 -> 0.6 | P64: =Control!K32 -> 0.6 | Q64: =Control!L32 -> 0.6 | R64: =Control!M32 -> 0.6 | S64: =Control!N32 -> 0.6
D65: 기타(이커머스) | I65: =I69*I67/1000 -> 22256 | J65: =J69*J67/1000 -> 42550 | K65: =K69*K67/1000 -> 57605 | L65: =L69*L67/1000 -> 47023 | M65: =M69*M67/1000 -> 47023 | N65: =N69*N67/1000 -> 94046 | O65: =O69*O67/1000 -> 99959.573 | P65: =P69*P67/1000 -> 121151 | ... S65: =S69*S67/1000 -> 215692.41
E66: % YoY | J66: =J65/(I65/9*12)-1 -> 0.433883 | K66: =K65/J65-1 -> 0.35381904 | L66: =(L65*2)/K65-1 -> 0.63260134 | M66: =L66 -> 0.63260134 | N66: =N65/K65-1 -> 0.63260134 | O66: =O65/N65-1 -> 0.062879581 | P66: =P65/O65-1 -> 0.212 | Q66: =Q65/P65-1 -> 0.212 | R66: =R65/Q65-1 -> 0.212 | S66: =S65/R65-1 -> 0.212
E67: 가격(천원) | I67: ='Dart_중고차 Sales'!D53 -> 8752.4715 | J67: ='Dart_중고차 Sales'!E53 -> 8811.0543 | K67: ='Dart_중고차 Sales'!F53 -> 8868.7585 | L67: ='Dart_중고차 Sales'!G53 -> 9501.7762 | M67: =L67 -> 9501.7762 | N67: =M67 -> 9501.7762 | O67: =(1+Control!J33)*N67 -> 9596.794 | P67: =(1+Control!K33)*O67 -> 9692.7619 | Q67: =(1+Control!L33)*P67 -> 9789.6895 | R67: =(1+Control!M33)*Q67 -> 9887.5864 | S67: =(1+Control!N33)*R67 -> 9986.4623
F68: % YoY | J68: =J67/(I67)-1 -> 0.006693278 | K68: =K67/J67-1 -> 0.0065490721 | L68: =(L67)/K67-1 -> 0.071376139 | M68: =L68 -> 0.071376139 | N68: =N67/K67-1 -> 0.071376139 | O68: =O67/N67-1 -> 0.01 | P68: =P67/O67-1 -> 0.01 | Q68: =Q67/P67-1 -> 0.01 | R68: =R67/Q67-1 -> 0.01 | S68: =S67/R67-1 -> 0.01
E69: 판매대수(대) | I69: ='Dart_중고차 Sales'!D42 -> 2542.8246 | J69: ='Dart_중고차 Sales'!E42 -> 4829.161 | K69: ='Dart_중고차 Sales'!F42 -> 6495.2721 | L69: ='Dart_중고차 Sales'!G42 -> 4948.8642 | M69: =L69 -> 4948.8642 | N69: =L69+M69 -> 9897.7284 | O69: =O71*O73 -> 10415.934 | P69: =P71*P73 -> 12499.121 | Q69: =Q71*Q73 -> 14998.945 | R69: =R71*R73 -> 17998.734 | S69: =S71*S73 -> 21598.481
F70: % YoY | J70: =J69/(I69/9*12)-1 -> 0.42434943 | K70: =K69/J69-1 -> 0.34501047 | L70: =(L69*2)/K69-1 -> 0.52383582 | M70: =L70 -> 0.52383582 | N70: =N69/K69-1 -> 0.52383582 | O70: =O69/N69-1 -> 0.052356021 | P70: =P69/O69-1 -> 0.2 | Q70: =Q69/P69-1 -> 0.2 | R70: =R69/Q69-1 -> 0.2 | S70: =S69/R69-1 -> 0.2
G71: 시장판매대수(대) | I71: =I69/I73 -> 3403.781 | J71: =J69/J73 -> 5138.7721 | K71: =K69/K73 -> 8307.5681 | L71: =L69/L73 -> 7233.2875 | M71: =M69/M73 -> 7233.2875 | N71: =L71+M71 -> 14466.575 | O71: =(1+Control!J34)*N71 -> 17359.89 | P71: =(1+Control!K34)*O71 -> 20831.868 | Q71: =(1+Control!L34)*P71 -> 24998.242 | R71: =(1+Control!M34)*Q71 -> 29997.89 | S71: =(1+Control!N34)*R71 -> 35997.468
H72: % YoY | J72: =J71/I71-1 -> 0.50972466 | K72: =K71/J71-1 -> 0.61664461 | L72: =(L71*2)/K71-1 -> 0.74137302 | M72: =L72 -> 0.74137302 | N72: =N71/K71-1 -> 0.74137302 | O72: =O71/N71-1 -> 0.2 | P72: =P71/O71-1 -> 0.2 | Q72: =Q71/P71-1 -> 0.2 | R72: =R71/Q71-1 -> 0.2 | S72: =S71/R71-1 -> 0.2
G73: 점유율 | I73: =Dart_시장리서치!F$43 -> 0.74705882 | J73: =Dart_시장리서치!G$43 -> 0.93975 | K73: =Dart_시장리서치!H$43 -> 0.78185 | L73: =Dart_시장리서치!I$43 -> 0.6841791 | M73: =L73 -> 0.6841791 | N73: =M73 -> 0.6841791 | O73: =Control!J35 -> 0.6 | P73: =Control!K35 -> 0.6 | Q73: =Control!L35 -> 0.6 | R73: =Control!M35 -> 0.6 | S73: =Control!N35 -> 0.6
C74: 지점내방 중고차 판매 | I74: =I77+I86+I95+I104+I113+I122+I131 -> 518742 | J74: =J77+J86+J95+J104+J113+J122+J131 -> 786019 | K74: =K77+K86+K95+K104+K113+K122+K131 -> 776425 | L74: =L77+L86+L95+L104+L113+L122+L131 -> 469142 | M74: =M77+M86+M95+M104+M113+M122+M131 -> 469142 | N74: =N77+N86+N95+N104+N113+N122+N131 -> 938284 | O74: =O77+O86+O95+O104+O113+O122+O131 -> 984663.93 | P74: =P77+P86+P95+P104+P113+P122+P131 -> 1193412.7 | ... S74: =S77+S86+S95+S104+S113+S122+S131 -> 2124704.4
D75: % YoY | J75: =J74/(I74/9*12)-1 -> 0.13643054 | K75: =K74/J74-1 -> -0.012205812 | L75: =(L74*2)/K74-1 -> 0.20846701 | M75: =L75 -> 0.20846701 | N75: =N74/K74-1 -> 0.20846701 | O75: =O74/N74-1 -> 0.049430585 | P75: =P74/O74-1 -> 0.212 | Q75: =Q74/P74-1 -> 0.212 | R75: =R74/Q74-1 -> 0.212 | S75: =S74/R74-1 -> 0.212
D76: 지점내방 판매대수 | I76: =I81+I90+I99+I108+I117+I126+I135 -> 39496 | J76: =J81+J90+J99+J108+J117+J126+J135 -> 61774 | K76: =K81+K90+K99+K108+K117+K126+K135 -> 58875 | L76: =L81+L90+L99+L108+L117+L126+L135 -> 31506 | M76: =M81+M90+M99+M108+M117+M126+M135 -> 31506 | N76: =N81+N90+N99+N108+N117+N126+N135 -> 63012 | O76: =O81+O90+O99+O108+O117+O126+O135 -> 65472 | P76: =P81+P90+P99+P108+P117+P126+P135 -> 78566.4 | ... S76: =S81+S90+S99+S108+S117+S126+S135 -> 135762.74
D77: SUV | I77: =I81*I79/1000 -> 138493 | J77: =J81*J79/1000 -> 225931 | K77: =K81*K79/1000 -> 229337 | L77: =L81*L79/1000 -> 143294 | M77: =M81*M79/1000 -> 143294 | N77: =N81*N79/1000 -> 286588 | O77: =O81*O79/1000 -> 300754.21 | P77: =P81*P79/1000 -> 364514.11 | ... S77: =S81*S79/1000 -> 648966.38
E78: % YoY | J78: =J77/(I77/9*12)-1 -> 0.22351491 | K78: =K77/J77-1 -> 0.015075399 | L78: =(L77*2)/K77-1 -> 0.249637 | M78: =L78 -> 0.249637 | N78: =N77/K77-1 -> 0.249637 | O78: =O77/N77-1 -> 0.049430585 | P78: =P77/O77-1 -> 0.212 | Q78: =Q77/P77-1 -> 0.212 | R78: =R77/Q77-1 -> 0.212 | S78: =S77/R77-1 -> 0.212
E79: 가격(천원) | I79: ='Dart_중고차 Sales'!K47 -> 16895.558 | J79: ='Dart_중고차 Sales'!L47 -> 15894.552 | K79: ='Dart_중고차 Sales'!M47 -> 16288.636 | L79: ='Dart_중고차 Sales'!N47 -> 18632.399 | M79: =L79 -> 18632.399 | N79: =M79 -> 18632.399 | O79: =(1+Control!J39)*N79 -> 18818.723 | P79: =(1+Control!K39)*O79 -> 19006.91 | Q79: =(1+Control!L39)*P79 -> 19196.979 | R79: =(1+Control!M39)*Q79 -> 19388.949 | S79: =(1+Control!N39)*R79 -> 19582.839
F80: % YoY | J80: =J79/(I79)-1 -> -0.059246667 | K80: =K79/J79-1 -> 0.024793648 | L80: =(L79)/K79-1 -> 0.14388946 | M80: =L80 -> 0.14388946 | N80: =N79/K79-1 -> 0.14388946 | O80: =O79/N79-1 -> 0.01 | P80: =P79/O79-1 -> 0.01 | Q80: =Q79/P79-1 -> 0.01 | R80: =R79/Q79-1 -> 0.01 | S80: =S79/R79-1 -> 0.01
E81: 판매대수(대) | I81: ='Dart_중고차 Sales'!K36 -> 8197.0067 | J81: ='Dart_중고차 Sales'!L36 -> 14214.367 | K81: ='Dart_중고차 Sales'!M36 -> 14079.57 | L81: ='Dart_중고차 Sales'!N36 -> 7690.5823 | M81: =L81 -> 7690.5823 | N81: =L81+M81 -> 15381.165 | O81: =O83*O85 -> 15981.648 | P81: =P83*P85 -> 19177.978 | Q81: =Q83*Q85 -> 23013.573 | R81: =R83*R85 -> 27616.288 | S81: =S83*S85 -> 33139.546
F82: % YoY | J82: =J81/(I81/9*12)-1 -> 0.3005693 | K82: =K81/J81-1 -> -0.0094831279 | L82: =(L81*2)/K81-1 -> 0.092445596 | M82: =L82 -> 0.092445596 | N82: =N81/K81-1 -> 0.092445596 | O82: =O81/N81-1 -> 0.039040183 | P82: =P81/O81-1 -> 0.2 | Q82: =Q81/P81-1 -> 0.2 | R82: =R81/Q81-1 -> 0.2 | S82: =S81/R81-1 -> 0.2
G83: 시장판매대수(대) | I83: =I81/I85 -> 530057.6 | J83: =J81/J85 -> 569044.09 | K83: =K81/K85 -> 628708.12 | L83: =L81/L85 -> 332951 | M83: =M81/M85 -> 332951 | N83: =L83+M83 -> 665902.01 | O83: =(1+Control!J40)*N83 -> 799082.41 | P83: =(1+Control!K40)*O83 -> 958898.89 | Q83: =(1+Control!L40)*P83 -> 1150678.7 | R83: =(1+Control!M40)*Q83 -> 1380814.4 | S83: =(1+Control!N40)*R83 -> 1656977.3
H84: % YoY | J84: =J83/I83-1 -> 0.073551418 | K84: =K83/J83-1 -> 0.10484957 | L84: =(L83*2)/K83-1 -> 0.059159226 | M84: =L84 -> 0.059159226 | N84: =N83/K83-1 -> 0.059159226 | O84: =O83/N83-1 -> 0.2 | P84: =P83/O83-1 -> 0.2 | Q84: =Q83/P83-1 -> 0.2 | R84: =R83/Q83-1 -> 0.2 | S84: =S83/R83-1 -> 0.2
G85: 점유율 | I85: =Dart_시장리서치!F$48 -> 0.01546437 | J85: =Dart_시장리서치!G$48 -> 0.024979377 | K85: =Dart_시장리서치!H$48 -> 0.022394447 | L85: =Dart_시장리서치!I$48 -> 0.02309824 | M85: =L85 -> 0.02309824 | N85: =M85 -> 0.02309824 | O85: =Control!J41 -> 0.02 | P85: =Control!K41 -> 0.02 | Q85: =Control!L41 -> 0.02 | R85: =Control!M41 -> 0.02 | S85: =Control!N41 -> 0.02
D86: 대형 | I86: =I90*I88/1000 -> 108869 | J86: =J90*J88/1000 -> 164745 | K86: =K90*K88/1000 -> 156947 | L86: =L90*L88/1000 -> 99480 | M86: =M90*M88/1000 -> 99480 | N86: =N90*N88/1000 -> 198960 | O86: =O90*O88/1000 -> 208794.71 | P86: =P90*P88/1000 -> 253059.19 | ... S86: =S90*S88/1000 -> 450536.49
E87: % YoY | J87: =J86/(I86/9*12)-1 -> 0.13493051 | K87: =K86/J86-1 -> -0.047333758 | L87: =(L86*2)/K86-1 -> 0.26768909 | M87: =L87 -> 0.26768909 | N87: =N86/K86-1 -> 0.26768909 | O87: =O86/N86-1 -> 0.049430585 | P87: =P86/O86-1 -> 0.212 | Q87: =Q86/P86-1 -> 0.212 | R87: =R86/Q86-1 -> 0.212 | S87: =S86/R86-1 -> 0.212
E88: 가격(천원) | I88: ='Dart_중고차 Sales'!K48 -> 18370.526 | J88: ='Dart_중고차 Sales'!L48 -> 17951.765 | K88: ='Dart_중고차 Sales'!M48 -> 18522.541 | L88: ='Dart_중고차 Sales'!N48 -> 20249.049 | M88: =L88 -> 20249.049 | N88: =M88 -> 20249.049 | O88: =(1+Control!J42)*N88 -> 20451.539 | P88: =(1+Control!K42)*O88 -> 20656.055 | Q88: =(1+Control!L42)*P88 -> 20862.615 | R88: =(1+Control!M42)*Q88 -> 21071.241 | S88: =(1+Control!N42)*R88 -> 21281.954
F89: % YoY | J89: =J88/(I88)-1 -> -0.022795261 | K89: =K88/J88-1 -> 0.031794937 | L89: =(L88)/K88-1 -> 0.093211195 | M89: =L89 -> 0.093211195 | N89: =N88/K88-1 -> 0.093211195 | O89: =O88/N88-1 -> 0.01 | P89: =P88/O88-1 -> 0.01 | Q89: =Q88/P88-1 -> 0.01 | R89: =R88/Q88-1 -> 0.01 | S89: =S88/R88-1 -> 0.01
E90: 판매대수(대) | I90: ='Dart_중고차 Sales'!K37 -> 5926.2864 | J90: ='Dart_중고차 Sales'!L37 -> 9177.0918 | K90: ='Dart_중고차 Sales'!M37 -> 8473.2976 | L90: ='Dart_중고차 Sales'!N37 -> 4912.8234 | M90: =L90 -> 4912.8234 | N90: =L90+M90 -> 9825.6467 | O90: =O92*O94 -> 10209.242 | P90: =P92*P94 -> 12251.09 | Q90: =Q92*Q94 -> 14701.308 | R90: =R92*R94 -> 17641.57 | S90: =S92*S94 -> 21169.884
F91: % YoY | J91: =J90/(I90/9*12)-1 -> 0.16140504 | K91: =K90/J90-1 -> -0.076690331 | L91: =(L90*2)/K90-1 -> 0.15960127 | M91: =L91 -> 0.15960127 | N91: =N90/K90-1 -> 0.15960127 | O91: =O90/N90-1 -> 0.039040183 | P91: =P90/O90-1 -> 0.2 | Q91: =Q90/P90-1 -> 0.2 | R91: =R90/Q90-1 -> 0.2 | S91: =S90/R90-1 -> 0.2
G92: 시장판매대수(대) | I92: =I90/I94 -> 383221.98 | J92: =J90/J94 -> 367386.73 | K92: =K90/K94 -> 378366.02 | L92: =L90/L94 -> 212692.54 | M92: =M90/M94 -> 212692.54 | N92: =L92+M92 -> 425385.07 | O92: =(1+Control!J43)*N92 -> 510462.09 | P92: =(1+Control!K43)*O92 -> 612554.5 | Q92: =(1+Control!L43)*P92 -> 735065.41 | R92: =(1+Control!M43)*Q92 -> 882078.49 | S92: =(1+Control!N43)*R92 -> 1058494.2
H93: % YoY | J93: =J92/I92-1 -> -0.041321344 | K93: =K92/J92-1 -> 0.02988482 | L93: =(L92*2)/K92-1 -> 0.1242687 | M93: =L93 -> 0.1242687 | N93: =N92/K92-1 -> 0.1242687 | O93: =O92/N92-1 -> 0.2 | P93: =P92/O92-1 -> 0.2 | Q93: =Q92/P92-1 -> 0.2 | R93: =R92/Q92-1 -> 0.2 | S93: =S92/R92-1 -> 0.2
G94: 점유율 | I94: =Dart_시장리서치!F$48 -> 0.01546437 | J94: =Dart_시장리서치!G$48 -> 0.024979377 | K94: =Dart_시장리서치!H$48 -> 0.022394447 | L94: =Dart_시장리서치!I$48 -> 0.02309824 | M94: =L94 -> 0.02309824 | N94: =M94 -> 0.02309824 | O94: =Control!J44 -> 0.02 | P94: =Control!K44 -> 0.02 | Q94: =Control!L44 -> 0.02 | R94: =Control!M44 -> 0.02 | S94: =Control!N44 -> 0.02
D95: 중형 | I95: =I99*I97/1000 -> 105618 | J95: =J99*J97/1000 -> 154058 | K95: =K99*K97/1000 -> 156090 | L95: =L99*L97/1000 -> 91748 | M95: =M99*M97/1000 -> 91748 | N95: =N99*N97/1000 -> 183496 | O95: =O99*O97/1000 -> 192566.31 | P95: =P99*P97/1000 -> 233390.37 | ... S95: =S99*S97/1000 -> 415518.91
E96: % YoY | J96: =J95/(I95/9*12)-1 -> 0.093975459 | K96: =K95/J95-1 -> 0.013189838 | L96: =(L95*2)/K95-1 -> 0.17557819 | M96: =L96 -> 0.17557819 | N96: =N95/K95-1 -> 0.17557819 | O96: =O95/N95-1 -> 0.049430585 | P96: =P95/O95-1 -> 0.212 | Q96: =Q95/P95-1 -> 0.212 | R96: =R95/Q95-1 -> 0.212 | S96: =S95/R95-1 -> 0.212
E97: 가격(천원) | I97: ='Dart_중고차 Sales'!K49 -> 13282.85 | J97: ='Dart_중고차 Sales'!L49 -> 12990.605 | K97: ='Dart_중고차 Sales'!M49 -> 13820.904 | L97: ='Dart_중고차 Sales'!N49 -> 15399.1 | M97: =L97 -> 15399.1 | N97: =M97 -> 15399.1 | O97: =(1+Control!J45)*N97 -> 15553.091 | P97: =(1+Control!K45)*O97 -> 15708.622 | Q97: =(1+Control!L45)*P97 -> 15865.708 | R97: =(1+Control!M45)*Q97 -> 16024.365 | S97: =(1+Control!N45)*R97 -> 16184.609
F98: % YoY | J98: =J97/(I97)-1 -> -0.022001697 | K98: =K97/J97-1 -> 0.063915374 | L98: =(L97)/K97-1 -> 0.11418902 | M98: =L98 -> 0.11418902 | N98: =N97/K97-1 -> 0.11418902 | O98: =O97/N97-1 -> 0.01 | P98: =P97/O97-1 -> 0.01 | Q98: =Q97/P97-1 -> 0.01 | R98: =R97/Q97-1 -> 0.01 | S98: =S97/R97-1 -> 0.01
E99: 판매대수(대) | I99: ='Dart_중고차 Sales'!K38 -> 7951.4561 | J99: ='Dart_중고차 Sales'!L38 -> 11859.186 | K99: ='Dart_중고차 Sales'!M38 -> 11293.762 | L99: ='Dart_중고차 Sales'!N38 -> 5958.0106 | M99: =L99 -> 5958.0106 | N99: =L99+M99 -> 11916.021 | O99: =O101*O103 -> 12381.225 | P99: =P101*P103 -> 14857.47 | Q99: =Q101*Q103 -> 17828.964 | R99: =R101*R103 -> 21394.757 | S99: =S101*S103 -> 25673.708
F100: % YoY | J100: =J99/(I99/9*12)-1 -> 0.11858626 | K100: =K99/J99-1 -> -0.047678168 | L100: =(L99*2)/K99-1 -> 0.055097628 | M100: =L100 -> 0.055097628 | N100: =N99/K99-1 -> 0.055097628 | O100: =O99/N99-1 -> 0.039040183 | P100: =P99/O99-1 -> 0.2 | Q100: =Q99/P99-1 -> 0.2 | R100: =R99/Q99-1 -> 0.2 | S100: =S99/R99-1 -> 0.2
G101: 시장판매대수(대) | I101: =I99/I103 -> 514179.13 | J101: =J99/J103 -> 474759.07 | K101: =K99/K103 -> 504310.82 | L101: =L99/L103 -> 257942.18 | M101: =M99/M103 -> 257942.18 | N101: =L101+M101 -> 515884.37 | O101: =(1+Control!J46)*N101 -> 619061.24 | P101: =(1+Control!K46)*O101 -> 742873.49 | Q101: =(1+Control!L46)*P101 -> 891448.19 | R101: =(1+Control!M46)*Q101 -> 1069737.8 | S101: =(1+Control!N46)*R101 -> 1283685.4
...

Sheet Sales Bridge
B1: Sales bridge | D1: Index
B3: KRW in millions | D3: 2018 | E3: 2019 | F3: 2020 | G3: 2021.1H
B4: 이커머스 판매매출 | D4: =Sales!I8 -> 155662 | E4: =Sales!J8 -> 284782 | F4: =Sales!K8 -> 408225 | G4: =Sales!L8 -> 322919
C5: 이커머스 총 판매대수 | D5: =Dart_시장리서치!F40 -> 17000 | E5: =Dart_시장리서치!G40 -> 24000 | F5: =Dart_시장리서치!H40 -> 40000 | G5: =Dart_시장리서치!I40/2 -> 33500
C6: 케이카 이커머스 점유율 | D6: =D7/D5 -> 0.74705882 | E6: =E7/E5 -> 0.93975 | F6: =F7/F5 -> 0.78185 | G6: =G7/G5 -> 0.6841791
C7: 케이카 이커머스 판매대수 | D7: =Dart_시장리서치!F42 -> 12700 | E7: =Dart_시장리서치!G42 -> 22554 | F7: =Dart_시장리서치!H42 -> 31274 | G7: =Dart_시장리서치!I42/2 -> 22920
C8: 이커머스 평균판매가격(천원) | D8: =D4*10^6/D7/1000 -> 12256.85 | E8: =E4*10^6/E7/1000 -> 12626.674 | F8: =F4*10^6/F7/1000 -> 13053.175 | G8: =G4*10^6/G7/1000 -> 14088.962
B9: 지점내방 판매매출 | D9: =Sales!I74 -> 518742 | E9: =Sales!J74 -> 786019 | F9: =Sales!K74 -> 776425 | G9: =Sales!L74 -> 469142
C10: 지점내방 총 판매대수 | D10: =Dart_시장리서치!F45 -> 2554000 | E10: =Dart_시장리서치!G45 -> 2473000 | F10: =Dart_시장리서치!H45 -> 2629000 | G10: =Dart_시장리서치!I45/2 -> 1364000
C11: 케이카 지점내방 점유율 | D11: =D12/D10 -> 0.01546437 | E11: =E12/E10 -> 0.024979377 | F11: =F12/F10 -> 0.022394447 | G11: =G12/G10 -> 0.02309824
C12: 케이카 지점내방 판매대수 | D12: =Dart_시장리서치!F47 -> 39496 | E12: =Dart_시장리서치!G47 -> 61774 | F12: =Dart_시장리서치!H47 -> 58875 | G12: =Dart_시장리서치!I47/2 -> 31506
C13: 지점내방 평균판매가격(천원) | D13: =D9*10^6/D12/1000 -> 13134.039 | E13: =E9*10^6/E12/1000 -> 12724.107 | F13: =F9*10^6/F12/1000 -> 13187.686 | G13: =G9*10^6/G12/1000 -> 14890.561
B14: 경매 | D14: =Sales!I140 -> 50546 | E14: =Sales!J140 -> 80966 | F14: =Sales!K140 -> 98049 | G14: =Sales!L140 -> 69172
B15: 렌터카 | D15: =Sales!I146 -> 0 | E15: =Sales!J146 -> 0 | F15: =Sales!K146 -> 0 | G15: =Sales!L146 -> 22392
B16: 기타 | D16: =Sales!I152 -> 17853 | E16: =Sales!J152 -> 33589 | F16: =Sales!K152 -> 40415 | G16: =Sales!L152 -> 26960
B17: 총매출 | D17: =D4+D9+D14+D15+D16 -> 742803 | E17: =E4+E9+E14+E15+E16 -> 1185356 | F17: =F4+F9+F14+F15+F16 -> 1323114 | G17: =G4+G9+G14+G15+G16 -> 910585
C20: 2018 Sales | D20: =D17 -> 742803
C21: 이커머스 시장 △Q | D21: =(E5-D5)*D6*D8*1000/10^6 -> 64096.118
C22: 이커머스 △점유율 | D22: =D5*(E6-D6)*D8*1000/10^6 -> 40150.378
C23: 이커머스 △가격 | D23: =D5*D6*(E8-D8)*1000/10^6 -> 4696.7568
C24: 이커머스 복합효과 | D24: =Sales!J8-(Sales!I8+D21+D22+D23) -> 20176.748
C25: 지점내방 시장 △Q | D25: =(E10-D10)*D11*D13*1000/10^6 -> -16451.88
C26: 지점내방 △점유율 | D26: =D10*(E11-D11)*D13*1000/10^6 -> 319174.61
C27: 지점내방 △가격 | D27: =D10*D11*(E13-D13)*1000/10^6 -> -16190.661
C28: 지점내방 복합효과 | D28: =Sales!J74-(Sales!I74+D25+D26+D27) -> -19255.066
C29: △경매매출 | D29: =E14-D14 -> 30420
C30: △렌터카매출 | D30: =E15-D15 -> 0
C31: △기타매출 | D31: =E16-D16 -> 15736
C32: 2019 Sales | D32: =E17 -> 1185356
C33: 이커머스 시장 △Q | D33: =(F5-E5)*E6*E8*1000/10^6 -> 189854.67
C34: 이커머스 △점유율 | D34: =E5*(F6-E6)*E8*1000/10^6 -> -47850.043
C35: 이커머스 △가격 | D35: =E5*E6*(F8-E8)*1000/10^6 -> 9619.3126
C36: 이커머스 복합효과 | D36: =Sales!K8-(Sales!J8+D33+D34+D35) -> -28180.936
C37: 지점내방 시장 △Q | D37: =(F10-E10)*E11*E13*1000/10^6 -> 49583.083
C38: 지점내방 △점유율 | D38: =E10*(F11-E11)*E13*1000/10^6 -> -81339.284
C39: 지점내방 △가격 | D39: =E10*E11*(F13-E13)*1000/10^6 -> 28637.101
C40: 지점내방 복합효과 | D40: =Sales!K74-(Sales!J74+D37+D38+D39) -> -6474.9002
C41: △경매매출 | D41: =F14-E14 -> 17083
C42: △렌터카매출 | D42: =F15-E15 -> 0
C43: △기타매출 | D43: =F16-E16 -> 6826
C44: 2020 Sales | D44: =F17 -> 1323114
C45: 이커머스 시장 △Q | D45: =(G5*2-F5)*F6*F8*1000/10^6 -> 275551.88
C46: 이커머스 △점유율 | D46: =F5*(G6-F6)*F8*1000/10^6 -> -50996.612
C47: 이커머스 △가격 | D47: =F5*F6*(G8-F8)*1000/10^6 -> 32393.185
C48: 이커머스 복합효과 | D48: =Sales!L8*2-(Sales!K8+D45+D46+D47) -> -19335.448
C49: 지점내방 시장 △Q | D49: =(G10*2-F10)*F11*F13*1000/10^6 -> 29237.762
C50: 지점내방 △점유율 | D50: =F10*(G11-F11)*F13*1000/10^6 -> 24400.835
C51: 지점내방 △가격 | D51: =F10*F11*(G13-F13)*1000/10^6 -> 100256.75
C52: 지점내방 복합효과 | D52: =Sales!L74*2-(Sales!K74+D49+D50+D51) -> 7963.6527
C53: △경매매출 | D53: =G14*2-F14 -> 40295
C54: △렌터카매출 | D54: =G15*2-F15 -> 44784
C55: △기타매출 | D55: =G16*2-F16 -> 13505
C56: 2021 Sales | D56: =G17*2 -> 1821170

Sheet Cost
B1: Cost | E1: Index
E3: Historical | J3: Forecast
B4: KRW in millions | E4: 2018 | F4: 2019 | G4: 2020 | H4: 2021.1H | I4: 2021.2H | J4: 2021 | K4: 2022 | L4: =K4+1 -> 2023 | M4: =L4+1 -> 2024 | N4: =M4+1 -> 2025 | O4: =N4+1 -> 2026
B5: 중고차 판매대수 | E5: =Sales!I7 -> 52196 | F5: =Sales!J7 -> 84328 | G5: =Sales!K7 -> 90149 | H5: =Sales!L7 -> 54426 | I5: =Sales!M7 -> 54426 | J5: =Sales!N7 -> 108852 | K5: =Sales!O7 -> 111343.67 | L5: =Sales!P7 -> 131007.24 | ... O5: =Sales!S7 -> 215003.75
B6: Total Sales | E6: =Sales!I160 -> 742803 | F6: =Sales!J160 -> 1185356 | G6: =Sales!K160 -> 1323114 | H6: =Sales!L160 -> 910585 | I6: =Sales!M160 -> 910585 | J6: =Sales!N160 -> 1821170 | K6: =Sales!O160 -> 1902459 | L6: =Sales!P160 -> 2256380 | ... O6: =Sales!S160 -> 3792952.9
B7: 중고차 Sales | E7: =Sales!I5 -> 674404 | F7: =Sales!J5 -> 1070801 | G7: =Sales!K5 -> 1184650 | H7: =Sales!L5 -> 792061 | I7: =Sales!M5 -> 792061 | J7: =Sales!N5 -> 1584122 | K7: =Sales!O5 -> 1630322.7 | L7: =Sales!P5 -> 1930634.3 | ... O7: =Sales!S5 -> 3233329.1
B8: 렌터카 매각 Sales | E8: =Sales!I148 -> 0 | F8: =Sales!J148 -> 0 | G8: =Sales!K148 -> 0 | H8: =Sales!L148 -> 5615 | I8: =Sales!M148 -> 5615 | J8: =Sales!N148 -> 11230 | K8: =Sales!O148 -> 13476 | L8: =Sales!P148 -> 16171.2 | ... O8: =Sales!S148 -> 27943.834
B9: 인건비 | E9: =SUM(E11:E13) -> 30994.723 | F9: =SUM(F11:F13) -> 48926.557 | G9: =SUM(G11:G13) -> 54031.414 | H9: =SUM(H11:H13) -> 33044.704 | I9: =SUM(I11:I13) -> 33044.704 | J9: =SUM(J11:J13) -> 66089.408 | K9: =SUM(K11:K13) -> 68601.231 | L9: =SUM(L11:L13) -> 81184.55 | ... O9: =SUM(O11:O13) -> 137055.76
C10: % of Sales | E10: =E9/E6 -> 0.041726707 | F10: =F9/F6 -> 0.041275834 | G10: =G9/G6 -> 0.040836552 | H10: =H9/H6 -> 0.036289533 | I10: =I9/I6 -> 0.036289533 | J10: =J9/J6 -> 0.036289533 | K10: =K9/K6 -> 0.036059242 | L10: =L9/L6 -> 0.035979999 | ... O10: =O9/O6 -> 0.036134317
C11: 종업원급여 | E11: =Labor!G9 -> 25858.31 | F11: =Labor!H9 -> 40917.289 | G11: =Labor!I9 -> 44758.009 | H11: =Labor!J9 -> 27738.124 | I11: =Labor!K9 -> 27738.124 | J11: =Labor!L9 -> 55476.248 | K11: =Labor!M9 -> 58729.897 | L11: =Labor!N9 -> 69817.432 | ... O11: =Labor!Q9 -> 118344.84
C12: 퇴직급여 | E12: =Labor!G58 -> 2136.705 | F12: =Labor!H58 -> 3125.462 | G12: =Labor!I58 -> 4481.863 | H12: =Labor!J58 -> 2195.341 | I12: =Labor!K58 -> 2195.341 | J12: =Labor!L58 -> 4390.682 | K12: =Labor!M58 -> 4967.0347 | L12: =Labor!N58 -> 5904.7542 | ... O12: =Labor!Q58 -> 10008.921
C13: 복리후생비 | E13: =Labor!G60 -> 2999.708 | F13: =Labor!H60 -> 4883.806 | G13: =Labor!I60 -> 4791.542 | H13: =Labor!J60 -> 3111.239 | I13: =Labor!K60 -> 3111.239 | J13: =Labor!L60 -> 6222.478 | K13: =Labor!M60 -> 4904.2994 | L13: =Labor!N60 -> 5462.364 | ... O13: =Labor!Q60 -> 8702.0035
B14: 주식보상비용 | E14: =Dart_Cost!C25/1000 -> 0 | F14: =Dart_Cost!D25/1000 -> 0 | G14: =Dart_Cost!E25/1000 -> 0 | H14: =Dart_Cost!F25/1000 -> 975.474 | I14: =H14 -> 975.474 | J14: =H14+I14 -> 1950.948 | K14: =K9*Control!J73 -> 2058.0369 | L14: =L9*Control!K73 -> 2435.5365 | M14: =M9*Control!L73 -> 2897.1162 | N14: =N9*Control!M73 -> 3458.893 | O14: =O9*Control!N73 -> 4111.6729
D15: % of Labor | E15: =E14/E9 -> 0 | F15: =F14/F9 -> 0 | G15: =G14/G9 -> 0 | H15: =H14/H9 -> 0.029519829 | I15: =I14/I9 -> 0.029519829 | J15: =J14/J9 -> 0.029519829 | K15: =K14/K9 -> 0.03 | L15: =L14/L9 -> 0.03 | ... O15: =O14/O9 -> 0.03
B16: 상각비 | E16: =SUM(E17:E18) -> 7432.3771 | F16: =SUM(F17:F18) -> 13537.456 | G16: =SUM(G17:G18) -> 15873.972 | H16: =SUM(H17:H18) -> 19724.316 | I16: =SUM(I17:I18) -> 19724.316 | J16: =SUM(J17:J18) -> 39448.632 | K16: =SUM(K17:K18) -> 33669.772 | L16: =SUM(L17:L18) -> 30919.503 | ... O16: =SUM(O17:O18) -> 25746.402
C17: 감가상각비 | E17: ='CapEx,D&A'!F9 -> 6680.6336 | F17: ='CapEx,D&A'!G9 -> 12256.755 | G17: ='CapEx,D&A'!H9 -> 14214.472 | H17: ='CapEx,D&A'!I9 -> 18802.028 | I17: ='CapEx,D&A'!J9 -> 18802.028 | J17: ='CapEx,D&A'!K9 -> 37604.056 | K17: ='CapEx,D&A'!L9 -> 32110.436 | L17: ='CapEx,D&A'!M9 -> 29350.294 | ... O17: ='CapEx,D&A'!P9 -> 24142.297
C18: 무형자산상각비 | E18: ='CapEx,D&A'!F10 -> 751.74352 | F18: ='CapEx,D&A'!G10 -> 1280.7009 | G18: ='CapEx,D&A'!H10 -> 1659.4994 | H18: ='CapEx,D&A'!I10 -> 922.28807 | I18: ='CapEx,D&A'!J10 -> 922.28807 | J18: ='CapEx,D&A'!K10 -> 1844.5761 | K18: ='CapEx,D&A'!L10 -> 1559.336 | L18: ='CapEx,D&A'!M10 -> 1569.2089 | ... O18: ='CapEx,D&A'!P10 -> 1604.1048
B19: 변동비 | E19: =E21+E24+E27+E31+E33+E35+E37+E39+E41+E29 -> 688489.81 | F19: =F21+F24+F27+F31+F33+F35+F37+F39+F41+F29 -> 1088832.5 | G19: =G21+G24+G27+G31+G33+G35+G37+G39+G41+G29 -> 1210703.1 | H19: =H21+H24+H27+H31+H33+H35+H37+H39+H41+H29 -> 812768.74 | I19: =I21+I24+I27+I31+I33+I35+I37+I39+I41+I29 -> 812768.74 | J19: =J21+J24+J27+J31+J33+J35+J37+J39+J41+J29 -> 1625537.5 | K19: =K21+K24+K27+K31+K33+K35+K37+K39+K41+K29 -> 1670801.7 | L19: =L21+L24+L27+L31+L33+L35+L37+L39+L41+L29 -> 1985483.9 | ... O19: =O21+O24+O27+O31+O33+O35+O37+O39+O41+O29 -> 3356864.7
C20: % of Total Sales | E20: =E19/E$6 -> 0.92688076 | F20: =F19/F$6 -> 0.91857004 | G20: =G19/G$6 -> 0.91504064 | H20: =H19/H$6 -> 0.89257866 | I20: =I19/I$6 -> 0.89257866 | J20: =J19/J$6 -> 0.89257866 | K20: =K19/K$6 -> 0.87823268 | L20: =L19/L$6 -> 0.87994214 | ... O20: =O19/O$6 -> 0.88502673
C21: 재고자산원가 | E21: =(Dart_Cost!C6+Dart_Cost!C7)/1000 -> 663748.17 | F21: =(Dart_Cost!D6+Dart_Cost!D7)/1000 -> 1053521.7 | G21: =(Dart_Cost!E6+Dart_Cost!E7)/1000 -> 1170061.6 | H21: =(Dart_Cost!F6+Dart_Cost!F7)/1000 -> 784113.35 | I21: =H21 -> 784113.35 | J21: =H21+I21 -> 1568226.7 | K21: =K5*Control!J74 -> 1604124.1 | L21: =L5*Control!K74 -> 1906290.6 | M21: =M5*Control!L74 -> 2268308.6 | N21: =N5*Control!M74 -> 2702399.5 | O21: =O5*Control!N74 -> 3223324.1
D22: 중고차 1대당 원가 | E22: =E21/E$5 -> 12.716457 | F22: =F21/F5 -> 12.493142 | G22: =G21/G5 -> 12.979196 | H22: =H21/H5 -> 14.406963 | I22: =H22 -> 14.406963 | J22: =I22 -> 14.406963 | K22: =K21/K5 -> 14.406963 | L22: =L21/L5 -> 14.551032 | M22: =M21/M5 -> 14.696543 | N22: =N21/N5 -> 14.843508 | O22: =O21/O5 -> 14.991943
D23: % of 중고차 Sales | E23: =E21/E$7 -> 0.98419963 | F23: =F21/F$7 -> 0.98386317 | G23: =G21/G$7 -> 0.98768544 | H23: =H21/H$7 -> 0.98996587 | I23: =I21/I$7 -> 0.98996587 | J23: =J21/J$7 -> 0.98996587 | K23: =K21/K$7 -> 0.98393041 | L23: =L21/L$7 -> 0.98739082 | ... O23: =O21/O$7 -> 0.99690566
C24: 판매보증비 | E24: =Dart_Cost!C24/1000 -> 3856.243 | F24: =Dart_Cost!D24/1000 -> 4812.931 | G24: =Dart_Cost!E24/1000 -> 3766.917 | H24: =Dart_Cost!F24/1000 -> 1813.818 | I24: =H24 -> 1813.818 | J24: =H24+I24 -> 3627.636 | K24: =K5*Control!J$75 -> 3710.6741 | L24: =L5*Control!K$75 -> 4365.9884 | M24: =M5*Control!L$75 -> 5143.6835 | N24: =N5*Control!M$75 -> 6067.3674 | O24: =O5*Control!N$75 -> 7165.2827
D25: 중고차 1대당 보증비 | E25: =E24/E$5 -> 0.073880048 | F25: =F24/F$5 -> 0.057073937 | G25: =G24/G$5 -> 0.041785455 | H25: =H24/H$5 -> 0.033326315 | I25: =I24/I$5 -> 0.033326315 | J25: =J24/J$5 -> 0.033326315 | K25: =K24/K$5 -> 0.033326315 | L25: =L24/L$5 -> 0.033326315 | ... O25: =O24/O$5 -> 0.033326315
D26: % of 중고차 Sales | E26: =E24/E$7 -> 0.0057180014 | F26: =F24/F$7 -> 0.0044947016 | G26: =G24/G$7 -> 0.0031797721 | H26: =H24/H$7 -> 0.0022899979 | I26: =I24/I$7 -> 0.0022899979 | J26: =J24/J$7 -> 0.0022899979 | K26: =K24/K$7 -> 0.0022760366 | L26: =L24/L$7 -> 0.002261427 | ... O26: =O24/O$7 -> 0.0022160697
C27: 차량매각원가 | E27: =Dart_Cost!C26/1000 -> 0 | F27: =Dart_Cost!D26/1000 -> 0 | G27: =Dart_Cost!E26/1000 -> 0 | H27: =Dart_Cost!F26/1000 -> 4368.328 | I27: =H27 -> 4368.328 | J27: =H27+I27 -> 8736.656 | K27: =K$8*Control!J76 -> 10483.987 | L27: =L$8*Control!K76 -> 12580.785 | M27: =M$8*Control!L76 -> 15096.942 | N27: =N$8*Control!M76 -> 18116.33 | O27: =O$8*Control!N76 -> 21739.596
D28: % of 렌터카매각 Sales | H28: =H27/H$8 -> 0.77797471 | I28: =I27/I$8 -> 0.77797471 | J28: =J27/J$8 -> 0.77797471 | K28: =K27/K$8 -> 0.77797471 | L28: =L27/L$8 -> 0.77797471 | M28: =M27/M$8 -> 0.77797471 | N28: =N27/N$8 -> 0.77797471 | O28: =O27/O$8 -> 0.77797471
C29: 지급수수료 | E29: =Dart_Cost!C19/1000 -> 6038.554 | F29: =Dart_Cost!D19/1000 -> 9360.366 | G29: =Dart_Cost!E19/1000 -> 10811.345 | H29: =Dart_Cost!F19/1000 -> 7607.318 | I29: =H29 -> 7607.318 | J29: =H29+I29 -> 15214.636 | K29: =K$6*Control!J77 -> 15481.994 | L29: =L$6*Control!K77 -> 18362.162 | M29: =M$6*Control!L77 -> 21806.388 | N29: =N$6*Control!M77 -> 25928.701 | O29: =O$6*Control!N77 -> 30866.617
D30: % of Total Sales | E30: =E29/E$6 -> 0.0081294152 | F30: =F29/F$6 -> 0.0078966707 | G30: =G29/G$6 -> 0.0081711364 | H30: =H29/H$6 -> 0.0083543195 | I30: =I29/I$6 -> 0.0083543195 | J30: =J29/J$6 -> 0.0083543195 | K30: =K29/K$6 -> 0.0081378855 | L30: =L29/L$6 -> 0.0081378855 | ... O30: =O29/O$6 -> 0.0081378855
C31: 부품비 | E31: =Dart_Cost!C23/1000 -> 468.221 | F31: =Dart_Cost!D23/1000 -> 594.292 | G31: =Dart_Cost!E23/1000 -> 693.463 | H31: =Dart_Cost!F23/1000 -> 349.912 | I31: =H31 -> 349.912 | J31: =H31+I31 -> 699.824 | K31: =K$6*Control!J78 -> 970.2974 | L31: =L$6*Control!K78 -> 1150.8052 | M31: =M$6*Control!L78 -> 1366.6639 | N31: =N$6*Control!M78 -> 1625.0201 | O31: =O$6*Control!N78 -> 1934.4923
D32: % of Total Sales | E32: =E31/E$6 -> 0.00063034344 | F32: =F31/F$6 -> 0.00050136162 | G32: =G31/G$6 -> 0.00052411432 | H32: =H31/H$6 -> 0.00038427165 | I32: =I31/I$6 -> 0.00038427165 | J32: =J31/J$6 -> 0.00038427165 | K32: =K31/K$6 -> 0.00051002276 | L32: =L31/L$6 -> 0.00051002276 | ... O32: =O31/O$6 -> 0.00051002276
C33: 세금과공과 | E33: =Dart_Cost!C12/1000 -> 1802.771 | F33: =Dart_Cost!D12/1000 -> 3765.01 | G33: =Dart_Cost!E12/1000 -> 5220.383 | H33: =Dart_Cost!F12/1000 -> 2969.282 | I33: =H33 -> 2969.282 | J33: =H33+I33 -> 5938.564 | K33: =K$6*Control!J79 -> 6092.45 | L33: =L$6*Control!K79 -> 7225.8495 | M33: =M$6*Control!L79 -> 8581.2158 | N33: =N$6*Control!M79 -> 10203.422 | O33: =O$6*Control!N79 -> 12146.583
D34: % of Total Sales | E34: =E33/E$6 -> 0.002426984 | F34: =F33/F$6 -> 0.0031762694 | G34: =G33/G$6 -> 0.0039455277 | H34: =H33/H$6 -> 0.003260851 | I34: =I33/I$6 -> 0.003260851 | J34: =J33/J$6 -> 0.003260851 | K34: =K33/K$6 -> 0.003202408 | L34: =L33/L$6 -> 0.003202408 | ... O34: =O33/O$6 -> 0.003202408
C35: 위탁차량비 | E35: =Dart_Cost!C22/1000 -> 232.945 | F35: =Dart_Cost!D22/1000 -> 267.44 | G35: =Dart_Cost!E22/1000 -> 376.683 | H35: =Dart_Cost!F22/1000 -> 153.236 | I35: =H35 -> 153.236 | J35: =H35+I35 -> 306.472 | K35: =K$6*Control!J80 -> 471.90494 | L35: =L$6*Control!K80 -> 559.69504 | M35: =M$6*Control!L80 -> 664.6781 | N35: =N$6*Control!M80 -> 790.32989 | O35: =O$6*Control!N80 -> 940.84194
D36: % of Total Sales | E36: =E35/E$6 -> 0.00031360266 | F36: =F35/F$6 -> 0.00022561998 | G36: =G35/G$6 -> 0.00028469429 | H36: =H35/H$6 -> 0.00016828303 | I36: =I35/I$6 -> 0.00016828303 | J36: =J35/J$6 -> 0.00016828303 | K36: =K35/K$6 -> 0.00024804999 | L36: =L35/L$6 -> 0.00024804999 | ... O36: =O35/O$6 -> 0.00024804999
C37: 소모품비 | E37: =Dart_Cost!C21/1000 -> 413.477 | F37: =Dart_Cost!D21/1000 -> 504.02 | G37: =Dart_Cost!E21/1000 -> 618.27 | H37: =Dart_Cost!F21/1000 -> 315.982 | I37: =H37 -> 315.982 | J37: =H37+I37 -> 631.964 | K37: =K$6*Control!J81 -> 854.27245 | L37: =L$6*Control!K81 -> 1013.1957 | M37: =M$6*Control!L81 -> 1203.2427 | N37: =N$6*Control!M81 -> 1430.7056 | O37: =O$6*Control!N81 -> 1703.1721
D38: % of Total Sales | E38: =E37/E$6 -> 0.00055664422 | F38: =F37/F$6 -> 0.00042520559 | G38: =G37/G$6 -> 0.000467284 | H38: =H37/H$6 -> 0.00034700989 | I38: =I37/I$6 -> 0.00034700989 | J38: =J37/J$6 -> 0.00034700989 | K38: =K37/K$6 -> 0.00044903593 | L38: =L37/L$6 -> 0.00044903593 | ... O38: =O37/O$6 -> 0.00044903593
C39: 보험료 | E39: =Dart_Cost!C16/1000 -> 235.401 | F39: =Dart_Cost!D16/1000 -> 341.832 | G39: =Dart_Cost!E16/1000 -> 349.413 | H39: =Dart_Cost!F16/1000 -> 1572.558 | I39: =H39 -> 1572.558 | J39: =H39+I39 -> 3145.116 | K39: =K$6*Control!J82 -> 1234.8612 | L39: =L$6*Control!K82 -> 1464.5867 | M39: =M$6*Control!L82 -> 1739.302 | N39: =N$6*Control!M82 -> 2068.1024 | O39: =O$6*Control!N82 -> 2461.9561
D40: % of Total Sales | E40: =E39/E$6 -> 0.00031690906 | F40: =F39/F$6 -> 0.00028837919 | G40: =G39/G$6 -> 0.00026408382 | H40: =H39/H$6 -> 0.0017269755 | I40: =I39/I$6 -> 0.0017269755 | J40: =J39/J$6 -> 0.0017269755 | K40: =K39/K$6 -> 0.0006490869 | L40: =L39/L$6 -> 0.0006490869 | ... O40: =O39/O$6 -> 0.0006490869
C41: 기타비용 | E41: =Dart_Cost!C27/1000 -> 11694.027 | F41: =Dart_Cost!D27/1000 -> 15664.953 | G41: =Dart_Cost!E27/1000 -> 18805.05 | H41: =Dart_Cost!F27/1000 -> 9504.955 | I41: =H41 -> 9504.955 | J41: =H41+I41 -> 19009.91 | K41: =K$6*Control!J83 -> 27377.163 | L41: =L$6*Control!K83 -> 32470.232 | M41: =M$6*Control!L83 -> 38560.734 | N41: =N$6*Control!M83 -> 45850.316 | O41: =O$6*Control!N83 -> 54582.144
D42: % of Total Sales | E42: =E41/E$6 -> 0.015743107 | F42: =F41/F$6 -> 0.013215399 | G42: =G41/G$6 -> 0.014212721 | H42: =H41/H$6 -> 0.010438295 | I42: =I41/I$6 -> 0.010438295 | J42: =J41/J$6 -> 0.010438295 | K42: =K41/K$6 -> 0.014390409 | L42: =L41/L$6 -> 0.014390409 | ... O42: =O41/O$6 -> 0.014390409
B43: 고정비 | E43: =E45+E49+E51+E53+E55+E47 -> 5220.352 | F43: =F45+F49+F51+F53+F55+F47 -> 4854.291 | G43: =G45+G49+G51+G53+G55+G47 -> 4806.921 | H43: =H45+H49+H51+H53+H55+H47 -> 5592.788 | I43: =I45+I49+I51+I53+I55+I47 -> 5592.788 | J43: =J45+J49+J51+J53+J55+J47 -> 11185.576 | K43: =K45+K49+K51+K53+K55+K47 -> 11409.288 | L43: =L45+L49+L51+L53+L55+L47 -> 11637.473 | ... O43: =O45+O49+O51+O53+O55+O47 -> 12349.78
C44: % of Total Sales | E44: =E43/E$6 -> 0.0070279091 | F44: =F43/F$6 -> 0.0040952178 | G44: =G43/G$6 -> 0.0036330362 | H44: =H43/H$6 -> 0.0061419725 | I44: =I43/I$6 -> 0.0061419725 | J44: =J43/J$6 -> 0.0061419725 | K44: =K43/K$6 -> 0.0059971266 | L44: =L43/L$6 -> 0.0051575857 | ... O44: =O43/O$6 -> 0.0032559802
C45: 여비교통비 | E45: =Dart_Cost!C11/1000 -> 298.819 | F45: =Dart_Cost!D11/1000 -> 406.295 | G45: =Dart_Cost!E11/1000 -> 306.753 | H45: =Dart_Cost!F11/1000 -> 182.523 | I45: =H45 -> 182.523 | J45: =H45+I45 -> 365.046 | K45: =J45*(1+Control!J87) -> 372.34692 | L45: =K45*(1+Control!K87) -> 379.79386 | M45: =L45*(1+Control!L87) -> 387.38974 | N45: =M45*(1+Control!M87) -> 395.13753 | O45: =N45*(1+Control!N87) -> 403.04028
D46: % of Total Sales | E46: =E45/E$6 -> 0.00040228567 | F46: =F45/F$6 -> 0.00034276201 | G46: =G45/G$6 -> 0.0002318417 | H46: =H45/H$6 -> 0.00020044587 | I46: =I45/I$6 -> 0.00020044587 | J46: =J45/J$6 -> 0.00020044587 | K46: =K45/K$6 -> 0.00019571876 | L46: =L45/L$6 -> 0.00016831999 | ... O46: =O45/O$6 -> 0.00010626029
C47: 대손상각비 | E47: =Dart_Cost!C13/1000 -> 0 | F47: =Dart_Cost!D13/1000 -> 1.5 | G47: =Dart_Cost!E13/1000 -> 6.4 | H47: =Dart_Cost!F13/1000 -> 0 | I47: =H47 -> 0 | J47: =H47+I47 -> 0 | K47: =J47*(1+Control!J88) -> 0 | L47: =K47*(1+Control!K88) -> 0 | M47: =L47*(1+Control!L88) -> 0 | N47: =M47*(1+Control!M88) -> 0 | O47: =N47*(1+Control!N88) -> 0
D48: % of Total Sales | E48: =E47/E$6 -> 0 | F48: =F47/F$6 -> 1.2654426e-06 | G48: =G47/G$6 -> 4.8370738e-06 | H48: =H47/H$6 -> 0 | I48: =I47/I$6 -> 0 | J48: =J47/J$6 -> 0 | K48: =K47/K$6 -> 0 | L48: =L47/L$6 -> 0 | ... O48: =O47/O$6 -> 0
C49: 접대비 | E49: =Dart_Cost!C10/1000 -> 811.035 | F49: =Dart_Cost!D10/1000 -> 1648.621 | G49: =Dart_Cost!E10/1000 -> 1293.548 | H49: =Dart_Cost!F10/1000 -> 721.307 | I49: =H49 -> 721.307 | J49: =H49+I49 -> 1442.614 | K49: =J49*(1+Control!J89) -> 1471.4663 | L49: =K49*(1+Control!K89) -> 1500.8956 | M49: =L49*(1+Control!L89) -> 1530.9135 | N49: =M49*(1+Control!M89) -> 1561.5318 | O49: =N49*(1+Control!N89) -> 1592.7624
D50: % of Total Sales | E50: =E49/E$6 -> 0.0010918575 | F50: =F49/F$6 -> 0.0013908235 | G50: =G49/G$6 -> 0.00097765423 | H50: =H49/H$6 -> 0.00079213582 | I50: =I49/I$6 -> 0.00079213582 | J50: =J49/J$6 -> 0.00079213582 | K50: =K49/K$6 -> 0.00077345492 | L50: =L49/L$6 -> 0.00066517856 | ... O50: =O49/O$6 -> 0.00041992676
C51: 지급임차료 | E51: =Dart_Cost!C15/1000 -> 1677.407 | F51: =Dart_Cost!D15/1000 -> 1566.864 | G51: =Dart_Cost!E15/1000 -> 1861.07 | H51: =Dart_Cost!F15/1000 -> 1190.181 | I51: =H51 -> 1190.181 | J51: =H51+I51 -> 2380.362 | K51: =J51*(1+Control!J90) -> 2427.9692 | L51: =K51*(1+Control!K90) -> 2476.5286 | M51: =L51*(1+Control!L90) -> 2526.0592 | N51: =M51*(1+Control!M90) -> 2576.5804 | O51: =N51*(1+Control!N90) -> 2628.112
D52: % of Total Sales | E52: =E51/E$6 -> 0.0022582125 | F52: =F51/F$6 -> 0.001321851 | G52: =G51/G$6 -> 0.0014065833 | H52: =H51/H$6 -> 0.001307051 | I52: =I51/I$6 -> 0.001307051 | J52: =J51/J$6 -> 0.001307051 | K52: =K51/K$6 -> 0.0012762268 | L52: =L51/L$6 -> 0.0010975672 | ... O52: =O51/O$6 -> 0.00069289338
C53: 차량유지비 | E53: =Dart_Cost!C17/1000 -> 855.248 | F53: =Dart_Cost!D17/1000 -> 1037.155 | G53: =Dart_Cost!E17/1000 -> 1140.067 | H53: =Dart_Cost!F17/1000 -> 771.644 | I53: =H53 -> 771.644 | J53: =H53+I53 -> 1543.288 | K53: =J53*(1+Control!J91) -> 1574.1538 | L53: =K53*(1+Control!K91) -> 1605.6368 | M53: =L53*(1+Control!L91) -> 1637.7496 | N53: =M53*(1+Control!M91) -> 1670.5046 | O53: =N53*(1+Control!N91) -> 1703.9147
D54: % of Total Sales | E54: =E53/E$6 -> 0.0011513793 | F54: =F53/F$6 -> 0.00087497343 | G54: =G53/G$6 -> 0.0008616544 | H54: =H53/H$6 -> 0.00084741567 | I54: =I53/I$6 -> 0.00084741567 | J54: =J53/J$6 -> 0.00084741567 | K54: =K53/K$6 -> 0.0008274311 | L54: =L53/L$6 -> 0.00071159859 | ... O54: =O53/O$6 -> 0.00044923169
C55: 운반비 | E55: =Dart_Cost!C18/1000 -> 1577.843 | F55: =Dart_Cost!D18/1000 -> 193.856 | G55: =Dart_Cost!E18/1000 -> 199.083 | H55: =Dart_Cost!F18/1000 -> 2727.133 | I55: =H55 -> 2727.133 | J55: =H55+I55 -> 5454.266 | K55: =J55*(1+Control!J92) -> 5563.3513 | L55: =K55*(1+Control!K92) -> 5674.6183 | M55: =L55*(1+Control!L92) -> 5788.1107 | N55: =M55*(1+Control!M92) -> 5903.8729 | O55: =N55*(1+Control!N92) -> 6021.9504
D56: % of Total Sales | E56: =E55/E$6 -> 0.0021241742 | F56: =F55/F$6 -> 0.00016354243 | G56: =G55/G$6 -> 0.00015046549 | H56: =H55/H$6 -> 0.0029949241 | I56: =I55/I$6 -> 0.0029949241 | J56: =J55/J$6 -> 0.0029949241 | K56: =K55/K$6 -> 0.002924295 | L56: =L55/L$6 -> 0.0025149214 | ... O56: =O55/O$6 -> 0.0015876681
B57: Total Labor | E57: =E9+E14+E16+E19+E43 -> 732137.26 | F57: =F9+F14+F16+F19+F43 -> 1156150.8 | G57: =G9+G14+G16+G19+G43 -> 1285415.4 | H57: =H9+H14+H16+H19+H43 -> 872106.02 | I57: =I9+I14+I16+I19+I43 -> 872106.02 | J57: =J9+J14+J16+J19+J43 -> 1744212 | K57: =K9+K14+K16+K19+K43 -> 1786540 | L57: =L9+L14+L16+L19+L43 -> 2111660.9 | ... O57: =O9+O14+O16+O19+O43 -> 3536128.4
D58: check>> | E58: =ROUND(E57,0)=ROUND(Dart_Cost!C28/1000,0) -> TRUE | F58: =ROUND(F57,0)=ROUND(Dart_Cost!D28/1000,0) -> TRUE | G58: =ROUND(G57,0)=ROUND(Dart_Cost!E28/1000,0) -> TRUE | H58: =ROUND(H57,0)=ROUND(Dart_Cost!F28/1000,0) -> TRUE

Sheet CapEx,D&A
B1: CapEx, D&A | F1: Index
F3: Historical | K3: Forecast
B4: KRW in millions | F4: 2018 | G4: 2019 | H4: 2020 | I4: 2021.1H | J4: 2021.2H | K4: 2021 | L4: 2022 | M4: 2023 | N4: 2024 | O4: 2025 | P4: 2016
B5: CapEx | F5: =F6+F7 -> 6203.4207 | G5: =G6+G7 -> 4496.4141 | H5: =H6+H7 -> 2238.3799 | I5: =I6+I7 -> 2044.2493 | J5: =J6+J7 -> 2044.2493 | K5: =K6+K7 -> 4088.4986 | L5: =L6+L7 -> 4256.2992 | M5: =M6+M7 -> 4469.1141 | ... P5: =P6+P7 -> 5173.5582
C6: 유형자산(사용권) | F6: =Dart_FS!C138/10^6 -> 4767.0067 | G6: =Dart_FS!D138/10^6 -> 3551.6559 | H6: =Dart_FS!E138/10^6 -> 1190.6147 | I6: =Dart_FS!F138/10^6 -> 1704.1197 | J6: =I6 -> 1704.1197 | K6: =I6+J6 -> 3408.2394 | L6: =Control!J96 -> 3229 | M6: =Control!K96 -> 3390.45 | N6: =Control!L96 -> 3559.9725 | O6: =Control!M96 -> 3737.9711 | P6: =Control!N96 -> 3924.8697
C7: 무형자산 | F7: =Dart_FS!C139/10^6 -> 1436.414 | G7: =Dart_FS!D139/10^6 -> 944.75825 | H7: =Dart_FS!E139/10^6 -> 1047.7652 | I7: =Dart_FS!F139/10^6 -> 340.1296 | J7: =I7 -> 340.1296 | K7: =I7+J7 -> 680.2592 | L7: =Control!J97 -> 1027.2992 | M7: =Control!K97 -> 1078.6641 | N7: =Control!L97 -> 1132.5973 | O7: =Control!M97 -> 1189.2272 | P7: =Control!N97 -> 1248.6885
B8: D&A | F8: =F9+F10 -> 7432.3771 | G8: =G9+G10 -> 13537.456 | H8: =H9+H10 -> 15873.972 | I8: =I9+I10 -> 19724.316 | J8: =J9+J10 -> 19724.316 | K8: =K9+K10 -> 39448.632 | L8: =L9+L10 -> 33669.772 | M8: =M9+M10 -> 30919.503 | ... P8: =P9+P10 -> 25746.402
C9: 유형자산 | F9: =Dart_FS!C82/10^6 -> 6680.6336 | G9: =Dart_FS!D82/10^6 -> 12256.755 | H9: =Dart_FS!E82/10^6 -> 14214.472 | I9: =Dart_FS!F82/10^6 -> 18802.028 | J9: =I9 -> 18802.028 | K9: =I9+J9 -> 37604.056 | L9: =AVERAGE(K15,K15+L6+L12)*L18 -> 32110.436 | M9: =AVERAGE(L15,L15+M6+M12)*M18 -> 29350.294 | N9: =AVERAGE(M15,M15+N6+N12)*N18 -> 27175.277 | O9: =AVERAGE(N15,N15+O6+O12)*O18 -> 25470.016 | P9: =AVERAGE(O15,O15+P6+P12)*P18 -> 24142.297
C10: 무형자산 | F10: =Dart_FS!C84/10^6 -> 751.74352 | G10: =Dart_FS!D84/10^6 -> 1280.7009 | H10: =Dart_FS!E84/10^6 -> 1659.4994 | I10: =Dart_FS!F84/10^6 -> 922.28807 | J10: =I10 -> 922.28807 | K10: =I10+J10 -> 1844.5761 | L10: =AVERAGE(K16,K16+L7+L13)*L19 -> 1559.336 | M10: =AVERAGE(L16,L16+M7+M13)*M19 -> 1569.2089 | N10: =AVERAGE(M16,M16+N7+N13)*N19 -> 1579.9373 | O10: =AVERAGE(N16,N16+O7+O13)*O19 -> 1591.5568 | P10: =AVERAGE(O16,O16+P7+P13)*P19 -> 1604.1048
B11: 기타변동 | F11: =F12+F13 -> 0 | G11: =G12+G13 -> 9963.1981 | H11: =H12+H13 -> 14308.68 | I11: =I12+I13 -> 112172.86 | J11: =J12+J13 -> 11905.699 | K11: =K12+K13 -> 124078.55 | L11: =L12+L13 -> 16000 | M11: =M12+M13 -> 16000 | ... P11: =P12+P13 -> 16000
C12: 유형자산 | F12: 0 | G12: =G15-(F15+G6-G9) -> 9963.1981 | H12: =H15-(G15+H6-H9) -> 13421.956 | I12: =I15-(H15+I6-I9) -> 111959.73 | J12: =AVERAGE(G12:H12) -> 11692.577 | K12: =I12+J12 -> 123652.31 | L12: =Control!J98 -> 15000 | M12: =Control!K98 -> 15000 | N12: =Control!L98 -> 15000 | O12: =Control!M98 -> 15000 | P12: =Control!N98 -> 15000
C13: 무형자산 | F13: 0 | G13: =G16-(F16+G7-G10) -> 0 | H13: =H16-(G16+H7-H10) -> 886.72391 | I13: =I16-(H16+I7-I10) -> 213.12179 | J13: =I13 -> 213.12179 | K13: =I13+J13 -> 426.24359 | L13: =Control!J99 -> 1000 | M13: =Control!K99 -> 1000 | N13: =Control!L99 -> 1000 | O13: =Control!M99 -> 1000 | P13: =Control!N99 -> 1000
B14: 장부가액 | F14: =F15+F16 -> 138077.16 | G14: =G15+G16 -> 138999.32 | H14: =H15+H16 -> 139672.41 | I14: =I15+I16 -> 234165.2 | J14: =J15+J16 -> 228390.83 | K14: =K15+K16 -> 228390.83 | L14: =L15+L16 -> 214977.36 | M14: =M15+M16 -> 204526.97 | ... P14: =P15+P16 -> 185757.1
C15: 유형자산(사용권) | F15: =(Dart_FS!C17 + Dart_FS!C19 ) /10^6 -> 60324.988 | G15: =(Dart_FS!D17 + Dart_FS!D19 ) /10^6 -> 61583.087 | H15: =(Dart_FS!E17 + Dart_FS!E19 ) /10^6 -> 61981.185 | I15: =(Dart_FS!F17 + Dart_FS!F19 ) /10^6 -> 156843.01 | J15: =I15+J6-J9+J12 -> 151437.68 | K15: =J15 -> 151437.68 | L15: =K15+L6-L9+L12 -> 137556.24 | M15: =L15+M6-M9+M12 -> 126596.4 | N15: =M15+N6-N9+N12 -> 117981.1 | O15: =N15+O6-O9+O12 -> 111249.05 | P15: =O15+P6-P9+P12 -> 106031.62
C16: 무형자산 | F16: =Dart_FS!C18/10^6 -> 77752.174 | G16: =Dart_FS!D18/10^6 -> 77416.232 | H16: =Dart_FS!E18/10^6 -> 77691.221 | I16: =Dart_FS!F18/10^6 -> 77322.185 | J16: =I16+J7-J10+J13 -> 76953.148 | K16: =J16 -> 76953.148 | L16: =K16+L7-L10+L13 -> 77421.111 | M16: =L16+M7-M10+M13 -> 77930.566 | N16: =M16+N7-N10+N13 -> 78483.226 | O16: =N16+O7-O10+O13 -> 79080.897 | P16: =O16+P7-P10+P13 -> 79725.481
B17: 상각비/장부가액
C18: 유형자산 | G18: =G9/AVERAGE(F15,F15+G6+G12) -> 0.18271189 | H18: =H9/AVERAGE(G15,G15+H6+H12) -> 0.20633767 | K18: =K9/AVERAGE(H15+K6+K12) -> 0.19891933 | L18: =Control!J100 -> 0.2 | M18: =Control!K100 -> 0.2 | N18: =Control!L100 -> 0.2 | O18: =Control!M100 -> 0.2 | P18: =Control!N100 -> 0.2
C19: 무형자산 | G19: =G10/AVERAGE(F16,F16+G7+G13) -> 0.016372109 | H19: =H10/AVERAGE(G16,G16+H7+H13) -> 0.021171546 | K19: =K10/AVERAGE(H16,H16+K7+K13) -> 0.023574523 | L19: =Control!J101 -> 0.02 | M19: =Control!K101 -> 0.02 | N19: =Control!L101 -> 0.02 | O19: =Control!M101 -> 0.02 | P19: =Control!N101 -> 0.02

Sheet Labor
B1: Labor | G1: Index
G3: Historical | L3: Forecast
B4: KRW in millions | G4: 2018 | H4: 2019 | I4: 2020 | J4: 2021.1H | K4: 2021.2H | L4: 2021 | M4: 2022 | N4: =M4+1 -> 2023 | O4: =N4+1 -> 2024 | P4: =O4+1 -> 2025 | Q4: =P4+1 -> 2026 | T4: 2022 | U4: 2023 | V4: 2024 | W4: 2025 | X4: 2026
B5: 중고차 판매대수 | G5: =Sales!I7 -> 52196 | H5: =Sales!J7 -> 84328 | I5: =Sales!K7 -> 90149 | J5: =Sales!L7 -> 54426 | K5: =Sales!M7 -> 54426 | L5: =Sales!N7 -> 108852 | M5: =Sales!O7 -> 111343.67 | N5: =Sales!P7 -> 131007.24 | ... Q5: =Sales!S7 -> 215003.75
B6: Total Sales | G6: =Sales!I160 -> 742803 | H6: =Sales!J160 -> 1185356 | I6: =Sales!K160 -> 1323114 | J6: =Sales!L160 -> 910585 | K6: =Sales!M160 -> 910585 | L6: =Sales!N160 -> 1821170 | M6: =Sales!O160 -> 1902459 | N6: =Sales!P160 -> 2256380 | ... Q6: =Sales!S160 -> 3792952.9
B7: 경매 | G7: =Sales!I140 -> 50546 | H7: =Sales!J140 -> 80966 | I7: =Sales!K140 -> 98049 | J7: =Sales!L140 -> 69172 | K7: =Sales!M140 -> 69172 | L7: =Sales!N140 -> 138344 | M7: =Sales!O140 -> 166012.8 | N7: =Sales!P140 -> 199215.36 | ... Q7: =Sales!S140 -> 344244.14
B8: 렌탈 | G8: =Sales!I146 -> 0 | H8: =Sales!J146 -> 0 | I8: =Sales!K146 -> 0 | J8: =Sales!L146 -> 22392 | K8: =Sales!M146 -> 22392 | L8: =Sales!N146 -> 44784 | M8: =Sales!O146 -> 53740.8 | N8: =Sales!P146 -> 64488.96 | ... Q8: =Sales!S146 -> 111436.92
B9: 종업원 급여 | G9: =Dart_Cost!C33/1000 -> 25858.31 | H9: =Dart_Cost!D33/1000 -> 40917.289 | I9: =Dart_Cost!E33/1000 -> 44758.009 | J9: =J10+J19+J28+J37+J44+J51 -> 27738.124 | K9: =K10+K19+K28+K37+K44+K51 -> 27738.124 | L9: =L10+L19+L28+L37+L44+L51 -> 55476.248 | M9: =M10+M19+M28+M37+M44+M51 -> 58729.897 | N9: =N10+N19+N28+N37+N44+N51 -> 69817.432 | O9: =O10+O19+O28+O37+O44+O51 -> 83165.445 | P9: =P10+P19+P28+P37+P44+P51 -> 99173.808 | Q9: =Q10+Q19+Q28+Q37+Q44+Q51 -> 118344.84
C10: 중고차 | J10: =J11+J15 -> 22029.607 | K10: =K11+K15 -> 22029.607 | L10: =L11+L15 -> 44059.214 | M10: =M11+M15 -> 45931.338 | N10: =N11+N15 -> 55095.958 | O10: =O11+O15 -> 66200.285 | P10: =P11+P15 -> 79675.761 | Q10: =Q11+Q15 -> 95983.975
D11: 남 | J11: =VALUE(Dart_Labor!S10)/1000 -> 20705.105 | K11: =K12*K14 -> 20705.105 | L11: =L12*L14 -> 41410.21 | M11: =M12*M14 -> 43154.298 | N11: =N12*N14 -> 51765.763 | O11: =O12*O14 -> 62217.831 | P11: =P12*P14 -> 74896.816 | Q11: =Q12*Q14 -> 90215.788
E12: 직원수 | J12: =VALUE(Dart_Labor!H10) -> 784 | K12: =J12 -> 784 | L12: =K12 -> 784 | M12: =ROUND(M$5/M13,0) -> 801 | N12: =ROUND(N$5/N13,0) -> 942 | O12: =ROUND(O$5/O13,0) -> 1110 | P12: =ROUND(P$5/P13,0) -> 1310 | Q12: =ROUND(Q$5/Q13,0) -> 1547
F13: 1인당 판매대수 | J13: =J$5/J12 -> 69.420918 | K13: =K$5/K12 -> 69.420918 | L13: =L$5/L12 -> 138.84184 | M13: =Control!J106 -> 139 | N13: =Control!K106 -> 139 | O13: =Control!L106 -> 139 | P13: =Control!M106 -> 139 | Q13: =Control!N106 -> 139
E14: 평균급여 | J14: =J11/J12 -> 26.409573 | K14: =J14 -> 26.409573 | L14: =J14+K14 -> 52.819146 | M14: =Control!J107 -> 53.875529 | N14: =Control!K107 -> 54.953039 | O14: =Control!L107 -> 56.0521 | P14: =Control!M107 -> 57.173142 | Q14: =Control!N107 -> 58.316605
D15: 여 | J15: =VALUE(Dart_Labor!S11)/1000 -> 1324.502 | K15: =K16*K18 -> 1324.502 | L15: =L16*L18 -> 2649.0041 | M15: =M16*M18 -> 2777.0393 | N15: =N16*N18 -> 3330.1955 | O15: =O16*O18 -> 3982.4544 | P15: =P16*P18 -> 4778.9453 | Q15: =Q16*Q18 -> 5768.187
E16: 직원수 | J16: =VALUE(Dart_Labor!H11) -> 72 | K16: =J16 -> 72 | L16: =K16 -> 72 | M16: =ROUND(M$5/M17,0) -> 74 | N16: =ROUND(N$5/N17,0) -> 87 | O16: =ROUND(O$5/O17,0) -> 102 | P16: =ROUND(P$5/P17,0) -> 120 | Q16: =ROUND(Q$5/Q17,0) -> 142
F17: 1인당 판매대수 | J17: =J$5/J16 -> 755.91667 | K17: =K$5/K16 -> 755.91667 | L17: =L$5/L16 -> 1511.8333 | M17: =Control!J108 -> 1511.8333 | N17: =Control!K108 -> 1511.8333 | O17: =Control!L108 -> 1511.8333 | P17: =Control!M108 -> 1511.8333 | Q17: =Control!N108 -> 1511.8333
E18: 평균급여 | J18: =J15/J16 -> 18.395862 | K18: =J18 -> 18.395862 | L18: =J18+K18 -> 36.791723 | M18: =Control!J109 -> 37.527558 | N18: =Control!K109 -> 38.278109 | O18: =Control!L109 -> 39.043671 | P18: =Control!M109 -> 39.824544 | Q18: =Control!N109 -> 40.621035
C19: 경매 | J19: =J20+J24 -> 715.81514 | K19: =K20+K24 -> 715.81514 | L19: =L20+L24 -> 1431.6303 | M19: =M20+M24 -> 1748.1387 | N19: =N20+N24 -> 2124.0897 | O19: =O20+O24 -> 2615.8305 | P19: =P20+P24 -> 3175.6593 | Q19: =Q20+Q24 -> 3912.638
D20: 남 | J20: =VALUE(Dart_Labor!S12)/1000 -> 670.2991 | K20: =K21*K23 -> 670.2991 | L20: =L21*L23 -> 1340.5982 | M20: =M21*M23 -> 1655.286 | N20: =N21*N23 -> 1982.025 | O20: =O21*O23 -> 2470.9246 | P20: =P21*P23 -> 2978.5872 | Q20: =Q21*Q23 -> 3661.3711
E21: 직원수 | J21: =VALUE(Dart_Labor!H12) -> 19 | K21: =J21 -> 19 | L21: =K21 -> 19 | M21: =ROUND(M$7/M22,0) -> 23 | N21: =ROUND(N$7/N22,0) -> 27 | O21: =ROUND(O$7/O22,0) -> 33 | P21: =ROUND(P$7/P22,0) -> 39 | Q21: =ROUND(Q$7/Q22,0) -> 47
F22: 1인당 경매매출 | J22: =J$7/J21 -> 3640.6316 | K22: =K$7/K21 -> 3640.6316 | L22: =L$7/L21 -> 7281.2632 | M22: =Control!J111 -> 7281.2632 | N22: =Control!K111 -> 7281.2632 | O22: =Control!L111 -> 7281.2632 | P22: =Control!M111 -> 7281.2632 | Q22: =Control!N111 -> 7281.2632
E23: 평균급여 | J23: =J20/J21 -> 35.2789 | K23: =J23 -> 35.2789 | L23: =J23+K23 -> 70.5578 | M23: =Control!J112 -> 71.968956 | N23: =Control!K112 -> 73.408335 | O23: =Control!L112 -> 74.876502 | P23: =Control!M112 -> 76.374032 | Q23: =Control!N112 -> 77.901512
D24: 여 | J24: =VALUE(Dart_Labor!S13)/1000 -> 45.516042 | K24: =K25*K27 -> 45.516042 | L24: =L25*L27 -> 91.032085 | M24: =M25*M27 -> 92.852727 | N24: =N25*N27 -> 142.06467 | O24: =O25*O27 -> 144.90597 | P24: =P25*P27 -> 197.07211 | Q24: =Q25*Q27 -> 251.26694
E25: 직원수 | J25: =VALUE(Dart_Labor!H13) -> 2 | K25: =J25 -> 2 | L25: =K25 -> 2 | M25: =ROUND(M$7/M26,0) -> 2 | N25: =ROUND(N$7/N26,0) -> 3 | O25: =ROUND(O$7/O26,0) -> 3 | P25: =ROUND(P$7/P26,0) -> 4 | Q25: =ROUND(Q$7/Q26,0) -> 5
F26: 1인당 경매매출 | J26: =J$7/J25 -> 34586 | K26: =K$7/K25 -> 34586 | L26: =L$7/L25 -> 69172 | M26: =Control!J113 -> 69172 | N26: =Control!K113 -> 69172 | O26: =Control!L113 -> 69172 | P26: =Control!M113 -> 69172 | Q26: =Control!N113 -> 69172
E27: 평균급여 | J27: =J24/J25 -> 22.758021 | K27: =J27 -> 22.758021 | L27: =J27+K27 -> 45.516042 | M27: =Control!J114 -> 46.426363 | N27: =Control!K114 -> 47.354891 | O27: =Control!L114 -> 48.301988 | P27: =Control!M114 -> 49.268028 | Q27: =Control!N114 -> 50.253389
C28: 렌탈 | J28: =J29+J33 -> 1202.318 | K28: =K29+K33 -> 1202.318 | L28: =L29+L33 -> 2404.6361 | M28: =M29+M33 -> 2956.9264 | N28: =N29+N33 -> 3605.353 | O28: =O29+O33 -> 4426.0576 | P28: =P29+P33 -> 5434.2217 | Q28: =Q29+Q33 -> 6560.5395
D29: 남 | J29: =VALUE(Dart_Labor!S14)/1000 -> 901.17408 | K29: =K30*K32 -> 901.17408 | L29: =L30*L32 -> 1802.3482 | M29: =M30*M32 -> 2206.0742 | N29: =N30*N32 -> 2700.2348 | O29: =O30*O32 -> 3289.786 | P29: =P30*P32 -> 4057.9128 | Q29: =Q30*Q32 -> 4935.0463
E30: 직원수 | J30: =VALUE(Dart_Labor!H14) -> 25 | K30: =J30 -> 25 | L30: =K30 -> 25 | M30: =ROUND(M$8/M31,0) -> 30 | N30: =ROUND(N$8/N31,0) -> 36 | O30: =ROUND(O$8/O31,0) -> 43 | P30: =ROUND(P$8/P31,0) -> 52 | Q30: =ROUND(Q$8/Q31,0) -> 62
F31: 1인당 렌탈매출 | J31: =J$8/J30 -> 895.68 | K31: =K$8/K30 -> 895.68 | L31: =L$8/L30 -> 1791.36 | M31: =Control!J116 -> 1791.36 | N31: =Control!K116 -> 1791.36 | O31: =Control!L116 -> 1791.36 | P31: =Control!M116 -> 1791.36 | Q31: =Control!N116 -> 1791.36
E32: 평균급여 | J32: =J29/J30 -> 36.046963 | K32: =J32 -> 36.046963 | L32: =J32+K32 -> 72.093927 | M32: =Control!J117 -> 73.535805 | N32: =Control!K117 -> 75.006521 | O32: =Control!L117 -> 76.506652 | P32: =Control!M117 -> 78.036785 | Q32: =Control!N117 -> 79.597521
D33: 여 | J33: =VALUE(Dart_Labor!S15)/1000 -> 301.14395 | K33: =K34*K36 -> 301.14395 | L33: =L34*L36 -> 602.2879 | M33: =M34*M36 -> 750.85225 | N33: =N34*N36 -> 905.11826 | O33: =O34*O36 -> 1136.2715 | P33: =P34*P36 -> 1376.3089 | Q33: =Q34*Q36 -> 1625.4932
E34: 직원수 | J34: =VALUE(Dart_Labor!H15) -> 9 | K34: =J34 -> 9 | L34: =K34 -> 9 | M34: =ROUND(M$8/M35,0) -> 11 | N34: =ROUND(N$8/N35,0) -> 13 | O34: =ROUND(O$8/O35,0) -> 16 | P34: =ROUND(P$8/P35,0) -> 19 | Q34: =ROUND(Q$8/Q35,0) -> 22
F35: 1인당 렌탈매출 | J35: =J$8/J34 -> 2488 | K35: =K$8/K34 -> 2488 | L35: =L$8/L34 -> 4976 | M35: =Control!J118 -> 4976 | N35: =Control!K118 -> 4976 | O35: =Control!L118 -> 4976 | P35: =Control!M118 -> 4976 | Q35: =Control!N118 -> 4976
E36: 평균급여 | J36: =J33/J34 -> 33.460439 | K36: =J36 -> 33.460439 | L36: =J36+K36 -> 66.920878 | M36: =Control!J119 -> 68.259295 | N36: =Control!K119 -> 69.624481 | O36: =Control!L119 -> 71.016971 | P36: =Control!M119 -> 72.43731 | Q36: =Control!N119 -> 73.886057
C37: 마케팅 | J37: =J38+J41 -> 786.11388 | K37: =K38+K41 -> 786.11388 | L37: =L38+L41 -> 1572.2278 | M37: =M38+M41 -> 1721.1217 | N37: =N38+N41 -> 1995.1408 | O37: =O38+O41 -> 2279.4323 | P37: =P38+P41 -> 2574.2974 | Q37: =Q38+Q41 -> 2880.0452
D38: 남 | J38: =VALUE(Dart_Labor!S16)/1000 -> 476.1762 | K38: =K39*K40 -> 476.1762 | L38: =L39*L40 -> 952.35241 | M38: =M39*M40 -> 1036.1594 | N38: =N39*N40 -> 1188.9929 | O38: =O39*O40 -> 1347.5253 | P38: =P39*P40 -> 1511.9234 | Q38: =Q39*Q40 -> 1682.3584
E39: 직원수 | J39: =VALUE(Dart_Labor!H16) -> 15 | K39: =J39 -> 15 | L39: =K39 -> 15 | M39: =Control!J121 -> 16 | N39: =Control!K121 -> 18 | O39: =Control!L121 -> 20 | P39: =Control!M121 -> 22 | Q39: =Control!N121 -> 24
E40: 평균급여 | J40: =J38/J39 -> 31.74508 | K40: =J40 -> 31.74508 | L40: =J40+K40 -> 63.490161 | M40: =Control!J122 -> 64.759964 | N40: =Control!K122 -> 66.055163 | O40: =Control!L122 -> 67.376266 | P40: =Control!M122 -> 68.723792 | Q40: =Control!N122 -> 70.098268
D41: 여 | J41: =VALUE(Dart_Labor!S17)/1000 -> 309.93767 | K41: =K42*K43 -> 309.93767 | L41: =L42*L43 -> 619.87535 | M41: =M42*M43 -> 684.96226 | N41: =N42*N43 -> 806.14789 | O41: =O42*O43 -> 931.90696 | P41: =P42*P43 -> 1062.3739 | Q41: =Q42*Q43 -> 1197.6868
E42: 직원수 | J42: =VALUE(Dart_Labor!H17) -> 12 | K42: =J42 -> 12 | L42: =K42 -> 12 | M42: =Control!J123 -> 13 | N42: =Control!K123 -> 15 | O42: =Control!L123 -> 17 | P42: =Control!M123 -> 19 | Q42: =Control!N123 -> 21
E43: 평균급여 | J43: =J41/J42 -> 25.828139 | K43: =J43 -> 25.828139 | L43: =J43+K43 -> 51.656279 | M43: =Control!J124 -> 52.689404 | N43: =Control!K124 -> 53.743193 | O43: =Control!L124 -> 54.818056 | P43: =Control!M124 -> 55.914418 | Q43: =Control!N124 -> 57.032706
C44: IT | J44: =J45+J48 -> 623.33431 | K44: =K45+K48 -> 623.33431 | L44: =L45+L48 -> 1246.6686 | M44: =M45+M48 -> 1384.0957 | N44: =N45+N48 -> 1641.2647 | O44: =O45+O48 -> 1908.1669 | P44: =P45+P48 -> 2185.0886 | Q44: =Q45+Q48 -> 2472.324
D45: 남 | J45: =VALUE(Dart_Labor!S18)/1000 -> 521.42172 | K45: =K46*K47 -> 521.42172 | L45: =L46*L47 -> 1042.8434 | M45: =M46*M47 -> 1134.6137 | N45: =N46*N47 -> 1301.9692 | O45: =O46*O47 -> 1475.5651 | P45: =P46*P47 -> 1655.584 | Q45: =Q46*Q47 -> 1842.2135
E46: 직원수 | J46: =VALUE(Dart_Labor!H18) -> 15 | K46: =J46 -> 15 | L46: =K46 -> 15 | M46: =Control!J126 -> 16 | N46: =Control!K126 -> 18 | O46: =Control!L126 -> 20 | P46: =Control!M126 -> 22 | Q46: =Control!N126 -> 24
E47: 평균급여 | J47: =J45/J46 -> 34.761448 | K47: =J47 -> 34.761448 | L47: =J47+K47 -> 69.522896 | M47: =Control!J127 -> 70.913354 | N47: =Control!K127 -> 72.331622 | O47: =Control!L127 -> 73.778254 | P47: =Control!M127 -> 75.253819 | Q47: =Control!N127 -> 76.758895
D48: 여 | J48: =VALUE(Dart_Labor!S19)/1000 -> 101.91258 | K48: =K49*K50 -> 101.91258 | L48: =L49*L50 -> 203.82517 | M48: =M49*M50 -> 249.482 | N48: =N49*N50 -> 339.29553 | O48: =O49*O50 -> 432.60179 | P48: =P49*P50 -> 529.5046 | Q48: =Q49*Q50 -> 630.11047
E49: 직원수 | J49: =VALUE(Dart_Labor!H19) -> 5 | K49: =J49 -> 5 | L49: =K49 -> 5 | M49: =Control!J128 -> 6 | N49: =Control!K128 -> 8 | O49: =Control!L128 -> 10 | P49: =Control!M128 -> 12 | Q49: =Control!N128 -> 14
E50: 평균급여 | J50: =J48/J49 -> 20.382517 | K50: =J50 -> 20.382517 | L50: =J50+K50 -> 40.765033 | M50: =Control!J129 -> 41.580334 | N50: =Control!K129 -> 42.411941 | O50: =Control!L129 -> 43.260179 | P50: =Control!M129 -> 44.125383 | Q50: =Control!N129 -> 45.007891
C51: 사무 | J51: =J52+J55 -> 2380.9355 | K51: =K52+K55 -> 2380.9355 | L51: =L52+L55 -> 4761.8709 | M51: =M52+M55 -> 4988.2765 | N51: =N52+N55 -> 5355.6251 | O51: =O52+O55 -> 5735.6723 | P51: =P52+P55 -> 6128.7791 | Q51: =Q52+Q55 -> 6535.316
D52: 남 | J52: =VALUE(Dart_Labor!S20)/1000 -> 1850.1271 | K52: =K53*K54 -> 1850.1271 | L52: =L53*L54 -> 3700.2542 | M52: =M53*M54 -> 3851.2849 | N52: =N53*N54 -> 4085.4431 | O52: =O53*O54 -> 4327.427 | P52: =P53*P54 -> 4577.4561 | Q52: =Q53*Q54 -> 4835.7554
E53: 직원수 | J53: =VALUE(Dart_Labor!H20) -> 49 | K53: =J53 -> 49 | L53: =K53 -> 49 | M53: =Control!J131 -> 50 | N53: =Control!K131 -> 52 | O53: =Control!L131 -> 54 | P53: =Control!M131 -> 56 | Q53: =Control!N131 -> 58
E54: 평균급여 | J54: =J52/J53 -> 37.757696 | K54: =J54 -> 37.757696 | L54: =J54+K54 -> 75.515391 | M54: =Control!J132 -> 77.025699 | N54: =Control!K132 -> 78.566213 | O54: =Control!L132 -> 80.137537 | P54: =Control!M132 -> 81.740288 | Q54: =Control!N132 -> 83.375094
D55: 여 | J55: =VALUE(Dart_Labor!S21)/1000 -> 530.80839 | K55: =K56*K57 -> 530.80839 | L55: =L56*L57 -> 1061.6168 | M55: =M56*M57 -> 1136.9916 | N55: =N56*N57 -> 1270.182 | O55: =O56*O57 -> 1408.2453 | P55: =P56*P57 -> 1551.323 | Q55: =Q56*Q57 -> 1699.5605
E56: 직원수 | J56: =VALUE(Dart_Labor!H21) -> 20 | K56: =J56 -> 20 | L56: =K56 -> 20 | M56: =Control!J133 -> 21 | N56: =Control!K133 -> 23 | O56: =Control!L133 -> 25 | P56: =Control!M133 -> 27 | Q56: =Control!N133 -> 29
E57: 평균급여 | J57: =J55/J56 -> 26.540419 | K57: =J57 -> 26.540419 | L57: =J57+K57 -> 53.080839 | M57: =Control!J134 -> 54.142455 | N57: =Control!K134 -> 55.225305 | O57: =Control!L134 -> 56.329811 | P57: =Control!M134 -> 57.456407 | Q57: =Control!N134 -> 58.605535
B58: 퇴직급여 | G58: =Dart_Cost!C34/1000 -> 2136.705 | H58: =Dart_Cost!D34/1000 -> 3125.462 | I58: =Dart_Cost!E34/1000 -> 4481.863 | J58: =Dart_Cost!F34/1000 -> 2195.341 | K58: =J58 -> 2195.341 | L58: =J58+K58 -> 4390.682 | M58: =M9*Control!J$136 -> 4967.0347 | N58: =N9*Control!K$136 -> 5904.7542 | O58: =O9*Control!L$136 -> 7033.6519 | P58: =P9*Control!M$136 -> 8387.5466 | Q58: =Q9*Control!N$136 -> 10008.921
C59: % of 종업원급여 | G59: =G58/G$9 -> 0.08263127 | H59: =H58/H$9 -> 0.076384875 | I59: =I58/I$9 -> 0.10013544 | J59: =J58/J$9 -> 0.079145259 | K59: =K58/K$9 -> 0.079145259 | L59: =L58/L$9 -> 0.079145259 | M59: =M58/M$9 -> 0.084574211 | N59: =N58/N$9 -> 0.084574211 | ... Q59: =Q58/Q$9 -> 0.084574211
B60: 복리후생비 | G60: =Dart_Cost!C9/10^3 -> 2999.708 | H60: =Dart_Cost!D9/10^3 -> 4883.806 | I60: =Dart_Cost!E9/10^3 -> 4791.542 | J60: =Dart_Cost!F9/10^3 -> 3111.239 | K60: =J60 -> 3111.239 | L60: =J60+K60 -> 6222.478 | M60: =M11*Control!J$137 -> 4904.2994 | N60: =N11*Control!K$137 -> 5462.364 | O60: =O11*Control!L$137 -> 6371.4431 | P60: =P11*Control!M$137 -> 7735.0779 | Q60: =Q11*Control!N$137 -> 8702.0035
C61: % of 종업원급여 | G61: =G60/G$9 -> 0.11600557 | H61: =H60/H$9 -> 0.11935801 | I61: =I60/I$9 -> 0.1070544 | J61: =J60/J$9 -> 0.11216472 | K61: =K60/K$9 -> 0.11216472 | L61: =L60/L$9 -> 0.11216472 | M61: =M60/M$9 -> 0.083506011 | N61: =N60/N$9 -> 0.078237825 | ... Q61: =Q60/Q$9 -> 0.073530909
B62: Total Labor | G62: =G9+G58+G60 -> 30994.723 | H62: =H9+H58+H60 -> 48926.557 | I62: =I9+I58+I60 -> 54031.414 | J62: =J9+J58+J60 -> 33044.704 | K62: =K9+K58+K60 -> 33044.704 | L62: =L9+L58+L60 -> 66089.408 | M62: =M9+M58+M60 -> 68601.231 | N62: =N9+N58+N60 -> 81184.55 | ... Q62: =Q9+Q58+Q60 -> 137055.76
F63: check>> | G63: =G62=(Dart_Cost!C8+Dart_Cost!C9)/1000 -> TRUE | H63: =H62=(Dart_Cost!D8+Dart_Cost!D9)/1000 -> TRUE | I63: =I62=(Dart_Cost!E8+Dart_Cost!E9)/1000 -> TRUE | J63: =J62=(Dart_Cost!F8+Dart_Cost!F9)/1000 -> TRUE

Sheet NWC
B1: NWC | E1: Index
E4: Historical | J4: Forecast
B5: KRW in 100 millions | E5: 2018 | F5: 2019 | G5: 2020 | H5: 2021.1H | I5: 2021.2H | J5: 2021 | K5: 2022 | L5: 2023 | M5: 2024 | N5: 2025 | O5: 2016
B6: Sales | E6: =Sales!I160 -> 742803 | F6: =Sales!J160 -> 1185356 | G6: =Sales!K160 -> 1323114 | H6: =Sales!L160 -> 910585 | I6: =Sales!M160 -> 910585 | J6: =Sales!N160 -> 1821170 | K6: =Sales!O160 -> 1902459 | L6: =Sales!P160 -> 2256380 | ... O6: =Sales!S160 -> 3792952.9
B7: 변동비 | E7: =Cost!E19 -> 688489.81 | F7: =Cost!F19 -> 1088832.5 | G7: =Cost!G19 -> 1210703.1 | H7: =Cost!H19 -> 812768.74 | I7: =Cost!I19 -> 812768.74 | J7: =Cost!J19 -> 1625537.5 | K7: =Cost!K19 -> 1670801.7 | L7: =Cost!L19 -> 1985483.9 | ... O7: =Cost!O19 -> 3356864.7
B8: 재고자산원가 | E8: =Cost!E21 -> 663748.17 | F8: =Cost!F21 -> 1053521.7 | G8: =Cost!G21 -> 1170061.6 | H8: =Cost!H21 -> 784113.35 | I8: =Cost!I21 -> 784113.35 | J8: =Cost!J21 -> 1568226.7 | K8: =Cost!K21 -> 1604124.1 | L8: =Cost!L21 -> 1906290.6 | ... O8: =Cost!O21 -> 3223324.1
B9: 영업유동자산 | E9: =E10+E12+E14 -> 135219.49 | F9: =F10+F12+F14 -> 157121.87 | G9: =G10+G12+G14 -> 168447.6 | H9: =H10+H12+H14 -> 178547.76 | I9: =I10+I12+I14 -> 178547.76 | J9: =J10+J12+J14 -> 178547.76 | K9: =K10+K12+K14 -> 246242.93 | L9: =L10+L12+L14 -> 272616.85 | ... O9: =O10+O12+O14 -> 460045.96
C10: 매출채권 | E10: =BS!E7 -> 7325.6303 | F10: =BS!F7 -> 4038.9555 | G10: =BS!G7 -> 4665.2039 | H10: =BS!H7 -> 7961.0649 | I10: =H10 -> 7961.0649 | J10: =I10 -> 7961.0649 | K10: =AVERAGE(J$6:K$6)*Control!J141 -> 8051.0053 | L10: =AVERAGE(K$6:L$6)*Control!K141 -> 8991.99 | M10: =AVERAGE(L$6:M$6)*Control!L141 -> 10672.306 | N10: =AVERAGE(M$6:N$6)*Control!M141 -> 12682.646 | O10: =AVERAGE(N$6:O$6)*Control!N141 -> 15089.841
D11: % of Sales | F11: =F10/AVERAGE(E$6:F$6) -> 0.0041894423 | G11: =G10/AVERAGE(F$6:G$6) -> 0.0037195613 | H11: =H10/AVERAGE(G$6,H$6*2) -> 0.0050638332 | I11: =I10/AVERAGE(G$6,I$6*2) -> 0.0050638332 | J11: =J10/AVERAGE(G$6,J$6) -> 0.0050638332 | K11: =K10/AVERAGE(J$6:K$6) -> 0.0043242789 | L11: =L10/AVERAGE(K$6:L$6) -> 0.0043242789 | M11: =M10/AVERAGE(L$6:M$6) -> 0.0043242789 | N11: =N10/AVERAGE(M$6:N$6) -> 0.0043242789 | O11: =O10/AVERAGE(N$6:O$6) -> 0.0043242789
C12: 재고자산 | E12: =BS!E11 -> 125377.11 | F12: =BS!F11 -> 150417.73 | G12: =BS!G11 -> 161331.91 | H12: =BS!H11 -> 165762.87 | I12: =H12 -> 165762.87 | J12: =I12 -> 165762.87 | K12: =AVERAGE(J$8:K$8)*Control!J142 -> 233359.54 | L12: =AVERAGE(K$8:L$8)*Control!K142 -> 258227.67 | M12: =AVERAGE(L$8:M$8)*Control!L142 -> 307085.38 | N12: =AVERAGE(M$8:N$8)*Control!M142 -> 365647.51 | O12: =AVERAGE(N$8:O$8)*Control!N142 -> 435898.88
D13: % of 재고자산원가 | F13: =F12/AVERAGE(E$8:F$8) -> 0.17518241 | G13: =G12/AVERAGE(F$8:G$8) -> 0.14510984 | H13: =H12/AVERAGE(G$8,H$8*2) -> 0.12107043 | I13: =I12/AVERAGE(G$8,I$8*2) -> 0.12107043 | J13: =J12/AVERAGE(G$8,J$8) -> 0.12107043 | K13: =K12/AVERAGE(J$8:K$8) -> 0.1471209 | L13: =L12/AVERAGE(K$8:L$8) -> 0.1471209 | M13: =M12/AVERAGE(L$8:M$8) -> 0.1471209 | N13: =N12/AVERAGE(M$8:N$8) -> 0.1471209 | O13: =O12/AVERAGE(N$8:O$8) -> 0.1471209
C14: 기타유동자산 | E14: =BS!E10 -> 2516.7444 | F14: =BS!F10 -> 2665.187 | G14: =BS!G10 -> 2450.4877 | H14: =BS!H10 -> 4823.8253 | I14: =H14 -> 4823.8253 | J14: =I14 -> 4823.8253 | K14: =AVERAGE(J$6:K$6)*Control!J143 -> 4832.3853 | L14: =AVERAGE(K$6:L$6)*Control!K143 -> 5397.1844 | M14: =AVERAGE(L$6:M$6)*Control!L143 -> 6405.7462 | N14: =AVERAGE(M$6:N$6)*Control!M143 -> 7612.3949 | O14: =AVERAGE(N$6:O$6)*Control!N143 -> 9057.2448
D15: % of Sales | F15: =F14/AVERAGE(E$6:F$6) -> 0.0027644889 | G15: =G14/AVERAGE(F$6:G$6) -> 0.0019537708 | H15: =H14/AVERAGE(G$6,H$6*2) -> 0.003068314 | I15: =I14/AVERAGE(G$6,I$6*2) -> 0.003068314 | J15: =J14/AVERAGE(G$6,J$6) -> 0.003068314 | K15: =K14/AVERAGE(J$6:K$6) -> 0.0025955245 | L15: =L14/AVERAGE(K$6:L$6) -> 0.0025955245 | M15: =M14/AVERAGE(L$6:M$6) -> 0.0025955245 | N15: =N14/AVERAGE(M$6:N$6) -> 0.0025955245 | O15: =O14/AVERAGE(N$6:O$6) -> 0.0025955245
B16: 영업유동부채 | E16: =E17+E19 -> 16632.495 | F16: =F17+F19 -> 15962.706 | G16: =G17+G19 -> 18774.702 | H16: =H17+H19 -> 35547.618 | I16: =I17+I19 -> 35547.618 | J16: =J17+J19 -> 35547.618 | K16: =K17+K19 -> 32610.95 | L16: =L17+L19 -> 36171.929 | ... O16: =O17+O19 -> 61053.611
C17: 매입채무및기타채무 | E17: =BS!E22 -> 6251.7466 | F17: =BS!F22 -> 4267.1034 | G17: =BS!G22 -> 6132.9 | H17: =BS!H22 -> 8997.5112 | I17: =H17 -> 8997.5112 | J17: =I17 -> 8997.5112 | K17: =AVERAGE(J$7:K$7)*Control!J144 -> 9054.1808 | L17: =AVERAGE(K$7:L$7)*Control!K144 -> 10042.859 | M17: =AVERAGE(L$7:M$7)*Control!L144 -> 11942.695 | N17: =AVERAGE(M$7:N$7)*Control!M144 -> 14219.73 | O17: =AVERAGE(N$7:O$7)*Control!N144 -> 16951.068
D18: % of V.C | F18: =F17/AVERAGE(E$7:F$7) -> 0.0048017215 | G18: =G17/AVERAGE(F$7:G$7) -> 0.0053340335 | H18: =H17/AVERAGE(G$7,H$7*2) -> 0.0063446742 | I18: =I17/AVERAGE(G$7,I$7*2) -> 0.0063446742 | J18: =J17/AVERAGE(G$7,J$7) -> 0.0063446742 | K18: =K17/AVERAGE(J$7:K$7) -> 0.0054934764 | L18: =L17/AVERAGE(K$7:L$7) -> 0.0054934764 | M18: =M17/AVERAGE(L$7:M$7) -> 0.0054934764 | N18: =N17/AVERAGE(M$7:N$7) -> 0.0054934764 | O18: =O17/AVERAGE(N$7:O$7) -> 0.0054934764
C19: 기타유동부채 | E19: =BS!E25 -> 10380.748 | F19: =BS!F25 -> 11695.602 | G19: =BS!G25 -> 12641.802 | H19: =BS!H25 -> 26550.106 | I19: =H19 -> 26550.106 | J19: =I19 -> 26550.106 | K19: =AVERAGE(J$7:K$7)*Control!J145 -> 23556.77 | L19: =AVERAGE(K$7:L$7)*Control!K145 -> 26129.07 | M19: =AVERAGE(L$7:M$7)*Control!L145 -> 31071.978 | N19: =AVERAGE(M$7:N$7)*Control!M145 -> 36996.268 | O19: =AVERAGE(N$7:O$7)*Control!N145 -> 44102.543
D20: % of V.C | F20: =F19/AVERAGE(E$7:F$7) -> 0.013160924 | G20: =G19/AVERAGE(F$7:G$7) -> 0.010995091 | H20: =H19/AVERAGE(G$7,H$7*2) -> 0.018722041 | I20: =I19/AVERAGE(G$7,I$7*2) -> 0.018722041 | J20: =J19/AVERAGE(G$7,J$7) -> 0.018722041 | K20: =K19/AVERAGE(J$7:K$7) -> 0.014292685 | L20: =L19/AVERAGE(K$7:L$7) -> 0.014292685 | M20: =M19/AVERAGE(L$7:M$7) -> 0.014292685 | N20: =N19/AVERAGE(M$7:N$7) -> 0.014292685 | O20: =O19/AVERAGE(N$7:O$7) -> 0.014292685
B21: NWC | E21: =E9-E16 -> 118586.99 | F21: =F9-F16 -> 141159.17 | G21: =G9-G16 -> 149672.9 | H21: =H9-H16 -> 143000.15 | I21: =I9-I16 -> 143000.15 | J21: =I21 -> 143000.15 | K21: =K9-K16 -> 213631.98 | L21: =L9-L16 -> 236444.92 | M21: =M9-M16 -> 281148.76 | N21: =N9-N16 -> 334726.55 | O21: =O9-O16 -> 398992.35
C22: △NWC | F22: =F21-E21 -> 22572.179 | G22: =G21-F21 -> 8513.7289 | H22: =H21-G21 -> -6672.7502 | I22: =I21-H21 -> 0 | J22: =J21-G21 -> -6672.7502 | K22: =K21-J21 -> 70631.837 | L22: =L21-K21 -> 22812.933 | M22: =M21-L21 -> 44703.84 | N22: =N21-M21 -> 53577.796 | O22: =O21-N21 -> 64265.799
C23: DSO | F23: =F11*365 -> 1.5291465 | G23: =G11*365 -> 1.3576399 | H23: =H11*365 -> 1.8482991 | I23: =I11*365 -> 1.8482991 | J23: =J11*365 -> 1.8482991 | K23: =K11*365 -> 1.5783618 | L23: =L11*365 -> 1.5783618 | M23: =M11*365 -> 1.5783618 | ... O23: =O11*365 -> 1.5783618
C24: DIO | F24: =F13*365 -> 63.941579 | G24: =G13*365 -> 52.965093 | H24: =H13*365 -> 44.190708 | I24: =I13*365 -> 44.190708 | J24: =J13*365 -> 44.190708 | K24: =K13*365 -> 53.699127 | L24: =L13*365 -> 53.699127 | M24: =M13*365 -> 53.699127 | ... O24: =O13*365 -> 53.699127
C25: DPO | F25: =F18*365 -> 1.7526284 | G25: =G18*365 -> 1.9469222 | H25: =H18*365 -> 2.3158061 | I25: =I18*365 -> 2.3158061 | J25: =J18*365 -> 2.3158061 | K25: =K18*365 -> 2.0051189 | L25: =L18*365 -> 2.0051189 | M25: =M18*365 -> 2.0051189 | ... O25: =O18*365 -> 2.0051189

Sheet BS
B1: Balance Sheet | E1: Index
B3: KRW in millions | E3: 2018 | F3: 2019 | G3: 2020 | H3: 2021.1H | J3: 분류
B4: 자산 | E4: =E5+E13 -> 288457.57 | F4: =F5+F13 -> 320014.73 | G4: =G5+G13 -> 342314.46 | H4: =H5+H13 -> 484945.68
C5: 유동자산 | E5: =SUM(E6:E12) -> 140084.66 | F5: =SUM(F6:F12) -> 168521.64 | G5: =SUM(G6:G12) -> 188905.27 | H5: =SUM(H6:H12) -> 233528.35
D6: 현금및현금성자산 | E6: =IFERROR(Dart_FS!C8/10^6,0) -> 1036.144 | F6: =IFERROR(Dart_FS!D8/10^6,0) -> 6804.7642 | G6: =IFERROR(Dart_FS!E8/10^6,0) -> 15534.676 | H6: =IFERROR(Dart_FS!F8/10^6,0) -> 47077.974 | J6: C.E
D7: 매출채권및기타채권 | E7: =IFERROR(Dart_FS!C9/10^6,0) -> 7325.6303 | F7: =IFERROR(Dart_FS!D9/10^6,0) -> 4038.9555 | G7: =IFERROR(Dart_FS!E9/10^6,0) -> 4665.2039 | H7: =IFERROR(Dart_FS!F9/10^6,0) -> 7961.0649 | J7: NWC
D8: 단기금융상품 | E8: =IFERROR(Dart_FS!C10/10^6,0) -> 0 | F8: =IFERROR(Dart_FS!D10/10^6,0) -> 0 | G8: =IFERROR(Dart_FS!E10/10^6,0) -> 0 | H8: =IFERROR(Dart_FS!F10/10^6,0) -> 200
D9: 기타금융자산 | E9: =IFERROR(Dart_FS!C11/10^6,0) -> 3760 | F9: =IFERROR(Dart_FS!D11/10^6,0) -> 4595 | G9: =IFERROR(Dart_FS!E11/10^6,0) -> 4923 | H9: =IFERROR(Dart_FS!F11/10^6,0) -> 7700.197
D10: 기타유동자산 | E10: =IFERROR(Dart_FS!C12/10^6,0) -> 2516.7444 | F10: =IFERROR(Dart_FS!D12/10^6,0) -> 2665.187 | G10: =IFERROR(Dart_FS!E12/10^6,0) -> 2450.4877 | H10: =IFERROR(Dart_FS!F12/10^6,0) -> 4823.8253 | J10: NWC
D11: 재고자산 | E11: =IFERROR(Dart_FS!C13/10^6,0) -> 125377.11 | F11: =IFERROR(Dart_FS!D13/10^6,0) -> 150417.73 | G11: =IFERROR(Dart_FS!E13/10^6,0) -> 161331.91 | H11: =IFERROR(Dart_FS!F13/10^6,0) -> 165762.87 | J11: NWC
D12: 당기법인세자산 | E12: =IFERROR(Dart_FS!C14/10^6,0) -> 69.029726 | F12: =IFERROR(Dart_FS!D14/10^6,0) -> 0 | G12: =IFERROR(Dart_FS!E14/10^6,0) -> 0 | H12: =IFERROR(Dart_FS!F14/10^6,0) -> 2.41217
C13: 비유동자산 | E13: =SUM(E14:E19) -> 148372.91 | F13: =SUM(F14:F19) -> 151493.09 | G13: =SUM(G14:G19) -> 153409.18 | H13: =SUM(H14:H19) -> 251417.33
D14: 장기기타금융자산 | E14: =IFERROR(Dart_FS!C16/10^6,0) -> 10036.382 | F14: =IFERROR(Dart_FS!D16/10^6,0) -> 12493.77 | G14: =IFERROR(Dart_FS!E16/10^6,0) -> 13736.778 | H14: =IFERROR(Dart_FS!F16/10^6,0) -> 16741.147
D15: 유형자산 | E15: =IFERROR(Dart_FS!C17/10^6,0) -> 26826.66 | F15: =IFERROR(Dart_FS!D17/10^6,0) -> 27508.006 | G15: =IFERROR(Dart_FS!E17/10^6,0) -> 26051.592 | H15: =IFERROR(Dart_FS!F17/10^6,0) -> 120299.11
D16: 무형자산 | E16: =IFERROR(Dart_FS!C18/10^6,0) -> 77752.174 | F16: =IFERROR(Dart_FS!D18/10^6,0) -> 77416.232 | G16: =IFERROR(Dart_FS!E18/10^6,0) -> 77691.221 | H16: =IFERROR(Dart_FS!F18/10^6,0) -> 77322.185
D17: 사용권자산 | E17: =IFERROR(Dart_FS!C19/10^6,0) -> 33498.328 | F17: =IFERROR(Dart_FS!D19/10^6,0) -> 34075.08 | G17: =IFERROR(Dart_FS!E19/10^6,0) -> 35929.592 | H17: =IFERROR(Dart_FS!F19/10^6,0) -> 36543.898
D18: 이연법인세자산 | E18: =IFERROR(Dart_FS!C20/10^6,0) -> 259.36943 | F18: =IFERROR(Dart_FS!D20/10^6,0) -> 0 | G18: =IFERROR(Dart_FS!E20/10^6,0) -> 0 | H18: =IFERROR(Dart_FS!F20/10^6,0) -> 0
D19: 기타비유동자산 | E19: =IFERROR(Dart_FS!C21/10^6,0) -> 0 | F19: =IFERROR(Dart_FS!D21/10^6,0) -> 0 | G19: =IFERROR(Dart_FS!E21/10^6,0) -> 0 | H19: =IFERROR(Dart_FS!F21/10^6,0) -> 510.99039
B20: 부채 | E20: =E21+E30 -> 153153.17 | F20: =F21+F30 -> 171646.92 | G20: =G21+G30 -> 171348.58 | H20: =H21+H30 -> 286891.77
C21: 유동부채 | E21: =SUM(E22:E29) -> 27609.104 | F21: =SUM(F22:F29) -> 28586.717 | G21: =SUM(G22:G29) -> 36675.34 | H21: =SUM(H22:H29) -> 228406.42
D22: 매입채무및기타채무 | E22: =IFERROR(Dart_FS!C25/10^6,0) -> 6251.7466 | F22: =IFERROR(Dart_FS!D25/10^6,0) -> 4267.1034 | G22: =IFERROR(Dart_FS!E25/10^6,0) -> 6132.9 | H22: =IFERROR(Dart_FS!F25/10^6,0) -> 8997.5112 | J22: NWC
D23: 기타금융부채 | E23: =IFERROR(Dart_FS!C26/10^6,0) -> 1568 | F23: =IFERROR(Dart_FS!D26/10^6,0) -> 1761 | G23: =IFERROR(Dart_FS!E26/10^6,0) -> 1934 | H23: =IFERROR(Dart_FS!F26/10^6,0) -> 4685.4577
D24: 차입금 | E24: =IFERROR(Dart_FS!C27/10^6,0) -> 0 | F24: =IFERROR(Dart_FS!D27/10^6,0) -> 0 | G24: =IFERROR(Dart_FS!E27/10^6,0) -> 0 | H24: =IFERROR(Dart_FS!F27/10^6,0) -> 137633.75
D25: 기타유동부채 | E25: =IFERROR(Dart_FS!C28/10^6,0) -> 10380.748 | F25: =IFERROR(Dart_FS!D28/10^6,0) -> 11695.602 | G25: =IFERROR(Dart_FS!E28/10^6,0) -> 12641.802 | H25: =IFERROR(Dart_FS!F28/10^6,0) -> 26550.106 | J25: NWC
D26: 리스부채(유동) | E26: =IFERROR(Dart_FS!C29/10^6,0) -> 9408.6093 | F26: =IFERROR(Dart_FS!D29/10^6,0) -> 10457.591 | G26: =IFERROR(Dart_FS!E29/10^6,0) -> 12180.235 | H26: =IFERROR(Dart_FS!F29/10^6,0) -> 13467.469 | J26: IBD
D27: 당기법인세부채 | E27: =IFERROR(Dart_FS!C30/10^6,0) -> 0 | F27: =IFERROR(Dart_FS!D30/10^6,0) -> 405.42044 | G27: =IFERROR(Dart_FS!E30/10^6,0) -> 3786.4031 | H27: =IFERROR(Dart_FS!F30/10^6,0) -> 8663.4516
D28: 전환사채 | E28: =IFERROR(Dart_FS!C31/10^6,0) -> 0 | F28: =IFERROR(Dart_FS!D31/10^6,0) -> 0 | G28: =IFERROR(Dart_FS!E31/10^6,0) -> 0 | H28: =IFERROR(Dart_FS!F31/10^6,0) -> 28390.307 | J28: IBD
D29: 파생상품부채 | E29: =IFERROR(Dart_FS!C32/10^6,0) -> 0 | F29: =IFERROR(Dart_FS!D32/10^6,0) -> 0 | G29: =IFERROR(Dart_FS!E32/10^6,0) -> 0 | H29: =IFERROR(Dart_FS!F32/10^6,0) -> 18.370811
C30: 비유동부채 | E30: =SUM(E31:E37) -> 125544.07 | F30: =SUM(F31:F37) -> 143060.2 | G30: =SUM(G31:G37) -> 134673.24 | H30: =SUM(H31:H37) -> 58485.346
D31: 장기차입금 | E31: =IFERROR(Dart_FS!C34/10^6,0) -> 97444.276 | F31: =IFERROR(Dart_FS!D34/10^6,0) -> 111763.08 | G31: =IFERROR(Dart_FS!E34/10^6,0) -> 99279.188 | H31: =IFERROR(Dart_FS!F34/10^6,0) -> 16577.778 | J31: IBD
D32: 기타비유동부채 | E32: =IFERROR(Dart_FS!C35/10^6,0) -> 801.995 | F32: =IFERROR(Dart_FS!D35/10^6,0) -> 1246.317 | G32: =IFERROR(Dart_FS!E35/10^6,0) -> 1118.7488 | H32: =IFERROR(Dart_FS!F35/10^6,0) -> 1544.1063
D33: 장기기타금융부채 | E33: =IFERROR(Dart_FS!C36/10^6,0) -> 31.8 | F33: =IFERROR(Dart_FS!D36/10^6,0) -> 30 | G33: =IFERROR(Dart_FS!E36/10^6,0) -> 30 | H33: =IFERROR(Dart_FS!F36/10^6,0) -> 2746.5881
D34: 리스부채(비유동) | E34: =IFERROR(Dart_FS!C37/10^6,0) -> 24358.533 | F34: =IFERROR(Dart_FS!D37/10^6,0) -> 24556.895 | G34: =IFERROR(Dart_FS!E37/10^6,0) -> 25229.612 | H34: =IFERROR(Dart_FS!F37/10^6,0) -> 25248.727 | J34: IBD
D35: 순확정급여채무 | E35: =IFERROR(Dart_FS!C38/10^6,0) -> 2907.4662 | F35: =IFERROR(Dart_FS!D38/10^6,0) -> 2169.7182 | G35: =IFERROR(Dart_FS!E38/10^6,0) -> 3280.26 | H35: =IFERROR(Dart_FS!F38/10^6,0) -> 6604.9652
D36: 이연법인세부채 | E36: =IFERROR(Dart_FS!C39/10^6,0) -> 0 | F36: =IFERROR(Dart_FS!D39/10^6,0) -> 3294.1887 | G36: =IFERROR(Dart_FS!E39/10^6,0) -> 5735.4273 | H36: =IFERROR(Dart_FS!F39/10^6,0) -> 5719.7851
D37: 비유동파생상품부채 | E37: =IFERROR(Dart_FS!C40/10^6,0) -> 0 | F37: =IFERROR(Dart_FS!D40/10^6,0) -> 0 | G37: =IFERROR(Dart_FS!E40/10^6,0) -> 0 | H37: =IFERROR(Dart_FS!F40/10^6,0) -> 43.396728
B38: 자본 | E38: =SUM(E39:E42) -> 135304.4 | F38: =SUM(F39:F42) -> 148367.81 | G38: =SUM(G39:G42) -> 170965.88 | H38: =SUM(H39:H42) -> 198053.91
C39: 자본금 | E39: =IFERROR(Dart_FS!C43/10^6,0) -> 6675.5 | F39: =IFERROR(Dart_FS!D43/10^6,0) -> 6675.5 | G39: =IFERROR(Dart_FS!E43/10^6,0) -> 6675.5 | H39: =IFERROR(Dart_FS!F43/10^6,0) -> 23442.184
C40: 기타불입자본 | E40: =IFERROR(Dart_FS!C44/10^6,0) -> 126738.38 | F40: =IFERROR(Dart_FS!D44/10^6,0) -> 126738.38 | G40: =IFERROR(Dart_FS!E44/10^6,0) -> 26738.38 | H40: =IFERROR(Dart_FS!F44/10^6,0) -> 44181.24
C41: 자본조정 | E41: =IFERROR(Dart_FS!C45/10^6,0) -> 0 | F41: =IFERROR(Dart_FS!D45/10^6,0) -> 0 | G41: =IFERROR(Dart_FS!E45/10^6,0) -> 0 | H41: =IFERROR(Dart_FS!F45/10^6,0) -> 2311.3204
C42: 이익잉여금 | E42: =IFERROR(Dart_FS!C46/10^6,0) -> 1890.5177 | F42: =IFERROR(Dart_FS!D46/10^6,0) -> 14953.929 | G42: =IFERROR(Dart_FS!E46/10^6,0) -> 137552 | H42: =IFERROR(Dart_FS!F46/10^6,0) -> 128119.17

Sheet Dart>>

Sheet Dart_시장리서치
B1: Dart_시장리서치 | C1: Index
B3: 연도별 중고차 매매업체수
B4: (단위: 개, 명)
B5: 구분 | C5: 2016 | D5: 2017 | E5: 2018 | F5: 2019 | G5: 2020 | H5: CAGR
B6: 중고차거래대수(천대) | C6: 2558 | D6: 2565 | E6: 2570 | F6: 2497 | G6: 2670 | H6: 0.011
B7: 매매업체수(개) | C7: 5127 | D7: 5734 | E7: 5811 | F7: 5964 | G7: 6213 | H7: 0.049
B9: 국내 채널별 국내 중고차 거래 규모 현황 및 전망
B10: (단위 : 천대)
B11: 구매 방식 | C11: 2015 | D11: 2016 | E11: 2017 | F11: 2018 | G11: 2019 | H11: 2020E | I11: 2021F | J11: 2022F | K11: 2023F | L11: 2024F | M11: 2025F
B12: Total Used Car Market | C12: 2530 | D12: 2558 | E12: 2565 | F12: 2570 | G12: 2497 | H12: 2670 | I12: 2795 | J12: 2871 | K12: 2914 | L12: 2930 | M12: 2959
B13: Online Market Size | C13: 4 | D13: 6 | E13: 13 | F13: 17 | G13: 24 | H13: 40 | I13: 67 | J13: 106 | K13: 154 | L13: 210 | M13: 266
B14: % of Online Market | C14: 0 | D14: 0 | E14: 0 | F14: 0.01 | G14: 0.01 | H14: 0.02 | I14: 0.02 | J14: 0.04 | K14: 0.05 | L14: 0.07 | M14: 0.09
B15: Offline Market Size | C15: 2526 | D15: 2552 | E15: 2553 | F15: 2554 | G15: 2473 | H15: 2629 | I15: 2728 | J15: 2765 | K15: 2760 | L15: 2719 | M15: 2693
B16: % of Offline Market | C16: 1 | D16: 1 | E16: 1 | F16: 0.99 | G16: 0.99 | H16: 0.98 | I16: 0.98 | J16: 0.96 | K16: 0.95 | L16: 0.93 | M16: 0.91
B18: 국토교통부 자동차등록통계 중 이전등록현황
B19: (단위 : 대)
B20: 구분 | C20: 2018 | D20: 2019 | E20: 2020 | F20: 2021.1H
B21: 합계 | C21: 3770107 | D21: 3695171 | E21: 3952820 | F21: 2019139
B22: 업자매매 | C22: 2335818 | D22: 2314853 | E22: 2489470 | F22: 1303961
B23: 당사자매매 | C23: 1357753 | D23: 1299280 | E23: 1384834 | F23: 679061
B24: 증여 | C24: 3997 | D24: 5938 | E24: 6267 | F24: 2607
B25: 상속 | C25: 51835 | D25: 51718 | E25: 51234 | F25: 25872
B26: 촉탁 | C26: 14727 | D26: 15982 | E26: 14842 | F26: 5085
B27: 기타 | C27: 5977 | D27: 7400 | E27: 6173 | F27: 2553
B29: 국내 중고차 시장 연도별 거래대수 현황 및 전망
B30: (단위 : 천대)
B31: 구분 | C31: 2015 | D31: 2016 | E31: 2017 | F31: 2018 | G31: 2019 | H31: 2020E | I31: 2021F | J31: 2022F | K31: 2023F | L31: 2024F | M31: 2025F
B32: 중고차 시장 합계 | C32: 2530 | D32: 2558 | E32: 2565 | F32: 2570 | G32: 2497 | H32: 2670 | I32: 2795 | J32: 2871 | K32: 2914 | L32: 2930 | M32: 2959
B33: 매매업자 거래 (B2C) | C33: 998 | D33: 1035 | E33: 1017 | F33: 1039 | G33: 1045 | H33: 1107 | I33: 1136 | J33: 1167 | K33: 1199 | L33: 1233 | M33: 1269
B34: 개인간 거래 (C2C) | C34: 1393 | D34: 1369 | E34: 1384 | F34: 1352 | G34: 1294 | H34: 1376 | I34: 1390 | J34: 1403 | K34: 1417 | L34: 1432 | M34: 1446
B35: 매매업자간 거래 (B2B) | C35: 138 | D35: 153 | E35: 163 | F35: 179 | G35: 157 | H35: 187 | I35: 269 | J35: 301 | K35: 298 | L35: 265 | M35: 244
B37: 케이카 점유율 산출(판매대수 기준)
B38: (단위 : 대)
C39: 2015 | D39: 2016 | E39: 2017 | F39: 2018 | G39: 2019 | H39: 2020E | I39: 2021F | J39: 2022F | K39: 2023F | L39: 2024F | M39: 2025F
B40: 온라인 판매대수 | C40: =C13*1000 -> 4000 | D40: =D13*1000 -> 6000 | E40: =E13*1000 -> 13000 | F40: =F13*1000 -> 17000 | G40: =G13*1000 -> 24000 | H40: =H13*1000 -> 40000 | I40: =I13*1000 -> 67000 | J40: =J13*1000 -> 106000 | ... M40: =M13*1000 -> 266000
B41: 온라인 시장성장률 | D41: =D40/C40-1 -> 0.5 | E41: =E40/D40-1 -> 1.1666667 | F41: =F40/E40-1 -> 0.30769231 | G41: =G40/F40-1 -> 0.41176471 | H41: =H40/G40-1 -> 0.66666667 | I41: =I40/H40-1 -> 0.675 | J41: =J40/I40-1 -> 0.58208955 | K41: =K40/J40-1 -> 0.45283019 | ... M41: =M40/L40-1 -> 0.26666667
B42: 케이카 이커머스 판매대수 | F42: ='Dart_중고차 Sales'!J13 -> 12700 | G42: ='Dart_중고차 Sales'!K13 -> 22554 | H42: ='Dart_중고차 Sales'!L13 -> 31274 | I42: ='Dart_중고차 Sales'!M13*2 -> 45840
B43: 이커머스 판매 점유율 | F43: =F42/F40 -> 0.74705882 | G43: =G42/G40 -> 0.93975 | H43: =H42/H40 -> 0.78185 | I43: =I42/I40 -> 0.6841791
C44: 2015 | D44: 2016 | E44: 2017 | F44: 2018 | G44: 2019 | H44: 2020E | I44: 2021F | J44: 2022F | K44: 2023F | L44: 2024F | M44: 2025F
B45: 오프라인 판매대수 | C45: =C15*1000 -> 2526000 | D45: =D15*1000 -> 2552000 | E45: =E15*1000 -> 2553000 | F45: =F15*1000 -> 2554000 | G45: =G15*1000 -> 2473000 | H45: =H15*1000 -> 2629000 | I45: =I15*1000 -> 2728000 | J45: =J15*1000 -> 2765000 | ... M45: =M15*1000 -> 2693000
B46: 오프라인 시장성장률 | D46: =D45/C45-1 -> 0.010292953 | E46: =E45/D45-1 -> 0.00039184953 | F46: =F45/E45-1 -> 0.00039169604 | G46: =G45/F45-1 -> -0.031714957 | H46: =H45/G45-1 -> 0.063081278 | I46: =I45/H45-1 -> 0.037656904 | J46: =J45/I45-1 -> 0.01356305 | K46: =K45/J45-1 -> -0.0018083183 | ... M46: =M45/L45-1 -> -0.0095623391
B47: 케이카 오프라인 판매대수 | F47: ='Dart_중고차 Sales'!J14 -> 39496 | G47: ='Dart_중고차 Sales'!K14 -> 61774 | H47: ='Dart_중고차 Sales'!L14 -> 58875 | I47: ='Dart_중고차 Sales'!M14*2 -> 63012
B48: 오프라인 판매 점유율 | F48: =F47/F45 -> 0.01546437 | G48: =G47/G45 -> 0.024979377 | H48: =H47/H45 -> 0.022394447 | I48: =I47/I45 -> 0.02309824

Sheet Dart_FS
B1: Dart_FS | C1: Index
B3: 재무상태표
B4: (단위 : 원)
B5: 과 목 | C5: 2018년 | D5: 2019년 | E5: 2020년 | F5: 2021년 반기
B6: 자 산
B7: Ⅰ. 유동자산 | C7: 140084658730 | D7: 168521638299 | E7: 188905274888 | F7: 233528347875
B8: 현금및현금성자산 | C8: 1036143978 | D8: 6804764155 | E8: 15534675923 | F8: 47077973883
B9: 매출채권및기타채권 | C9: 7325630278 | D9: 4038955476 | E9: 4665203909 | F9: 7961064921
B10: 단기금융상품 | C10: - | D10: - | E10: - | F10: 200000000
B11: 기타금융자산 | C11: 3760000000 | D11: 4595000000 | E11: 4923000000 | F11: 7700197000
B12: 기타유동자산 | C12: 2516744386 | D12: 2665187034 | E12: 2450487684 | F12: 4823825309
B13: 재고자산 | C13: 125377110362 | D13: 150417731634 | E13: 161331907372 | F13: 165762874592
B14: 당기법인세자산 | C14: 69029726 | D14: - | E14: - | F14: 2412170
B15: Ⅱ. 비유동자산 | C15: 148372913364 | D15: 151493088083 | E15: 153409183704 | F15: 251417333240
B16: 장기기타금융자산 | C16: 10036381890 | D16: 12493769764 | E16: 13736777638 | F16: 16741147248
B17: 유형자산 | C17: 26826660048 | D17: 27508006286 | E17: 26051592431 | F17: 120299112751
B18: 무형자산 | C18: 77752174341 | D18: 77416231660 | E18: 77691221374 | F18: 77322184699
B19: 사용권자산 | C19: 33498327654 | D19: 34075080373 | E19: 35929592261 | F19: 36543898147
B20: 이연법인세자산 | C20: 259369431 | D20: - | E20: - | F20: -
B21: 기타비유동자산 | C21: - | D21: - | E21: - | F21: 510990395
B22: 자 산 총 계 | C22: 288457572094 | D22: 320014726382 | E22: 342314458592 | F22: 484945681115
B23: 부 채
B24: Ⅰ. 유동부채 | C24: 27609104323 | D24: 28586717019 | E24: 36675340005 | F24: 228406421239
B25: 매입채무및기타채무 | C25: 6251746598 | D25: 4267103424 | E25: 6132899971 | F25: 8997511157
B26: 기타금융부채 | C26: 1568000000 | D26: 1761000000 | E26: 1934000000 | F26: 4685457675
B27: 차입금 | C27: - | D27: - | E27: - | F27: 137633747269
B28: 기타유동부채 | C28: 10380748473 | D28: 11695602179 | E28: 12641801550 | F28: 26550106376
B29: 리스부채(유동) | C29: 9408609252 | D29: 10457590971 | E29: 12180235358 | F29: 13467469351
B30: 당기법인세부채 | C30: - | D30: 405420445 | E30: 3786403126 | F30: 8663451559
B31: 전환사채 | C31: - | D31: - | E31: - | F31: 28390307041
B32: 파생상품부채 | C32: - | D32: - | E32: - | F32: 18370811
B33: Ⅱ. 비유동부채 | C33: 125544070061 | D33: 143060200127 | E33: 134673235633 | F33: 58485346040
B34: 장기차입금 | C34: 97444275815 | D34: 111763081349 | E34: 99279187934 | F34: 16577777781
B35: 기타비유동부채 | C35: 801994999 | D35: 1246317029 | E35: 1118748764 | F35: 1544106287
B36: 장기기타금융부채 | C36: 31800000 | D36: 30000000 | E36: 30000000 | F36: 2746588076
B37: 리스부채(비유동) | C37: 24358533072 | D37: 24556894777 | E37: 25229611690 | F37: 25248726908
B38: 순확정급여채무 | C38: 2907466175 | D38: 2169718232 | E38: 3280259963 | F38: 6604965172
B39: 이연법인세부채 | C39: - | D39: 3294188740 | E39: 5735427282 | F39: 5719785088
B40: 비유동파생상품부채 | C40: - | D40: - | E40: - | F40: 43396728
B41: 부 채 총 계 | C41: 153153174384 | D41: 171646917146 | E41: 171348575638 | F41: 286891767279
B42: 자 본
B43: Ⅰ. 자본금 | C43: 6675500000 | D43: 6675500000 | E43: 6675500000 | F43: 23442184500
B44: Ⅱ. 기타불입자본 | C44: 126738380000 | D44: 126738380000 | E44: 26738380000 | F44: 44181239746
B45: Ⅲ. 자본조정 | C45: - | D45: - | E45: - | F45: 2311320356
B46: Ⅳ. 이익잉여금 | C46: 1890517710 | D46: 14953929236 | E46: 137552002954 | F46: 128119169234
B47: 자 본 총 계 | C47: 135304397710 | D47: 148367809236 | E47: 170965882954 | F47: 198053913836
B48: 부 채 및 자 본 총 계 | C48: 288457572094 | D48: 320014726382 | E48: 342314458592 | F48: 484945681115
B50: 손익계산서
B51: (단위 : 원)
B52: 과 목 | C52: 2018년(제2기) | D52: 2019년 | E52: 2020년 | F52: 2021년 반기
B53: Ⅰ. 매출액 | C53: 742803120095 | D53: 1185355254882 | E53: 1323113771001 | F53: 910583602776
B54: Ⅱ. 매출원가 | C54: 670019632815 | D54: 1062154024596 | E54: 1179322430915 | F54: 808030708362
B55: Ⅲ. 매출총이익 | C55: 72783487280 | D55: 123201230286 | E55: 143791340086 | F55: 102552894414
B56: Ⅳ. 판매비와관리비 | C56: 62117629223 | D56: 93996787696 | E56: 106092958002 | F56: 64075316250
B57: Ⅴ. 영업이익 | C57: 10665858057 | D57: 29204442590 | E57: 37698382084 | F57: 38477578164
B58: 기타영업외수익 | C58: 67576328 | D58: 227259758 | E58: 90981213 | F58: 1454843428
B59: 기타영업외비용 | C59: 2281645197 | D59: 945627210 | E59: 324463557 | F59: 270017590
B60: 금융이익 | C60: 428719373 | D60: 447776360 | E60: 494176433 | F60: 166286309
B61: 금융원가 | C61: 5395129662 | D61: 9657986740 | E61: 6973677086 | F61: 4217389038
B62: Ⅵ. 법인세비용차감전순이익 | C62: 3485378899 | D62: 19275864758 | E62: 30985399087 | F62: 35611301273
B63: Ⅶ. 법인세비용 | C63: 800985218 | D63: 4498080007 | E63: 6855748975 | F63: 9067442910
B64: Ⅷ. 당기순이익 | C64: 2684393681 | D64: 14777784751 | E64: 24129650112 | F64: 26543858363
... B68: Ⅹ. 총포괄이익 | C68: 1890517683 | D68: 13063411526 | E68: 22598073718 | F68: 25279766280
B69: XI. 주당이익
B70: 기본주당이익 | C70: 255 | D70: 1107 | E70: 1807 | F70: 581
B71: 희석주당이익 | C71: 255 | D71: 1107 | E71: 1807 | F71: 581
B73: 현금흐름표
B74: (단위 : 원)
B75: 과 목 | C75: 2018년 | D75: 2019년 | E75: 2020년 | F75: 2021년 반기
B76: Ⅰ.영업활동으로 인한 현금흐름 | C76: -6292014452 | D76: 6365303157 | E76: 33469617211 | F76: 44920482945
B77: 1. 영업활동에서 창출된 현금 | C77: -1097756709 | D77: 13494809717 | E77: 40366044125 | F77: 52809639815
B78: (1) 당기순이익 | C78: 2684393681 | D78: 14777784751 | E78: 24129650112 | F78: 26543858363
B79: (2) 조정 | C79: 15394472653 | D79: 30869133853 | E79: 32732273101 | F79: 34872897364
B80: 법인세비용 | C80: 800985218 | D80: 4498080007 | E80: 6855748975 | F80: 9067442910
B81: 퇴직급여 | C81: 1849143724 | D81: 3078173160 | E81: 3411759510 | F81: 2089494521
B82: 감가상각비 | C82: 6680633571 | D82: 12256755057 | E82: 14214472395 | F82: 18802027766 | I82: -12460955
B83: 복리후생비 | C83: 0 | D83: 0 | E83: 0 | F83: 0 | I83: -6341073
B84: 무형자산상각비 | C84: 751743523 | D84: 1280700931 | E84: 1659499373 | F84: 922288070
B85: 대손상각비 | C85: 0 | D85: 1500000 | E85: 6400000 | F85: 475670
B86: 대손충당금환입 | C86: 0 | D86: 0 | E86: 0 | F86: -5114158
B87: 기타의대손상각비 | C87: 15100000 | D87: 112893280 | E87: 105764158 | F87: 4504263
B88: 재고자산평가손실 | C88: 0 | D88: 0 | E88: 0 | F88: 105503647
B89: 재고자산감모손실 | C89: 0 | D89: 18117273 | E89: 13491374 | F89: 7491364
B90: 이자비용 | C90: 5395129662 | D90: 9657986740 | E90: 6973677086 | F90: 4217389038
B91: 유형자산처분손실 | C91: 252122236 | D91: 501830910 | E91: 133991890 | F91: 207881573
B92: 이자수익 | C92: 428719373 | D92: -447776360 | E92: -494176433 | F92: -166286309
B93: 재고자산평가손실환입 | C93: 95869474 | D93: -77374663 | E93: -106810501 | F93: -54017484
B94: 유형자산처분이익 | C94: 17535382 | D94: -11752482 | E94: -41544726 | F94: -7854245
B95: 리스회수이익 | C95: - | D95: - | E95: - | F95: -1215650925
B96: 리스회수손실 | C96: - | D96: - | E96: - | F96: 2678765
B97: 파생상품평가이익 | C97: - | D97: - | E97: - | F97: -80831577
B98: 주식보상비용 | C98: - | D98: - | E98: - | F98: 975474475
B99: (3) 운전자본변동 | C99: -19176623043 | D99: -32152108887 | E99: -16495879088 | F99: -8607115912
B100: 매출채권 | C100: -1944505577 | D100: -428911779 | E100: -1446151509 | F100: -123705468
B101: 단기금융상품 | C101: - | D101: - | E101: - | F101: -200000000
B102: 미수금 | C102: -884896088 | D102: -104868617 | E102: 707738918 | F102: 225825087
B103: 선급금 | C103: 2783977522 | D103: -1084166860 | E103: 597799364 | F103: -662520103
B104: 선급비용 | C104: -102893857 | D104: -188657804 | E104: -122416017 | F104: -901766076
B105: 상품 | C105: -19916360343 | D105: -24975187028 | E105: -11000299691 | F105: 1749801031
B106: 저장품 | C106: -200418726 | D106: -6176854 | E106: 179443080 | F106: -196089000
...

Sheet Dart_Labor
B1: Dart_Labor | D1: Index
B3: (단위 : 명, 천원) << 2021년 1월~7월
B4: 직 원 | L4: 소속외 근로자 | O4: 비고
B5: 사업부문 | C5: 성별 | D5: 직원수 | I5: 평균 | J5: 연간급여 | K5: 1인평균 | L5: 남 | M5: 여 | N5: 계
D6: 기간의 정함이 | F6: 기간제 | H6: 합계 | I6: 근속연수 | J6: 총액 | K6: 급여액
D7: 없는 근로자 | F7: 근로자
D8: 전체 | E8: 단시간 | F8: 전체 | G8: 단시간
E9: 근로자 | G9: 근로자 | Q9: 보정액 | S9: 보정결과
B10: 중고차 | C10: 남 | D10: 782 | E10: 0 | F10: 2 | G10: 0 | H10: 784 | I10: 5.5 | J10: 24338802 | K10: 31,044 | L10: 6 | M10: 0 | N10: 6 | O10: - | Q10: =$J$26*J10/$J$22 -> -156725.15 | S10: =J10*(6/7)+Q10 -> 20705105
C11: 여 | D11: 71 | E11: 0 | F11: 1 | G11: 0 | H11: 72 | I11: 5.4 | J11: 1556949 | K11: 21,624 | L11: 0 | M11: 25 | N11: 25 | O11: - | Q11: =$J$26*J11/$J$22 -> -10025.681 | S11: =J11*(6/7)+Q11 -> 1324502
B12: 경매 | C12: 남 | D12: 18 | E12: 0 | F12: 1 | G12: 0 | H12: 19 | I12: 6.4 | J12: 787935 | K12: 41,470 | L12: 0 | M12: 0 | N12: 0 | O12: - | Q12: =$J$26*J12/$J$22 -> -5073.7596 | S12: =J12*(6/7)+Q12 -> 670299.1
C13: 여 | D13: 2 | E13: 0 | F13: 0 | G13: 0 | H13: 2 | I13: 4 | J13: 53504 | K13: 26,752 | L13: 0 | M13: 8 | N13: 8 | O13: - | Q13: =$J$26*J13/$J$22 -> -344.52897 | S13: =J13*(6/7)+Q13 -> 45516.042
B14: 렌탈 | C14: 남 | D14: 25 | E14: 0 | F14: 0 | G14: 0 | H14: 25 | I14: 4 | J14: 1059328 | K14: 42,373 | L14: 0 | M14: 0 | N14: 0 | O14: - | Q14: =$J$26*J14/$J$22 -> -6821.3439 | S14: =J14*(6/7)+Q14 -> 901174.08
C15: 여 | D15: 9 | E15: 0 | F15: 0 | G15: 0 | H15: 9 | I15: 1.6 | J15: 353994 | K15: 39,333 | L15: 0 | M15: 1 | N15: 1 | O15: - | Q15: =$J$26*J15/$J$22 -> -2279.4779 | S15: =J15*(6/7)+Q15 -> 301143.95
B16: 마케팅 | C16: 남 | D16: 15 | E16: 0 | F16: 0 | G16: 0 | H16: 15 | I16: 6.7 | J16: 559744 | K16: 37,316 | L16: 10 | M16: 0 | N16: 10 | O16: - | Q16: =$J$26*J16/$J$22 -> -3604.3665 | S16: =J16*(6/7)+Q16 -> 476176.2
C17: 여 | D17: 12 | E17: 0 | F17: 0 | G17: 0 | H17: 12 | I17: 5.2 | J17: 364331 | K17: 30,361 | L17: 0 | M17: 43 | N17: 43 | O17: - | Q17: =$J$26*J17/$J$22 -> -2346.0411 | S17: =J17*(6/7)+Q17 -> 309937.67
B18: IT | C18: 남 | D18: 15 | E18: 0 | F18: 0 | G18: 0 | H18: 15 | I18: 6.4 | J18: 612930 | K18: 40,862 | L18: 8 | M18: 0 | N18: 8 | O18: - | Q18: =$J$26*J18/$J$22 -> -3946.8477 | S18: =J18*(6/7)+Q18 -> 521421.72
C19: 여 | D19: 5 | E19: 0 | F19: 0 | G19: 0 | H19: 5 | I19: 4.4 | J19: 119798 | K19: 23,960 | L19: 0 | M19: 1 | N19: 1 | O19: - | Q19: =$J$26*J19/$J$22 -> -771.41675 | S19: =J19*(6/7)+Q19 -> 101912.58
B20: 사무 | C20: 남 | D20: 49 | E20: 0 | F20: 0 | G20: 0 | H20: 49 | I20: 7.4 | J20: 2174820 | K20: 44,384 | L20: 1 | M20: 0 | N20: 1 | O20: - | Q20: =$J$26*J20/$J$22 -> -14004.345 | S20: =J20*(6/7)+Q20 -> 1850127.1
C21: 여 | D21: 18 | E21: 0 | F21: 2 | G21: 0 | H21: 20 | I21: 5.5 | J21: 623964 | K21: 31,198 | L21: 0 | M21: 1 | N21: 1 | O21: - | Q21: =$J$26*J21/$J$22 -> -4017.8991 | S21: =J21*(6/7)+Q21 -> 530808.39
B22: 합 계 | D22: 1021 | E22: 0 | F22: 6 | G22: 0 | H22: 1027 | I22: 5.6 | J22: 32606099 | K22: 31,749 | L22: 25 | M22: 79 | N22: 104 | O22: - | Q22: =SUM(Q10:Q21) -> -209960.86 | S22: =SUM(S10:S21) -> 27738124
S23: =S22=J25 -> TRUE
H24: 반기기준 | J24: =J22*6/7 -> 27948085
H25: To be 손익계산서 종업원 급여 | J25: =Dart_Cost!F33 -> 27738124
H26: 보정액 | J26: =J25-J24 -> -209960.86

Sheet Dart_Cost
B1: Dart_Cost | C1: Index
B3: 비용의 성격별 분류
B4: (단위 : 천원)
B5: 구 분 | C5: 2018 | D5: 2019 | E5: 2020 | F5: 2021.1H
B6: 재고자산의 변동 | C6: 663748170 | D6: -25034444 | E6: -11093619 | F6: -4234879
B7: 상품의 매입액 | C7: 0 | D7: 1078556109 | E7: 1181155177 | F7: 788348233
B8: 종업원급여 | C8: 27995015 | D8: 44042751 | E8: 49239872 | F8: 29933465
B9: 복리후생비 | C9: 2999708 | D9: 4883806 | E9: 4791542 | F9: 3111239
B10: 접대비 | C10: 811035 | D10: 1648621 | E10: 1293548 | F10: 721307
B11: 여비교통비 | C11: 298819 | D11: 406295 | E11: 306753 | F11: 182523
B12: 세금과공과 | C12: 1802771 | D12: 3765010 | E12: 5220383 | F12: 2969282
B13: 대손상각비 | C13: 0 | D13: 1500 | E13: 6400 | F13: 0
B14: 감가상각비 | C14: 6680634 | D14: 12256755 | E14: 14214472 | F14: 18802028
B15: 지급임차료 | C15: 1677407 | D15: 1566864 | E15: 1861070 | F15: 1190181
B16: 보험료 | C16: 235401 | D16: 341832 | E16: 349413 | F16: 1572558
B17: 차량유지비 | C17: 855248 | D17: 1037155 | E17: 1140067 | F17: 771644
... B27: 기타비용 | C27: 11694027 | D27: 15664953 | E27: 18805050 | F27: 9504955
B28: 합 계 | C28: 732137262 | D28: 1156150812 | E28: 1285415389 | F28: =SUM(F6:F27) -> 872106025
B30: 판매비와 관리비
B31: (단위 : 천원) | C31: =C33+C34 -> 27995015 | D31: =D33+D34 -> 44042751 | E31: =E33+E34 -> 49239872 | F31: =F33+F34 -> 29933465
B32: 구 분 | C32: 2018 | D32: 2019 | E32: 2020 | F32: 2021.1H
B33: 급여 | C33: 25858310 | D33: 40917289 | E33: 44758009 | F33: 27738124
B34: 퇴직급여 | C34: 2136705 | D34: 3125462 | E34: 4481863 | F34: 2195341
B35: 복리후생비 | C35: 2999708 | D35: 4883806 | E35: 4791542 | F35: 3111239
B36: 접대비 | C36: 811035 | D36: 1648621 | E36: 1293548 | F36: 721307
B37: 여비교통비 | C37: 298819 | D37: 406295 | E37: 306753 | F37: 182523
B38: 광고선전비 | C38: 0 | D38: 8052969 | E38: 9631908 | F38: 5712917
B39: 기타비용 | C39: 11682769 | D39: 4654289 | E39: 4749332 | F39: 2842150
B40: 대손상각비 | C40: 0 | D40: 1500 | E40: 6400 | F40: 0
B41: 세금과공과 | C41: 1802771 | D41: 3765010 | E41: 5220383 | F41: 2884288
B42: 감가상각비 | C42: 6570271 | D42: 12256754 | E42: 14214472 | F42: 7802166
B43: 지급임차료 | C43: 1677407 | D43: 1566864 | E43: 1861070 | F43: 1190181
B44: 보험료 | C44: 204676 | D44: 341832 | E44: 349413 | F44: 202866
... B51: 합 계 | C51: 62117629 | D51: 93996788 | E51: 106092958 | F51: 64075316
B53: 판매비와 관리비(성격별 분류)
B54: (단위 : 천원)
B55: 구 분 | C55: 2018 | D55: 2019 | E55: 2020 | F55: 2021.1H
B56: 재고자산의 변동 | C56: 0 | D56: 0 | E56: 0 | F56: 0
B57: 상품의 매입액 | C57: 0 | D57: 0 | E57: 0 | F57: 0
B58: 종업원급여 | C58: =C33+C34 -> 27995015 | D58: =D33+D34 -> 44042751 | E58: =E33+E34 -> 49239872 | F58: =F33+F34 -> 29933465
B59: 복리후생비 | C59: =C35 -> 2999708 | D59: =D35 -> 4883806 | E59: =E35 -> 4791542 | F59: =F35 -> 3111239
B60: 접대비 | C60: =C36 -> 811035 | D60: =D36 -> 1648621 | E60: =E36 -> 1293548 | F60: =F36 -> 721307
B61: 여비교통비 | C61: =C37 -> 298819 | D61: =D37 -> 406295 | E61: =E37 -> 306753 | F61: =F37 -> 182523
B62: 세금과공과 | C62: =C41 -> 1802771 | D62: =D41 -> 3765010 | E62: =E41 -> 5220383 | F62: =F41 -> 2884288
B63: 대손상각비 | C63: =C40 -> 0 | D63: =D40 -> 1500 | E63: =E40 -> 6400 | F63: =F40 -> 0
B64: 감가상각비 | C64: =C42 -> 6570271 | D64: =D42 -> 12256754 | E64: =E42 -> 14214472 | F64: =F42 -> 7802166
B65: 지급임차료 | C65: =C43 -> 1677407 | D65: =D43 -> 1566864 | E65: =E43 -> 1861070 | F65: =F43 -> 1190181
B66: 보험료 | C66: =C44 -> 204676 | D66: =D44 -> 341832 | E66: =E44 -> 349413 | F66: =F44 -> 202866
B67: 차량유지비 | C67: =C45 -> 855248 | D67: =D45 -> 1037155 | E67: =E45 -> 1140067 | F67: =F45 -> 751149
B68: 운반비 | C68: =C46 -> 1219506 | D68: =D46 -> 193856 | E68: =E46 -> 199083 | F68: =F46 -> 130243
B69: 지급수수료 | C69: =C47 -> 4835183 | D69: =D47 -> 9360366 | E69: =E47 -> 10811345 | F69: =F47 -> 6397078
B70: 무형자산상각비 | C70: =C48 -> 751744 | D70: =D48 -> 1280700 | E70: =E48 -> 1659500 | F70: =F48 -> 922288
B71: 소모품비 | C71: =C49 -> 413477 | D71: =D49 -> 504020 | E71: =E49 -> 618270 | F71: =F49 -> 315982
B72: 위탁차량비 | C72: 0 | D72: 0 | E72: 0 | F72: 0
B73: 부품비 | C73: 0 | D73: 0 | E73: 0 | F73: 0
B74: 판매보증비 | C74: 0 | D74: 0 | E74: 0 | F74: 0
B75: 주식보상비용 | C75: =C50 -> 0 | D75: =D50 -> 0 | E75: =E50 -> 0 | F75: =F50 -> 975474
B76: 차량매각원가 | C76: 0 | D76: 0 | E76: 0 | F76: 0
B77: 기타비용 | C77: =C78-SUM(C56:C76) -> 11682769 | D77: =D78-SUM(D56:D76) -> 12707258 | E77: =E78-SUM(E56:E76) -> 14381240 | F77: =F78-SUM(F56:F76) -> 8555067
B78: 합 계 | C78: =C51 -> 62117629 | D78: =D51 -> 93996788 | E78: =E51 -> 106092958 | F78: =F51 -> 64075316
B80: 매출원가(성격별 분류)
B81: (단위 : 천원)
B82: 구 분 | C82: 2018 | D82: 2019 | E82: 2020 | F82: 2021.1H
B83: 재고자산의 변동 | C83: =C6-C56 -> 663748170 | D83: =D6-D56 -> -25034444 | E83: =E6-E56 -> -11093619 | F83: =F6-F56 -> -4234879
B84: 상품의 매입액 | C84: =C7-C57 -> 0 | D84: =D7-D57 -> 1078556109 | E84: =E7-E57 -> 1181155177 | F84: =F7-F57 -> 788348233
B85: 종업원급여 | C85: =C8-C58 -> 0 | D85: =D8-D58 -> 0 | E85: =E8-E58 -> 0 | F85: =F8-F58 -> 0
B86: 복리후생비 | C86: =C9-C59 -> 0 | D86: =D9-D59 -> 0 | E86: =E9-E59 -> 0 | F86: =F9-F59 -> 0
B87: 접대비 | C87: =C10-C60 -> 0 | D87: =D10-D60 -> 0 | E87: =E10-E60 -> 0 | F87: =F10-F60 -> 0
B88: 여비교통비 | C88: =C11-C61 -> 0 | D88: =D11-D61 -> 0 | E88: =E11-E61 -> 0 | F88: =F11-F61 -> 0
B89: 세금과공과 | C89: =C12-C62 -> 0 | D89: =D12-D62 -> 0 | E89: =E12-E62 -> 0 | F89: =F12-F62 -> 84994
B90: 대손상각비 | C90: =C13-C63 -> 0 | D90: =D13-D63 -> 0 | E90: =E13-E63 -> 0 | F90: =F13-F63 -> 0
B91: 감가상각비 | C91: =C14-C64 -> 110363 | D91: =D14-D64 -> 1 | E91: =E14-E64 -> 0 | F91: =F14-F64 -> 10999862
B92: 지급임차료 | C92: =C15-C65 -> 0 | D92: =D15-D65 -> 0 | E92: =E15-E65 -> 0 | F92: =F15-F65 -> 0
B93: 보험료 | C93: =C16-C66 -> 30725 | D93: =D16-D66 -> 0 | E93: =E16-E66 -> 0 | F93: =F16-F66 -> 1369692
B94: 차량유지비 | C94: =C17-C67 -> 0 | D94: =D17-D67 -> 0 | E94: =E17-E67 -> 0 | F94: =F17-F67 -> 20495
... B105: 합 계 | C105: =C28-C78 -> 670019633 | D105: =D28-D78 -> 1062154024 | E105: =E28-E78 -> 1179322431 | F105: =F28-F78 -> 808030709

Sheet Dart_Sales
B1: Dart_Sales | C1: Index
B4: (단위 : 백만원)
B5: 사업부문 | C5: 매출유형 | D5: 내용 | E5: 판매경로 | F5: 2018 | G5: 2019 | H5: 2020 | I5: 2021.1H
B6: 중고차사업부문 | C6: 상품매출 | D6: 차량판매 | E6: 이커머스 | F6: 155662 | G6: 284782 | H6: 408225 | I6: 322919
E7: 지점내방 | F7: 518742 | G7: 786019 | H7: 776425 | I7: 469142
E8: 경매 | F8: 47395 | G8: 76145 | H8: 92450 | I8: 65592
E9: 소계 | F9: 721799 | G9: 1146945 | H9: 1277100 | I9: 857653
C10: 용역매출 | D10: 보증 및 금융 수수료 등 | E10: 이커머스 | F10: 3536 | G10: 8426 | H10: 12754 | I10: 10354
E11: 지점내방 | F11: 12724 | G11: 21736 | H11: 23630 | I11: 13891
E12: 경매 | F12: 3151 | G12: 4821 | H12: 5599 | I12: 3580
E13: 소계 | F13: 19411 | G13: 34983 | H13: 41983 | I13: 27824
C14: 기타매출 | D14: - | E14: - | F14: 1593 | G14: 3427 | H14: 4031 | I14: 2365
C15: 중고차 사업 부문 소계 | F15: 742803 | G15: 1185355 | H15: 1323114 | I15: 887842
B16: 렌터카사업부문 | C16: 상품매출 | D16: 반납차량매각 | E16: 렌터카매각매출 | F16: 0 | G16: 0 | H16: 0 | I16: 5615
C17: 용역매출 | D17: 차량렌트 | E17: 대여매출 | F17: 0 | G17: 0 | H17: 0 | I17: 16777
C18: 기타매출 | D18: - | E18: - | F18: 0 | G18: 0 | H18: 0 | I18: 350
C19: 렌터카 사업 부문 소계 | F19: 0 | G19: 0 | H19: 0 | I19: 22742
B20: 합계 | E20: 이커머스 | F20: 159198 | G20: 293208 | H20: 420979 | I20: 333272
E21: 지점내방 | F21: 531465 | G21: 807755 | H21: 800055 | I21: 483033
E22: 경매 | F22: 50547 | G22: 80966 | H22: 98049 | I22: 69172
E23: 렌터카매각매출 | F23: 0 | G23: 0 | H23: 0 | I23: 5615
E24: 대여매출 | F24: 0 | G24: 0 | H24: 0 | I24: 16777
E25: 기타 | F25: 1593 | G25: 3427 | H25: 4031 | I25: 2715
E26: 합계 | F26: 742803 | G26: 1185355 | H26: 1323114 | I26: 910584

Sheet Dart_중고차 Sales
B1: Dart_중고차 Sales | D1: Index
B4: Dart_Sales raw
B6: 차종별 매출 | I6: 채널별 매출 | O6: 차종별 평균단가
B7: 단위 : 백만원 | D7: 2018 | E7: 2019 | F7: 2020 | G7: 2021.1H | I7: 단위 : 백만원 | J7: 2018 | K7: 2019 | L7: 2020 | M7: 2021.1H | O7: 단위 : 백만원 | P7: 2018 | Q7: 2019 | R7: 2020 | S7: 2021.1H
B8: SUV | D8: 180052 | E8: 307788 | F8: 349917 | G8: 241926 | I8: 이커머스 | J8: 155662 | K8: 284782 | L8: 408225 | M8: 322919 | O8: SUV | P8: 16621 | Q8: 15862 | R8: 16231 | S8: 18210
B9: 대형 | D9: 141538 | E9: 224434 | F9: 239466 | G9: 167954 | I9: 지점내방 | J9: 518742 | K9: 786019 | L9: 776425 | M9: 469142 | O9: 대형 | P9: 18072 | Q9: 17915 | R9: 18457 | S9: 19790
B10: 중형 | D10: 137311 | E10: 209875 | F10: 238159 | G10: 154899 | J10: =SUM(J8:J9) -> 674404 | K10: =SUM(K8:K9) -> 1070801 | L10: =SUM(L8:L9) -> 1184650 | M10: =SUM(M8:M9) -> 792061 | O10: 중형 | P10: 13067 | Q10: 12964 | R10: 13772 | S10: 15050
B11: 준중형 | D11: 94848 | E11: 132729 | F11: 150492 | G11: 91227 | I11: 채널별 판매대수 | O11: 준중형 | P11: 9344 | Q11: 9125 | R11: 9450 | S11: 10464
B12: 소형 | D12: 17121 | E12: 24045 | F12: 28903 | G12: 15782 | I12: 단위 : 대 | J12: 2018 | K12: 2019 | L12: 2020 | M12: 2021.1H | O12: 소형 | P12: 10083 | Q12: 10002 | R12: 10821 | S12: 10466
B13: 화물차 | D13: 7116 | E13: 11933 | F13: 10544 | G13: 4936 | I13: 이커머스 | J13: 12700 | K13: 22554 | L13: 31274 | M13: 22920 | O13: 화물차 | P13: 9828 | Q13: 9936 | R13: 10502 | S13: 12855
B14: 기타 | D14: 96419 | E14: 159997 | F14: 167169 | G14: 115337 | I14: 지점내방 | J14: 39496 | K14: 61774 | L14: 58875 | M14: 31506 | O14: 기타 | P14: 9251 | Q14: 8861 | R14: 8929 | S14: 9814
I16: 채널별 판매단가
I17: 판매경로 | J17: 2018 | K17: 2019 | L17: 2020 | M17: 2021.1H
I18: 이커머스 | J18: =J8*10^6/J13/1000 -> 12256.85 | K18: =K8*10^6/K13/1000 -> 12626.674 | L18: =L8*10^6/L13/1000 -> 13053.175 | M18: =M8*10^6/M13/1000 -> 14088.962
I19: 지점내방 | J19: =J9*10^6/J14/1000 -> 13134.039 | K19: =K9*10^6/K14/1000 -> 12724.107 | L19: =L9*10^6/L14/1000 -> 13187.686 | M19: =M9*10^6/M14/1000 -> 14890.561
I20: 평균단가 | J20: =SUM(J8:J9)*10^6/SUM(J13:J14)/1000 -> 12920.607 | K20: =SUM(K8:K9)*10^6/SUM(K13:K14)/1000 -> 12698.048 | L20: =SUM(L8:L9)*10^6/SUM(L13:L14)/1000 -> 13141.022 | M20: =SUM(M8:M9)*10^6/SUM(M13:M14)/1000 -> 14552.989
B22: Sales 재분류
B24: 이커머스-차종별 매출(채널별 매출) | I24: 지점내방-차종별 매출(채널별 매출)
B25: 단위 : 백만원 | D25: 2018 | E25: 2019 | F25: 2020 | G25: 2021.1H | I25: 단위 : 백만원 | K25: 2018 | L25: 2019 | M25: 2020 | N25: 2021.1H
B26: 이커머스 | C26: SUV | D26: =ROUND(J$8*D8/SUM(D$8:D$14),0) -> 41558 | E26: =ROUND(K$8*E8/SUM(E$8:E$14),0) -> 81857 | F26: =ROUND(L$8*F8/SUM(F$8:F$14),0) -> 120580 | G26: =ROUND(M$8*G8/SUM(G$8:G$14),0) -> 98632 | I26: 지점내방 | J26: SUV | K26: =ROUND(J$9*D8/SUM(D$8:D$14),0) -> 138493 | L26: =ROUND(K$9*E8/SUM(E$8:E$14),0) -> 225931 | M26: =ROUND(L$9*F8/SUM(F$8:F$14),0) -> 229337 | N26: =ROUND(M$9*G8/SUM(G$8:G$14),0) -> 143294
C27: 대형 | D27: =ROUND(J$8*D9/SUM(D$8:D$14),0) -> 32669 | E27: =ROUND(K$8*E9/SUM(E$8:E$14),0) -> 59689 | F27: =ROUND(L$8*F9/SUM(F$8:F$14),0) -> 82519 | G27: =ROUND(M$8*G9/SUM(G$8:G$14),0) -> 68474 | J27: 대형 | K27: =ROUND(J$9*D9/SUM(D$8:D$14),0) -> 108869 | L27: =ROUND(K$9*E9/SUM(E$8:E$14),0) -> 164745 | M27: =ROUND(L$9*F9/SUM(F$8:F$14),0) -> 156947 | N27: =ROUND(M$9*G9/SUM(G$8:G$14),0) -> 99480
C28: 중형 | D28: =ROUND(J$8*D10/SUM(D$8:D$14),0) -> 31693 | E28: =ROUND(K$8*E10/SUM(E$8:E$14),0) -> 55817 | F28: =ROUND(L$8*F10/SUM(F$8:F$14),0) -> 82069 | G28: =ROUND(M$8*G10/SUM(G$8:G$14),0) -> 63151 | J28: 중형 | K28: =ROUND(J$9*D10/SUM(D$8:D$14),0) -> 105618 | L28: =ROUND(K$9*E10/SUM(E$8:E$14),0) -> 154058 | M28: =ROUND(L$9*F10/SUM(F$8:F$14),0) -> 156090 | N28: =ROUND(M$9*G10/SUM(G$8:G$14),0) -> 91748
C29: 준중형 | D29: =ROUND(J$8*D11/SUM(D$8:D$14),0) -> 21892 | E29: =ROUND(K$8*E11/SUM(E$8:E$14),0) -> 35300 | F29: =ROUND(L$8*F11/SUM(F$8:F$14),0) -> 51859 | G29: =ROUND(M$8*G11/SUM(G$8:G$14),0) -> 37193 | J29: 준중형 | K29: =ROUND(J$9*D11/SUM(D$8:D$14),0) -> 72956 | L29: =ROUND(K$9*E11/SUM(E$8:E$14),0) -> 97429 | M29: =ROUND(L$9*F11/SUM(F$8:F$14),0) -> 98633 | N29: =ROUND(M$9*G11/SUM(G$8:G$14),0) -> 54034
C30: 소형 | D30: =ROUND(J$8*D12/SUM(D$8:D$14),0) -> 3952 | E30: =ROUND(K$8*E12/SUM(E$8:E$14),0) -> 6395 | F30: =ROUND(L$8*F12/SUM(F$8:F$14),0) -> 9960 | G30: =ROUND(M$8*G12/SUM(G$8:G$14),0) -> 6434 | J30: 소형 | K30: =ROUND(J$9*D12/SUM(D$8:D$14),0) -> 13169 | L30: =ROUND(K$9*E12/SUM(E$8:E$14),0) -> 17650 | M30: =ROUND(L$9*F12/SUM(F$8:F$14),0) -> 18943 | N30: =ROUND(M$9*G12/SUM(G$8:G$14),0) -> 9348
C31: 화물차 | D31: =ROUND(J$8*D13/SUM(D$8:D$14),0) -> 1642 | E31: =ROUND(K$8*E13/SUM(E$8:E$14),0) -> 3174 | F31: =ROUND(L$8*F13/SUM(F$8:F$14),0) -> 3633 | G31: =ROUND(M$8*G13/SUM(G$8:G$14),0) -> 2012 | J31: 화물차 | K31: =ROUND(J$9*D13/SUM(D$8:D$14),0) -> 5474 | L31: =ROUND(K$9*E13/SUM(E$8:E$14),0) -> 8759 | M31: =ROUND(L$9*F13/SUM(F$8:F$14),0) -> 6911 | N31: =ROUND(M$9*G13/SUM(G$8:G$14),0) -> 2924
C32: 기타 | D32: =J8-SUM(D26:D31) -> 22256 | E32: =K8-SUM(E26:E31) -> 42550 | F32: =L8-SUM(F26:F31) -> 57605 | G32: =M8-SUM(G26:G31) -> 47023 | J32: 기타 | K32: =J9-SUM(K26:K31) -> 74163 | L32: =K9-SUM(L26:L31) -> 117447 | M32: =L9-SUM(M26:M31) -> 109564 | N32: =M9-SUM(N26:N31) -> 68314
B34: 이커머스-차종별 판매대수 | I34: 지점내방-차종별 판매대수
B35: 단위 : 대 | D35: 2018 | E35: 2019 | F35: 2020 | G35: 2021.1H | I35: 단위 : 대 | K35: 2018 | L35: 2019 | M35: 2020 | N35: 2021.1H
B36: 이커머스 | C36: SUV | D36: =D26*10^6/(D47*1000) -> 2635.7336 | E36: =E26*10^6/(E47*1000) -> 5189.7434 | F36: =F26*10^6/(F47*1000) -> 7478.9905 | G36: =G26*10^6/(G47*1000) -> 5594.7556 | I36: 지점내방 | J36: SUV | K36: =K26*10^6/(K47*1000) -> 8197.0067 | L36: =L26*10^6/(L47*1000) -> 14214.367 | M36: =M26*10^6/(M47*1000) -> 14079.57 | N36: =N26*10^6/(N47*1000) -> 7690.5823
C37: 대형 | D37: =D27*10^6/(D48*1000) -> 1905.6084 | E37: =E27*10^6/(E48*1000) -> 3350.6225 | F37: =F27*10^6/(F48*1000) -> 4500.9669 | G37: =G27*10^6/(G48*1000) -> 3573.9883 | J37: 대형 | K37: =K27*10^6/(K48*1000) -> 5926.2864 | L37: =L27*10^6/(L48*1000) -> 9177.0918 | M37: =M27*10^6/(M48*1000) -> 8473.2976 | N37: =N27*10^6/(N48*1000) -> 4912.8234
C38: 중형 | D38: =D28*10^6/(D49*1000) -> 2556.769 | E38: =E28*10^6/(E49*1000) -> 4329.8762 | F38: =F28*10^6/(F49*1000) -> 5999.2244 | G38: =G28*10^6/(G49*1000) -> 4334.28 | J38: 중형 | K38: =K28*10^6/(K49*1000) -> 7951.4561 | L38: =L28*10^6/(L49*1000) -> 11859.186 | M38: =M28*10^6/(M49*1000) -> 11293.762 | N38: =N28*10^6/(N49*1000) -> 5958.0106
C39: 준중형 | D39: =D29*10^6/(D50*1000) -> 2469.7707 | E39: =E29*10^6/(E50*1000) -> 3890.3604 | F39: =F29*10^6/(F50*1000) -> 5524.6569 | G39: =G29*10^6/(G50*1000) -> 3671.4423 | J39: 준중형 | K39: =K29*10^6/(K50*1000) -> 7680.9122 | L39: =L29*10^6/(L50*1000) -> 10655.284 | M39: =M29*10^6/(M50*1000) -> 10400.423 | N39: =N29*10^6/(N50*1000) -> 5046.7356
C40: 소형 | D40: =D30*10^6/(D51*1000) -> 413.1723 | E40: =E30*10^6/(E51*1000) -> 642.98628 | F40: =F30*10^6/(F51*1000) -> 926.62694 | G40: =G30*10^6/(G51*1000) -> 634.99975 | J40: 소형 | K40: =K30*10^6/(K51*1000) -> 1284.8359 | L40: =L30*10^6/(L51*1000) -> 1761.0331 | M40: =M30*10^6/(M51*1000) -> 1744.3833 | N40: =N30*10^6/(N51*1000) -> 872.92944
C41: 화물차 | D41: =D31*10^6/(D52*1000) -> 176.12136 | E41: =E31*10^6/(E52*1000) -> 321.25016 | F41: =F31*10^6/(F52*1000) -> 348.26222 | G41: =G31*10^6/(G52*1000) -> 161.66988 | J41: 화물차 | K41: =K31*10^6/(K52*1000) -> 547.92897 | L41: =L31*10^6/(L52*1000) -> 879.73646 | M41: =M31*10^6/(M52*1000) -> 655.73661 | N41: =N31*10^6/(N52*1000) -> 222.30358
C42: 기타 | D42: =J13-SUM(D36:D41) -> 2542.8246 | E42: =K13-SUM(E36:E41) -> 4829.161 | F42: =L13-SUM(F36:F41) -> 6495.2721 | G42: =M13-SUM(G36:G41) -> 4948.8642 | J42: 기타 | K42: =J14-SUM(K36:K41) -> 7907.5738 | L42: =K14-SUM(L36:L41) -> 13227.302 | M42: =L14-SUM(M36:M41) -> 12227.828 | N42: =M14-SUM(N36:N41) -> 6802.6151
B45: 차종별 평균단가_이커머스 | I45: 차종별 평균단가_지점내방
B46: 단위 : 천원 | D46: 2018 | E46: 2019 | F46: 2020 | G46: 2021.1H | I46: 단위 : 천원 | K46: 2018 | L46: 2019 | M46: 2020 | N46: 2021.1H
B47: 이커머스 | C47: SUV | D47: =P8*(J$18/J$20) -> 15767.147 | E47: =Q8*(K$18/K$20) -> 15772.841 | F47: =R8*(L$18/L$20) -> 16122.497 | G47: =S8*(M$18/M$20) -> 17629.367 | I47: 지점내방 | J47: SUV | K47: =P8*(J$19/J$20) -> 16895.558 | L47: =Q8*(K$19/K$20) -> 15894.552 | M47: =R8*(L$19/L$20) -> 16288.636 | N47: =S8*(M$19/M$20) -> 18632.399
C48: 대형 | D48: =P9*(J$18/J$20) -> 17143.606 | E48: =Q9*(K$18/K$20) -> 17814.302 | F48: =R9*(L$18/L$20) -> 18333.616 | G48: =S9*(M$18/M$20) -> 19158.988 | J48: 대형 | K48: =P9*(J$19/J$20) -> 18370.526 | L48: =Q9*(K$19/K$20) -> 17951.765 | M48: =R9*(L$19/L$20) -> 18522.541 | N48: =S9*(M$19/M$20) -> 20249.049
C49: 중형 | D49: =P10*(J$18/J$20) -> 12395.723 | E49: =Q10*(K$18/K$20) -> 12891.131 | F49: =R10*(L$18/L$20) -> 13679.935 | G49: =S10*(M$18/M$20) -> 14570.125 | J49: 중형 | K49: =P10*(J$19/J$20) -> 13282.85 | L49: =Q10*(K$19/K$20) -> 12990.605 | M49: =R10*(L$19/L$20) -> 13820.904 | N49: =S10*(M$19/M$20) -> 15399.1
C50: 준중형 | D50: =P11*(J$18/J$20) -> 8863.9807 | E50: =Q11*(K$18/K$20) -> 9073.7094 | F50: =R11*(L$18/L$20) -> 9386.8273 | G50: =S11*(M$18/M$20) -> 10130.351 | J50: 준중형 | K50: =P11*(J$19/J$20) -> 9498.351 | L50: =Q11*(K$19/K$20) -> 9143.7265 | M50: =R11*(L$19/L$20) -> 9483.5569 | N50: =S11*(M$19/M$20) -> 10706.723
C51: 소형 | D51: =P12*(J$18/J$20) -> 9565.0168 | E51: =Q12*(K$18/K$20) -> 9945.7799 | F51: =R12*(L$18/L$20) -> 10748.662 | G51: =S12*(M$18/M$20) -> 10132.287 | J51: 소형 | K51: =P12*(J$19/J$20) -> 10249.558 | L51: =Q12*(K$19/K$20) -> 10022.526 | M51: =R12*(L$19/L$20) -> 10859.425 | N51: =S12*(M$19/M$20) -> 10708.769
C52: 화물차 | D52: =P13*(J$18/J$20) -> 9323.1166 | E52: =Q13*(K$18/K$20) -> 9880.1508 | F52: =R13*(L$18/L$20) -> 10431.795 | G52: =S13*(M$18/M$20) -> 12445.113 | J52: 화물차 | K52: =P13*(J$19/J$20) -> 9990.346 | L52: =Q13*(K$19/K$20) -> 9956.3908 | M52: =R13*(L$19/L$20) -> 10539.293 | N52: =S13*(M$19/M$20) -> 13153.185
C53: 기타 | D53: =D32*10^6/D42/1000 -> 8752.4715 | E53: =E32*10^6/E42/1000 -> 8811.0543 | F53: =F32*10^6/F42/1000 -> 8868.7585 | G53: =G32*10^6/G42/1000 -> 9501.7762 | J53: 기타 | K53: =K32*10^6/K42/1000 -> 9378.7301 | L53: =L32*10^6/L42/1000 -> 8879.1351 | M53: =M32*10^6/M42/1000 -> 8960.2179 | N53: =N32*10^6/N42/1000 -> 10042.315

Sheet Dart_Capture
A1: Dart_Captures | C1: Index
